Workbook
Name Be: [1]lists!$B$4:$B$10
Name Bu: [1]lists!$C$4:$C$31
Name Cz: [1]lists!$D$4:$D$17
Name dw: [2]lists!$D$4:$D$17
Name dwqdf: [2]lists!$C$4:$C$31
Name fedf: [2]lists!$G$4:$G$19
Name H: #REF!
Name Hu: [1]lists!$E$4:$E$10
Name I: #REF!
Name J: #REF!
Name Ka: [1]lists!$F$4:$F$19
Name Po: [1]lists!$G$4:$G$19
Name Ro: [1]lists!$H$4:$H$11
Name Ru: [1]lists!$I$4:$I$83
Name Sl: [1]lists!$J$4:$J$11
Name Slo: [1]lists!$K$4:$K$15
Name Uk: [1]lists!$L$4:$L$30

Sheet About PMR

Sheet Table of contents
B2: Table of contents
B3: About PMR
B4: Summary
B5: Poland
B6: Austria
B7: Czech Republic
B8: Greece
B9: Hungary
B10: Slovakia
B11: Croatia
B12: Vertical split
B13: Methodology
B14: Contacts details

Sheet Summary
A1: Year | B1: 2016 | C1: 2017 | D1: 2018 | E1: 2019 | F1: 2020 | G1: 2021 | H1: 2022 | I1: 2023 | J1: 2024 | K1: 2025e | L1: 2026f | M1: 2027f | N1: 2028f | O1: 2029f | P1: 2030f | R1: CAGR 2019-2024 | S1: CAGR 2025-2030
A2: Total IT market size (€ m) | B2: =B4+B6+B8 -> 31193.545 | C2: =C4+C6+C8 -> 32481.585 | D2: =D4+D6+D8 -> 34111.969 | E2: =E4+E6+E8 -> 36196.393 | F2: =F4+F6+F8 -> 36922.215 | G2: =G4+G6+G8 -> 40349.6 | H2: =H4+H6+H8 -> 43024.99 | I2: =I4+I6+I8 -> 46287.696 | ... P2: =P4+P6+P8 -> 71249.507 | R2: =(J2/D2)^(1/6)-1 -> 0.069020871 | S2: =(P2/J2)^(1/6)-1 -> 0.0576119
A3: Growth rate (%) | C3: =C2/B2-1 -> 0.041291894 | D3: =D2/C2-1 -> 0.050194079 | E3: =E2/D2-1 -> 0.061105353 | F3: =F2/E2-1 -> 0.020052342 | G3: =G2/F2-1 -> 0.09282718 | H3: =H2/G2-1 -> 0.06630523 | I3: =I2/H2-1 -> 0.075832809 | J3: =J2/I2-1 -> 0.099912987 | ... P3: =P2/O2-1 -> 0.053891031
A4: Software | B4: =Poland!B4+Austria!B4+'Czech Republic'!B4+Greece!B4+Hungary!B4+Slovakia!B4+Croatia!B4 -> 6022.6998 | C4: =Poland!C4+Austria!C4+'Czech Republic'!C4+Greece!C4+Hungary!C4+Slovakia!C4+Croatia!C4 -> 6331.3662 | D4: =Poland!D4+Austria!D4+'Czech Republic'!D4+Greece!D4+Hungary!D4+Slovakia!D4+Croatia!D4 -> 6648.8056 | E4: =Poland!E4+Austria!E4+'Czech Republic'!E4+Greece!E4+Hungary!E4+Slovakia!E4+Croatia!E4 -> 7057.8692 | F4: =Poland!F4+Austria!F4+'Czech Republic'!F4+Greece!F4+Hungary!F4+Slovakia!F4+Croatia!F4 -> 7366.2936 | G4: =Poland!G4+Austria!G4+'Czech Republic'!G4+Greece!G4+Hungary!G4+Slovakia!G4+Croatia!G4 -> 7780.2696 | H4: =Poland!H4+Austria!H4+'Czech Republic'!H4+Greece!H4+Hungary!H4+Slovakia!H4+Croatia!H4 -> 8294.5214 | I4: =Poland!I4+Austria!I4+'Czech Republic'!I4+Greece!I4+Hungary!I4+Slovakia!I4+Croatia!I4 -> 9130.7545 | ... P4: =Poland!P4+Austria!P4+'Czech Republic'!P4+Greece!P4+Hungary!P4+Slovakia!P4+Croatia!P4 -> 15041.211 | R4: =(J4/D4)^(1/6)-1 -> 0.072809641 | S4: =(P4/J4)^(1/6)-1 -> 0.067990016
A5: Growth rate (%) | C5: =C4/B4-1 -> 0.051250511 | D5: =D4/C4-1 -> 0.050137591 | E5: =E4/D4-1 -> 0.061524372 | F5: =F4/E4-1 -> 0.043699358 | G5: =G4/F4-1 -> 0.056198686 | H5: =H4/G4-1 -> 0.066096906 | I5: =I4/H4-1 -> 0.10081753 | J5: =J4/I4-1 -> 0.1101278 | ... P5: =P4/O4-1 -> 0.066949335
A6: Hardware | B6: =Poland!B6+Austria!B6+'Czech Republic'!B6+Greece!B6+Hungary!B6+Slovakia!B6+Croatia!B6 -> 13086.818 | C6: =Poland!C6+Austria!C6+'Czech Republic'!C6+Greece!C6+Hungary!C6+Slovakia!C6+Croatia!C6 -> 13603.741 | D6: =Poland!D6+Austria!D6+'Czech Republic'!D6+Greece!D6+Hungary!D6+Slovakia!D6+Croatia!D6 -> 14433.702 | E6: =Poland!E6+Austria!E6+'Czech Republic'!E6+Greece!E6+Hungary!E6+Slovakia!E6+Croatia!E6 -> 15434.475 | F6: =Poland!F6+Austria!F6+'Czech Republic'!F6+Greece!F6+Hungary!F6+Slovakia!F6+Croatia!F6 -> 15654.028 | G6: =Poland!G6+Austria!G6+'Czech Republic'!G6+Greece!G6+Hungary!G6+Slovakia!G6+Croatia!G6 -> 18039.267 | H6: =Poland!H6+Austria!H6+'Czech Republic'!H6+Greece!H6+Hungary!H6+Slovakia!H6+Croatia!H6 -> 19105.111 | I6: =Poland!I6+Austria!I6+'Czech Republic'!I6+Greece!I6+Hungary!I6+Slovakia!I6+Croatia!I6 -> 20072.67 | ... P6: =Poland!P6+Austria!P6+'Czech Republic'!P6+Greece!P6+Hungary!P6+Slovakia!P6+Croatia!P6 -> 27882.995 | R6: =(J6/D6)^(1/6)-1 -> 0.072470336 | S6: =(P6/J6)^(1/6)-1 -> 0.04057884
A7: Growth rate (%) | C7: =C6/B6-1 -> 0.039499488 | D7: =D6/C6-1 -> 0.061009808 | E7: =E6/D6-1 -> 0.069335823 | F7: =F6/E6-1 -> 0.014224841 | G7: =G6/F6-1 -> 0.15237223 | H7: =H6/G6-1 -> 0.05908467 | I7: =I6/H6-1 -> 0.050643973 | J7: =J6/I6-1 -> 0.094168814 | ... P7: =P6/O6-1 -> 0.030646586
A8: Services | B8: =Poland!B8+Austria!B8+'Czech Republic'!B8+Greece!B8+Hungary!B8+Slovakia!B8+Croatia!B8 -> 12084.027 | C8: =Poland!C8+Austria!C8+'Czech Republic'!C8+Greece!C8+Hungary!C8+Slovakia!C8+Croatia!C8 -> 12546.478 | D8: =Poland!D8+Austria!D8+'Czech Republic'!D8+Greece!D8+Hungary!D8+Slovakia!D8+Croatia!D8 -> 13029.461 | E8: =Poland!E8+Austria!E8+'Czech Republic'!E8+Greece!E8+Hungary!E8+Slovakia!E8+Croatia!E8 -> 13704.048 | F8: =Poland!F8+Austria!F8+'Czech Republic'!F8+Greece!F8+Hungary!F8+Slovakia!F8+Croatia!F8 -> 13901.893 | G8: =Poland!G8+Austria!G8+'Czech Republic'!G8+Greece!G8+Hungary!G8+Slovakia!G8+Croatia!G8 -> 14530.063 | H8: =Poland!H8+Austria!H8+'Czech Republic'!H8+Greece!H8+Hungary!H8+Slovakia!H8+Croatia!H8 -> 15625.357 | I8: =Poland!I8+Austria!I8+'Czech Republic'!I8+Greece!I8+Hungary!I8+Slovakia!I8+Croatia!I8 -> 17084.271 | ... P8: =Poland!P8+Austria!P8+'Czech Republic'!P8+Greece!P8+Hungary!P8+Slovakia!P8+Croatia!P8 -> 28325.3 | R8: =(J8/D8)^(1/6)-1 -> 0.063137749 | S8: =(P8/J8)^(1/6)-1 -> 0.070578397
A9: Growth rate (%) | C9: =C8/B8-1 -> 0.038269653 | D9: =D8/C8-1 -> 0.03849544 | E9: =E8/D8-1 -> 0.051774027 | F9: =F8/E8-1 -> 0.014436985 | G9: =G8/F8-1 -> 0.045185921 | H9: =H8/G8-1 -> 0.075381199 | I9: =I8/H8-1 -> 0.093368361 | J9: =J8/I8-1 -> 0.10120259 | ... P9: =P8/O8-1 -> 0.070703234
A11: Smartphones market size (€ m) | B11: =Poland!B11+Austria!B11+'Czech Republic'!B11+Greece!B11+Hungary!B11+Slovakia!B11+Croatia!B11 -> 5000.2985 | C11: =Poland!C11+Austria!C11+'Czech Republic'!C11+Greece!C11+Hungary!C11+Slovakia!C11+Croatia!C11 -> 5198.2324 | D11: =Poland!D11+Austria!D11+'Czech Republic'!D11+Greece!D11+Hungary!D11+Slovakia!D11+Croatia!D11 -> 5562.3409 | E11: =Poland!E11+Austria!E11+'Czech Republic'!E11+Greece!E11+Hungary!E11+Slovakia!E11+Croatia!E11 -> 6050.2573 | F11: =Poland!F11+Austria!F11+'Czech Republic'!F11+Greece!F11+Hungary!F11+Slovakia!F11+Croatia!F11 -> 5291.2075 | G11: =Poland!G11+Austria!G11+'Czech Republic'!G11+Greece!G11+Hungary!G11+Slovakia!G11+Croatia!G11 -> 6685.3091 | H11: =Poland!H11+Austria!H11+'Czech Republic'!H11+Greece!H11+Hungary!H11+Slovakia!H11+Croatia!H11 -> 6946.8631 | I11: =Poland!I11+Austria!I11+'Czech Republic'!I11+Greece!I11+Hungary!I11+Slovakia!I11+Croatia!I11 -> 7116.1743 | ... P11: =Poland!P11+Austria!P11+'Czech Republic'!P11+Greece!P11+Hungary!P11+Slovakia!P11+Croatia!P11 -> 9115.502 | R11: =(J11/D11)^(1/6)-1 -> 0.053236256 | S11: =(P11/J11)^(1/6)-1 -> 0.030927277
A12: Growth rate (%) | C12: =C11/B11-1 -> 0.039584403 | D12: =D11/C11-1 -> 0.070044685 | E12: =E11/D11-1 -> 0.087717814 | F12: =F11/E11-1 -> -0.12545744 | G12: =G11/F11-1 -> 0.26347513 | H12: =H11/G11-1 -> 0.039123683 | I12: =I11/H11-1 -> 0.024372333 | J12: =J11/I11-1 -> 0.067003467 | ... P12: =P11/O11-1 -> 0.021299493
A14: Cybersecurity market size (€ m) | B14: =Poland!B14+Austria!B14+'Czech Republic'!B14+Greece!B14+Hungary!B14+Slovakia!B14+Croatia!B14 -> 868.22291 | C14: =Poland!C14+Austria!C14+'Czech Republic'!C14+Greece!C14+Hungary!C14+Slovakia!C14+Croatia!C14 -> 951.50134 | D14: =Poland!D14+Austria!D14+'Czech Republic'!D14+Greece!D14+Hungary!D14+Slovakia!D14+Croatia!D14 -> 1073.345 | E14: =Poland!E14+Austria!E14+'Czech Republic'!E14+Greece!E14+Hungary!E14+Slovakia!E14+Croatia!E14 -> 1170.9903 | F14: =Poland!F14+Austria!F14+'Czech Republic'!F14+Greece!F14+Hungary!F14+Slovakia!F14+Croatia!F14 -> 1182.537 | G14: =Poland!G14+Austria!G14+'Czech Republic'!G14+Greece!G14+Hungary!G14+Slovakia!G14+Croatia!G14 -> 1271.5908 | H14: =Poland!H14+Austria!H14+'Czech Republic'!H14+Greece!H14+Hungary!H14+Slovakia!H14+Croatia!H14 -> 1465.6583 | I14: =Poland!I14+Austria!I14+'Czech Republic'!I14+Greece!I14+Hungary!I14+Slovakia!I14+Croatia!I14 -> 1645.9208 | ... P14: =Poland!P14+Austria!P14+'Czech Republic'!P14+Greece!P14+Hungary!P14+Slovakia!P14+Croatia!P14 -> 2930.1344 | R14: =(J14/D14)^(1/6)-1 -> 0.093405396 | S14: =(P14/J14)^(1/6)-1 -> 0.081210259
A15: Growth rate (%) | C15: =C14/B14-1 -> 0.095918259 | D15: =D14/C14-1 -> 0.12805407 | E15: =E14/D14-1 -> 0.090972974 | F15: =F14/E14-1 -> 0.009860593 | G15: =G14/F14-1 -> 0.075307376 | H15: =H14/G14-1 -> 0.15261794 | I15: =I14/H14-1 -> 0.1229908 | J15: =J14/I14-1 -> 0.11433985 | ... P15: =P14/O14-1 -> 0.079120666
A17: Enterprises (by size) (number of enterprises in thousands)
A18: Microenterprises (0-9 employees) | B18: =Poland!B18+Austria!B18+'Czech Republic'!B18+Greece!B18+Hungary!B18+Slovakia!B18+Croatia!B18 -> 3838.5999 | C18: =Poland!C18+Austria!C18+'Czech Republic'!C18+Greece!C18+Hungary!C18+Slovakia!C18+Croatia!C18 -> 3830.8917 | D18: =Poland!D18+Austria!D18+'Czech Republic'!D18+Greece!D18+Hungary!D18+Slovakia!D18+Croatia!D18 -> 3878.4667 | E18: =Poland!E18+Austria!E18+'Czech Republic'!E18+Greece!E18+Hungary!E18+Slovakia!E18+Croatia!E18 -> 4016.7657 | F18: =Poland!F18+Austria!F18+'Czech Republic'!F18+Greece!F18+Hungary!F18+Slovakia!F18+Croatia!F18 -> 4069.4619 | G18: =Poland!G18+Austria!G18+'Czech Republic'!G18+Greece!G18+Hungary!G18+Slovakia!G18+Croatia!G18 -> 4306.4773 | H18: =Poland!H18+Austria!H18+'Czech Republic'!H18+Greece!H18+Hungary!H18+Slovakia!H18+Croatia!H18 -> 4497.7475 | I18: =Poland!I18+Austria!I18+'Czech Republic'!I18+Greece!I18+Hungary!I18+Slovakia!I18+Croatia!I18 -> 4521.2448 | ... P18: =Poland!P18+Austria!P18+'Czech Republic'!P18+Greece!P18+Hungary!P18+Slovakia!P18+Croatia!P18 -> 4920.1701 | R18: =(J18/D18)^(1/6)-1 -> 0.027111084 | S18: =(P18/J18)^(1/6)-1 -> 0.012984014
A19: Growth rate (%) | C19: =C18/B18-1 -> -0.0020080644 | D19: =D18/C18-1 -> 0.012418787 | E19: =E18/D18-1 -> 0.035658163 | F19: =F18/E18-1 -> 0.013119048 | G19: =G18/F18-1 -> 0.058242462 | H19: =H18/G18-1 -> 0.044414526 | I19: =I18/H18-1 -> 0.0052242439 | J19: =J18/I18-1 -> 0.0071787225 | ... P19: =P18/O18-1 -> 0.011609494
A20: SME (10-249 employees) | B20: =Poland!B20+Austria!B20+'Czech Republic'!B20+Greece!B20+Hungary!B20+Slovakia!B20+Croatia!B20 -> 310.09102 | C20: =Poland!C20+Austria!C20+'Czech Republic'!C20+Greece!C20+Hungary!C20+Slovakia!C20+Croatia!C20 -> 320.00879 | D20: =Poland!D20+Austria!D20+'Czech Republic'!D20+Greece!D20+Hungary!D20+Slovakia!D20+Croatia!D20 -> 326.92679 | E20: =Poland!E20+Austria!E20+'Czech Republic'!E20+Greece!E20+Hungary!E20+Slovakia!E20+Croatia!E20 -> 333.34971 | F20: =Poland!F20+Austria!F20+'Czech Republic'!F20+Greece!F20+Hungary!F20+Slovakia!F20+Croatia!F20 -> 322.31785 | G20: =Poland!G20+Austria!G20+'Czech Republic'!G20+Greece!G20+Hungary!G20+Slovakia!G20+Croatia!G20 -> 338.63737 | H20: =Poland!H20+Austria!H20+'Czech Republic'!H20+Greece!H20+Hungary!H20+Slovakia!H20+Croatia!H20 -> 345.76303 | I20: =Poland!I20+Austria!I20+'Czech Republic'!I20+Greece!I20+Hungary!I20+Slovakia!I20+Croatia!I20 -> 349.09182 | ... P20: =Poland!P20+Austria!P20+'Czech Republic'!P20+Greece!P20+Hungary!P20+Slovakia!P20+Croatia!P20 -> 378.64304 | R20: =(J20/D20)^(1/6)-1 -> 0.012659029 | S20: =(P20/J20)^(1/6)-1 -> 0.011967752
A21: Growth rate (%) | C21: =C20/B20-1 -> 0.031983414 | D21: =D20/C20-1 -> 0.021618153 | E21: =E20/D20-1 -> 0.019646351 | F21: =F20/E20-1 -> -0.033093959 | G21: =G20/F20-1 -> 0.050631769 | H21: =H20/G20-1 -> 0.021042145 | I21: =I20/H20-1 -> 0.009627378 | J21: =J20/I20-1 -> 0.0099276833 | ... P21: =P20/O20-1 -> 0.0088050583
A22: Large enterprises (250+ employees) | B22: =Poland!B22+Austria!B22+'Czech Republic'!B22+Greece!B22+Hungary!B22+Slovakia!B22+Croatia!B22 -> 9.7070413 | C22: =Poland!C22+Austria!C22+'Czech Republic'!C22+Greece!C22+Hungary!C22+Slovakia!C22+Croatia!C22 -> 10.05411 | D22: =Poland!D22+Austria!D22+'Czech Republic'!D22+Greece!D22+Hungary!D22+Slovakia!D22+Croatia!D22 -> 10.386775 | E22: =Poland!E22+Austria!E22+'Czech Republic'!E22+Greece!E22+Hungary!E22+Slovakia!E22+Croatia!E22 -> 10.464251 | F22: =Poland!F22+Austria!F22+'Czech Republic'!F22+Greece!F22+Hungary!F22+Slovakia!F22+Croatia!F22 -> 10.137901 | G22: =Poland!G22+Austria!G22+'Czech Republic'!G22+Greece!G22+Hungary!G22+Slovakia!G22+Croatia!G22 -> 10.43184 | H22: =Poland!H22+Austria!H22+'Czech Republic'!H22+Greece!H22+Hungary!H22+Slovakia!H22+Croatia!H22 -> 10.690449 | I22: =Poland!I22+Austria!I22+'Czech Republic'!I22+Greece!I22+Hungary!I22+Slovakia!I22+Croatia!I22 -> 10.720171 | ... P22: =Poland!P22+Austria!P22+'Czech Republic'!P22+Greece!P22+Hungary!P22+Slovakia!P22+Croatia!P22 -> 11.637745 | R22: =(J22/D22)^(1/6)-1 -> 0.0074795473 | S22: =(P22/J22)^(1/6)-1 -> 0.011568068
A23: Growth rate (%) | C23: =C22/B22-1 -> 0.035754301 | D23: =D22/C22-1 -> 0.033087528 | E23: =E22/D22-1 -> 0.0074590316 | F23: =F22/E22-1 -> -0.031187095 | G23: =G22/F22-1 -> 0.028994079 | H23: =H22/G22-1 -> 0.024790296 | I23: =I22/H22-1 -> 0.0027802645 | J23: =J22/I22-1 -> 0.013202989 | ... P23: =P22/O22-1 -> 0.0080935043
A24: Number of all enterprises | B24: =B18+B20+B22 -> 4158.3979 | C24: =C18+C20+C22 -> 4160.9546 | D24: =D18+D20+D22 -> 4215.7803 | E24: =E18+E20+E22 -> 4360.5797 | F24: =F18+F20+F22 -> 4401.9176 | G24: =G18+G20+G22 -> 4655.5465 | H24: =H18+H20+H22 -> 4854.201 | I24: =I18+I20+I22 -> 4881.0568 | ... P24: =P18+P20+P22 -> 5310.4509 | R24: =(J24/D24)^(1/6)-1 -> 0.025979818 | S24: =(P24/J24)^(1/6)-1 -> 0.0129082
A25: Growth rate (%) | C25: =C24/B24-1 -> 0.00061482392 | D25: =D24/C24-1 -> 0.013176229 | E25: =E24/D24-1 -> 0.034346997 | F25: =F24/E24-1 -> 0.009479916 | G25: =G24/F24-1 -> 0.05761783 | H25: =H24/G24-1 -> 0.042670482 | I25: =I24/H24-1 -> 0.0055324952 | J25: =J24/I24-1 -> 0.0073885584 | ... P25: =P24/O24-1 -> 0.011401288
A27: Percentage of enterprises using cloud computing
A28: Percent of microenterprises using cloud computing | B28: =B34/B18 -> 0.069345581 | C28: =C34/C18 -> 0.080986551 | D28: =D34/D18 -> 0.094503563 | E28: =E34/E18 -> 0.11065462 | F28: =F34/F18 -> 0.12932043 | G28: =G34/G18 -> 0.15169014 | H28: =H34/H18 -> 0.17747194 | I28: =I34/I18 -> 0.20707046 | ... P28: =P34/P18 -> 0.4752687
A29: Percent of SME using cloud computing | B29: =B36/B20 -> 0.11488284 | C29: =C36/C20 -> 0.14059932 | D29: =D36/D20 -> 0.1716105 | E29: =E36/E20 -> 0.20958246 | F29: =F36/F20 -> 0.25564668 | G29: =G36/G20 -> 0.30822647 | H29: =H36/H20 -> 0.36628783 | I29: =I36/I20 -> 0.42772883 | ... P29: =P36/P20 -> 0.78252853
A30: Percent of large enterprises using cloud computing | B30: =B38/B22 -> 0.28914034 | C30: =C38/C22 -> 0.36528339 | D30: =D38/D22 -> 0.44965655 | E30: =E38/E22 -> 0.53705933 | F30: =F38/F22 -> 0.62258108 | G30: =G38/G22 -> 0.69883238 | H30: =H38/H22 -> 0.7637952 | I30: =I38/I22 -> 0.81625577 | ... P30: =P38/P22 -> 0.96813844
A31: Percent of all enterprises using cloud computing | B31: =B40/B24 -> 0.073254359 | C31: =C40/C24 -> 0.086258168 | D31: =D40/D24 -> 0.1013581 | E31: =E40/E24 -> 0.11924054 | F31: =F40/F24 -> 0.13970632 | G31: =G40/G24 -> 0.16430235 | H31: =H40/H24 -> 0.19221249 | I31: =I40/I24 -> 0.22418983 | ... P31: =P40/P24 -> 0.49825689
A33: Number of enterprises using cloud computing (thousands)
A34: Number of microenterprises using cloud computing | B34: =Poland!B34+Austria!B34+'Czech Republic'!B34+Greece!B34+Hungary!B34+Slovakia!B34+Croatia!B34 -> 266.18994 | C34: =Poland!C34+Austria!C34+'Czech Republic'!C34+Greece!C34+Hungary!C34+Slovakia!C34+Croatia!C34 -> 310.2507 | D34: =Poland!D34+Austria!D34+'Czech Republic'!D34+Greece!D34+Hungary!D34+Slovakia!D34+Croatia!D34 -> 366.52892 | E34: =Poland!E34+Austria!E34+'Czech Republic'!E34+Greece!E34+Hungary!E34+Slovakia!E34+Croatia!E34 -> 444.4737 | F34: =Poland!F34+Austria!F34+'Czech Republic'!F34+Greece!F34+Hungary!F34+Slovakia!F34+Croatia!F34 -> 526.26456 | G34: =Poland!G34+Austria!G34+'Czech Republic'!G34+Greece!G34+Hungary!G34+Slovakia!G34+Croatia!G34 -> 653.25014 | H34: =Poland!H34+Austria!H34+'Czech Republic'!H34+Greece!H34+Hungary!H34+Slovakia!H34+Croatia!H34 -> 798.22396 | I34: =Poland!I34+Austria!I34+'Czech Republic'!I34+Greece!I34+Hungary!I34+Slovakia!I34+Croatia!I34 -> 936.21625 | ... P34: =Poland!P34+Austria!P34+'Czech Republic'!P34+Greece!P34+Hungary!P34+Slovakia!P34+Croatia!P34 -> 2338.4028 | R34: =(J34/D34)^(1/6)-1 -> 0.19980327 | S34: =(P34/J34)^(1/6)-1 -> 0.13507652
A35: Growth rate (%) | C35: =C34/B34-1 -> 0.16552378 | D35: =D34/C34-1 -> 0.18139595 | E35: =E34/D34-1 -> 0.21265655 | F35: =F34/E34-1 -> 0.18401732 | G35: =G34/F34-1 -> 0.2412961 | H35: =H34/G34-1 -> 0.22192696 | I35: =I34/H34-1 -> 0.17287415 | J35: =J34/I34-1 -> 0.16786412 | ... P35: =P34/O34-1 -> 0.10139376
A36: Number of SME using cloud computing | B36: =Poland!B36+Austria!B36+'Czech Republic'!B36+Greece!B36+Hungary!B36+Slovakia!B36+Croatia!B36 -> 35.624136 | C36: =Poland!C36+Austria!C36+'Czech Republic'!C36+Greece!C36+Hungary!C36+Slovakia!C36+Croatia!C36 -> 44.993018 | D36: =Poland!D36+Austria!D36+'Czech Republic'!D36+Greece!D36+Hungary!D36+Slovakia!D36+Croatia!D36 -> 56.104069 | E36: =Poland!E36+Austria!E36+'Czech Republic'!E36+Greece!E36+Hungary!E36+Slovakia!E36+Croatia!E36 -> 69.864252 | F36: =Poland!F36+Austria!F36+'Czech Republic'!F36+Greece!F36+Hungary!F36+Slovakia!F36+Croatia!F36 -> 82.399486 | G36: =Poland!G36+Austria!G36+'Czech Republic'!G36+Greece!G36+Hungary!G36+Slovakia!G36+Croatia!G36 -> 104.377 | H36: =Poland!H36+Austria!H36+'Czech Republic'!H36+Greece!H36+Hungary!H36+Slovakia!H36+Croatia!H36 -> 126.64879 | I36: =Poland!I36+Austria!I36+'Czech Republic'!I36+Greece!I36+Hungary!I36+Slovakia!I36+Croatia!I36 -> 149.31663 | ... P36: =Poland!P36+Austria!P36+'Czech Republic'!P36+Greece!P36+Hungary!P36+Slovakia!P36+Croatia!P36 -> 296.29898 | R36: =(J36/D36)^(1/6)-1 -> 0.20650805 | S36: =(P36/J36)^(1/6)-1 -> 0.093769333
A37: Growth rate (%) | C37: =C36/B36-1 -> 0.26299255 | D37: =D36/C36-1 -> 0.24695055 | E37: =E36/D36-1 -> 0.24526177 | F37: =F36/E36-1 -> 0.17942271 | G37: =G36/F36-1 -> 0.26671907 | H37: =H36/G36-1 -> 0.21337832 | I37: =I36/H36-1 -> 0.17898193 | J37: =J36/I36-1 -> 0.15895752 | ... P37: =P36/O36-1 -> 0.054589469
A38: Number of large enterprises using cloud computing | B38: =Poland!B38+Austria!B38+'Czech Republic'!B38+Greece!B38+Hungary!B38+Slovakia!B38+Croatia!B38 -> 2.8066973 | C38: =Poland!C38+Austria!C38+'Czech Republic'!C38+Greece!C38+Hungary!C38+Slovakia!C38+Croatia!C38 -> 3.6725994 | D38: =Poland!D38+Austria!D38+'Czech Republic'!D38+Greece!D38+Hungary!D38+Slovakia!D38+Croatia!D38 -> 4.6704816 | E38: =Poland!E38+Austria!E38+'Czech Republic'!E38+Greece!E38+Hungary!E38+Slovakia!E38+Croatia!E38 -> 5.6199235 | F38: =Poland!F38+Austria!F38+'Czech Republic'!F38+Greece!F38+Hungary!F38+Slovakia!F38+Croatia!F38 -> 6.3116654 | G38: =Poland!G38+Austria!G38+'Czech Republic'!G38+Greece!G38+Hungary!G38+Slovakia!G38+Croatia!G38 -> 7.2901078 | H38: =Poland!H38+Austria!H38+'Czech Republic'!H38+Greece!H38+Hungary!H38+Slovakia!H38+Croatia!H38 -> 8.1653134 | I38: =Poland!I38+Austria!I38+'Czech Republic'!I38+Greece!I38+Hungary!I38+Slovakia!I38+Croatia!I38 -> 8.7504014 | ... P38: =Poland!P38+Austria!P38+'Czech Republic'!P38+Greece!P38+Hungary!P38+Slovakia!P38+Croatia!P38 -> 11.266948 | R38: =(J38/D38)^(1/6)-1 -> 0.12214367 | S38: =(P38/J38)^(1/6)-1 -> 0.032029975
A39: Growth rate (%) | C39: =C38/B38-1 -> 0.30851283 | D39: =D38/C38-1 -> 0.27171008 | E39: =E38/D38-1 -> 0.20328564 | F39: =F38/E38-1 -> 0.12308744 | G39: =G38/F38-1 -> 0.15502127 | H39: =H38/G38-1 -> 0.12005386 | I39: =I38/H38-1 -> 0.071655303 | J39: =J38/I38-1 -> 0.06567423 | ... P39: =P38/O38-1 -> 0.016677752
A40: Number of all enterprises using cloud computing | B40: =B38+B36+B34 -> 304.62077 | C40: =C38+C36+C34 -> 358.91632 | D40: =D38+D36+D34 -> 427.30347 | E40: =E38+E36+E34 -> 519.95787 | F40: =F38+F36+F34 -> 614.97571 | G40: =G38+G36+G34 -> 764.91725 | H40: =H38+H36+H34 -> 933.03806 | I40: =I38+I36+I34 -> 1094.2833 | ... P40: =P38+P36+P34 -> 2645.9688 | R40: =(J40/D40)^(1/6)-1 -> 0.19997315 | S40: =(P40/J40)^(1/6)-1 -> 0.12928403
A41: Growth rate (%) | C41: =C40/B40-1 -> 0.17823981 | D41: =D40/C40-1 -> 0.19053788 | E41: =E40/D40-1 -> 0.21683512 | F41: =F40/E40-1 -> 0.1827414 | G41: =G40/F40-1 -> 0.24381701 | H41: =H40/G40-1 -> 0.21978955 | I41: =I40/H40-1 -> 0.17281741 | J41: =J40/I40-1 -> 0.16583164 | ... P41: =P40/O40-1 -> 0.095560211
A43: Total cloud computing market size (€ m) | B43: =B55+B111 -> 604.40326 | C43: =C55+C111 -> 766.58844 | D43: =D55+D111 -> 982.41971 | E43: =E55+E111 -> 1269.0813 | F43: =F55+F111 -> 1571.7157 | G43: =G55+G111 -> 1986.9813 | H43: =H55+H111 -> 2520.7643 | I43: =I55+I111 -> 3147.438 | ... P43: =P55+P111 -> 10331.793 | R43: =(J43/D43)^(1/6)-1 -> 0.2571425 | S43: =(P43/J43)^(1/6)-1 -> 0.17741237
A44: Growth rate (%) | C44: =C43/B43-1 -> 0.26833935 | D44: =D43/C43-1 -> 0.28154778 | E44: =E43/D43-1 -> 0.29179137 | F44: =F43/E43-1 -> 0.23846731 | G44: =G43/F43-1 -> 0.26421164 | H44: =H43/G43-1 -> 0.26864016 | I44: =I43/H43-1 -> 0.24860464 | J44: =J43/I43-1 -> 0.2321028 | ... P44: =P43/O43-1 -> 0.14426293
A46: Public cloud (by size of enterprises) (€ m)
A47: Microenterprises (0-9 employees) | B47: =Poland!B47+Austria!B47+'Czech Republic'!B47+Greece!B47+Hungary!B47+Slovakia!B47+Croatia!B47 -> 25.879968 | C47: =Poland!C47+Austria!C47+'Czech Republic'!C47+Greece!C47+Hungary!C47+Slovakia!C47+Croatia!C47 -> 34.085921 | D47: =Poland!D47+Austria!D47+'Czech Republic'!D47+Greece!D47+Hungary!D47+Slovakia!D47+Croatia!D47 -> 46.673206 | E47: =Poland!E47+Austria!E47+'Czech Republic'!E47+Greece!E47+Hungary!E47+Slovakia!E47+Croatia!E47 -> 62.866763 | F47: =Poland!F47+Austria!F47+'Czech Republic'!F47+Greece!F47+Hungary!F47+Slovakia!F47+Croatia!F47 -> 84.479821 | G47: =Poland!G47+Austria!G47+'Czech Republic'!G47+Greece!G47+Hungary!G47+Slovakia!G47+Croatia!G47 -> 113.68498 | H47: =Poland!H47+Austria!H47+'Czech Republic'!H47+Greece!H47+Hungary!H47+Slovakia!H47+Croatia!H47 -> 155.24631 | I47: =Poland!I47+Austria!I47+'Czech Republic'!I47+Greece!I47+Hungary!I47+Slovakia!I47+Croatia!I47 -> 202.1687 | ... P47: =Poland!P47+Austria!P47+'Czech Republic'!P47+Greece!P47+Hungary!P47+Slovakia!P47+Croatia!P47 -> 921.32627 | R47: =(J47/D47)^(1/6)-1 -> 0.33144533 | S47: =(P47/J47)^(1/6)-1 -> 0.23471757
A48: Growth rate (%) | C48: =C47/B47-1 -> 0.31707736 | D48: =D47/C47-1 -> 0.36928109 | E48: =E47/D47-1 -> 0.34695615 | F48: =F47/E47-1 -> 0.34379149 | G48: =G47/F47-1 -> 0.34570575 | H48: =H47/G47-1 -> 0.36558325 | I48: =I47/H47-1 -> 0.30224481 | J48: =J47/I47-1 -> 0.28615634 | ... P48: =P47/O47-1 -> 0.19307867
A49: SME (10-249 employees) | B49: =Poland!B49+Austria!B49+'Czech Republic'!B49+Greece!B49+Hungary!B49+Slovakia!B49+Croatia!B49 -> 341.41786 | C49: =Poland!C49+Austria!C49+'Czech Republic'!C49+Greece!C49+Hungary!C49+Slovakia!C49+Croatia!C49 -> 419.18141 | D49: =Poland!D49+Austria!D49+'Czech Republic'!D49+Greece!D49+Hungary!D49+Slovakia!D49+Croatia!D49 -> 522.9079 | E49: =Poland!E49+Austria!E49+'Czech Republic'!E49+Greece!E49+Hungary!E49+Slovakia!E49+Croatia!E49 -> 662.4666 | F49: =Poland!F49+Austria!F49+'Czech Republic'!F49+Greece!F49+Hungary!F49+Slovakia!F49+Croatia!F49 -> 808.77643 | G49: =Poland!G49+Austria!G49+'Czech Republic'!G49+Greece!G49+Hungary!G49+Slovakia!G49+Croatia!G49 -> 999.28781 | H49: =Poland!H49+Austria!H49+'Czech Republic'!H49+Greece!H49+Hungary!H49+Slovakia!H49+Croatia!H49 -> 1237.3658 | I49: =Poland!I49+Austria!I49+'Czech Republic'!I49+Greece!I49+Hungary!I49+Slovakia!I49+Croatia!I49 -> 1511.5319 | ... P49: =Poland!P49+Austria!P49+'Czech Republic'!P49+Greece!P49+Hungary!P49+Slovakia!P49+Croatia!P49 -> 4157.1798 | R49: =(J49/D49)^(1/6)-1 -> 0.2310572 | S49: =(P49/J49)^(1/6)-1 -> 0.14758281
A50: Growth rate (%) | C50: =C49/B49-1 -> 0.2277665 | D50: =D49/C49-1 -> 0.24745013 | E50: =E49/D49-1 -> 0.26688965 | F50: =F49/E49-1 -> 0.22085615 | G50: =G49/F49-1 -> 0.23555507 | H50: =H49/G49-1 -> 0.23824763 | I50: =I49/H49-1 -> 0.22157242 | J50: =J49/I49-1 -> 0.20414085 | ... P50: =P49/O49-1 -> 0.1150985
A51: Large enterprises (250+ employees) | B51: =Poland!B51+Austria!B51+'Czech Republic'!B51+Greece!B51+Hungary!B51+Slovakia!B51+Croatia!B51 -> 56.387564 | C51: =Poland!C51+Austria!C51+'Czech Republic'!C51+Greece!C51+Hungary!C51+Slovakia!C51+Croatia!C51 -> 79.998903 | D51: =Poland!D51+Austria!D51+'Czech Republic'!D51+Greece!D51+Hungary!D51+Slovakia!D51+Croatia!D51 -> 112.87606 | E51: =Poland!E51+Austria!E51+'Czech Republic'!E51+Greece!E51+Hungary!E51+Slovakia!E51+Croatia!E51 -> 157.53596 | F51: =Poland!F51+Austria!F51+'Czech Republic'!F51+Greece!F51+Hungary!F51+Slovakia!F51+Croatia!F51 -> 211.58765 | G51: =Poland!G51+Austria!G51+'Czech Republic'!G51+Greece!G51+Hungary!G51+Slovakia!G51+Croatia!G51 -> 291.64161 | H51: =Poland!H51+Austria!H51+'Czech Republic'!H51+Greece!H51+Hungary!H51+Slovakia!H51+Croatia!H51 -> 394.67277 | I51: =Poland!I51+Austria!I51+'Czech Republic'!I51+Greece!I51+Hungary!I51+Slovakia!I51+Croatia!I51 -> 520.95688 | ... P51: =Poland!P51+Austria!P51+'Czech Republic'!P51+Greece!P51+Hungary!P51+Slovakia!P51+Croatia!P51 -> 2383.5963 | R51: =(J51/D51)^(1/6)-1 -> 0.34796439 | S51: =(P51/J51)^(1/6)-1 -> 0.23337003
A52: Growth rate (%) | C52: =C51/B51-1 -> 0.41873309 | D52: =D51/C51-1 -> 0.4109701 | E52: =E51/D51-1 -> 0.3956543 | F52: =F51/E51-1 -> 0.34310704 | G52: =G51/F51-1 -> 0.37834888 | H52: =H51/G51-1 -> 0.35328007 | I52: =I51/H51-1 -> 0.31997166 | J52: =J51/I51-1 -> 0.29978219 | ... P52: =P51/O51-1 -> 0.18673623
A53: Public administration | B53: =Poland!B53+Austria!B53+'Czech Republic'!B53+Greece!B53+Hungary!B53+Slovakia!B53+Croatia!B53 -> 21.795027 | C53: =Poland!C53+Austria!C53+'Czech Republic'!C53+Greece!C53+Hungary!C53+Slovakia!C53+Croatia!C53 -> 28.366736 | D53: =Poland!D53+Austria!D53+'Czech Republic'!D53+Greece!D53+Hungary!D53+Slovakia!D53+Croatia!D53 -> 37.53394 | E53: =Poland!E53+Austria!E53+'Czech Republic'!E53+Greece!E53+Hungary!E53+Slovakia!E53+Croatia!E53 -> 51.421312 | F53: =Poland!F53+Austria!F53+'Czech Republic'!F53+Greece!F53+Hungary!F53+Slovakia!F53+Croatia!F53 -> 69.841881 | G53: =Poland!G53+Austria!G53+'Czech Republic'!G53+Greece!G53+Hungary!G53+Slovakia!G53+Croatia!G53 -> 95.743853 | H53: =Poland!H53+Austria!H53+'Czech Republic'!H53+Greece!H53+Hungary!H53+Slovakia!H53+Croatia!H53 -> 126.22651 | I53: =Poland!I53+Austria!I53+'Czech Republic'!I53+Greece!I53+Hungary!I53+Slovakia!I53+Croatia!I53 -> 162.63497 | ... P53: =Poland!P53+Austria!P53+'Czech Republic'!P53+Greece!P53+Hungary!P53+Slovakia!P53+Croatia!P53 -> 680.69319 | R53: =(J53/D53)^(1/6)-1 -> 0.33265421 | S53: =(P53/J53)^(1/6)-1 -> 0.2162898
A54: Growth rate (%) | C54: =C53/B53-1 -> 0.30152332 | D54: =D53/C53-1 -> 0.32316741 | E54: =E53/D53-1 -> 0.36999505 | F54: =F53/E53-1 -> 0.35822828 | G54: =G53/F53-1 -> 0.3708659 | H54: =H53/G53-1 -> 0.31837719 | I54: =I53/H53-1 -> 0.28843752 | J54: =J53/I53-1 -> 0.29275154 | ... P54: =P53/O53-1 -> 0.16635037
A55: Total | B55: =B53+B51+B49+B47 -> 445.48041 | C55: =C53+C51+C49+C47 -> 561.63297 | D55: =D53+D51+D49+D47 -> 719.9911 | E55: =E53+E51+E49+E47 -> 934.29064 | F55: =F53+F51+F49+F47 -> 1174.6858 | G55: =G53+G51+G49+G47 -> 1500.3583 | H55: =H53+H51+H49+H47 -> 1913.5114 | I55: =I53+I51+I49+I47 -> 2397.2924 | ... P55: =P53+P51+P49+P47 -> 8142.7956 | R55: =(J55/D55)^(1/6)-1 -> 0.26622381 | S55: =(P55/J55)^(1/6)-1 -> 0.1832157
A56: Growth rate (%) | C56: =C55/B55-1 -> 0.26073548 | D56: =D55/C55-1 -> 0.28196019 | E56: =E55/D55-1 -> 0.29764192 | F56: =F55/E55-1 -> 0.25730232 | G56: =G55/F55-1 -> 0.2772422 | H56: =H55/G55-1 -> 0.27536963 | I56: =I55/H55-1 -> 0.25282373 | J56: =J55/I55-1 -> 0.2378527 | ... P56: =P55/O55-1 -> 0.14809359
A58: Public cloud spending per capita (by size of enterprises) (€ )
A59: Microenterprises (0-9 employees) | B59: =(B47*1000000)/(B34*1000) -> 97.223691 | C59: =(C47*1000000)/(C34*1000) -> 109.86573 | D59: =(D47*1000000)/(D34*1000) -> 127.3384 | E59: =(E47*1000000)/(E34*1000) -> 141.44091 | F59: =(F47*1000000)/(F34*1000) -> 160.52729 | G59: =(G47*1000000)/(G34*1000) -> 174.02978 | H59: =(H47*1000000)/(H34*1000) -> 194.48966 | I59: =(I47*1000000)/(I34*1000) -> 215.94231 | ... P59: =(P47*1000000)/(P34*1000) -> 393.9981 | R59: =(J59/D59)^(1/6)-1 -> 0.10971971 | S59: =(P59/J59)^(1/6)-1 -> 0.087783557
A60: Growth rate (%) | C60: =C59/B59-1 -> 0.13003045 | D60: =D59/C59-1 -> 0.15903656 | E60: =E59/D59-1 -> 0.11074826 | F60: =F59/E59-1 -> 0.13494243 | G60: =G59/F59-1 -> 0.084113416 | H60: =H59/G59-1 -> 0.11756536 | I60: =I59/H59-1 -> 0.11030225 | J60: =J59/I59-1 -> 0.10128938 | ... P60: =P59/O59-1 -> 0.083244448
A61: SME (10-249 employees) | B61: =(B49*1000000)/(B36*1000) -> 9583.8915 | C61: =(C49*1000000)/(C36*1000) -> 9316.5878 | D61: =(D49*1000000)/(D36*1000) -> 9320.3204 | E61: =(E49*1000000)/(E36*1000) -> 9482.197 | F61: =(F49*1000000)/(F36*1000) -> 9815.3091 | G61: =(G49*1000000)/(G36*1000) -> 9573.8315 | H61: =(H49*1000000)/(H36*1000) -> 9770.056 | I61: =(I49*1000000)/(I36*1000) -> 10122.997 | ... P61: =(P49*1000000)/(P36*1000) -> 14030.355 | R61: =(J61/D61)^(1/6)-1 -> 0.020347275 | S61: =(P61/J61)^(1/6)-1 -> 0.049200024
A62: Growth rate (%) | C62: =C61/B61-1 -> -0.027890939 | D62: =D61/C61-1 -> 0.0004006368 | E62: =E61/D61-1 -> 0.017368138 | F62: =F61/E61-1 -> 0.035130271 | G62: =G61/F61-1 -> -0.024602143 | H62: =H61/G61-1 -> 0.020495921 | I62: =I61/H61-1 -> 0.036124805 | J62: =J61/I61-1 -> 0.03898618 | ... P62: =P61/O61-1 -> 0.057376859
A63: Large enterprises (250+ employees) | B63: =(B51*1000000)/(B38*1000) -> 20090.362 | C63: =(C51*1000000)/(C38*1000) -> 21782.638 | D63: =(D51*1000000)/(D38*1000) -> 24167.97 | E63: =(E51*1000000)/(E38*1000) -> 28031.691 | F63: =(F51*1000000)/(F38*1000) -> 33523.269 | G63: =(G51*1000000)/(G38*1000) -> 40005.116 | H63: =(H51*1000000)/(H38*1000) -> 48335.288 | I63: =(I51*1000000)/(I38*1000) -> 59535.198 | ... P63: =(P51*1000000)/(P38*1000) -> 211556.51 | R63: =(J63/D63)^(1/6)-1 -> 0.20124047 | S63: =(P63/J63)^(1/6)-1 -> 0.19509129
A64: Growth rate (%) | C64: =C63/B63-1 -> 0.084233233 | D64: =D63/C63-1 -> 0.10950611 | E64: =E63/D63-1 -> 0.15986949 | F64: =F63/E63-1 -> 0.19590603 | G64: =G63/F63-1 -> 0.19335368 | H64: =H63/G63-1 -> 0.20822767 | I64: =I63/H63-1 -> 0.2317129 | J64: =J63/I63-1 -> 0.2196806 | ... P64: =P63/O63-1 -> 0.16726881
A65: Total | B65: =(B55*1000000)/(B40*1000) -> 1462.4098 | C65: =(C55*1000000)/(C40*1000) -> 1564.802 | D65: =(D55*1000000)/(D40*1000) -> 1684.9643 | E65: =(E55*1000000)/(E40*1000) -> 1796.8583 | F65: =(F55*1000000)/(F40*1000) -> 1910.1336 | G65: =(G55*1000000)/(G40*1000) -> 1961.4648 | H65: =(H55*1000000)/(H40*1000) -> 2050.8395 | I65: =(I55*1000000)/(I40*1000) -> 2190.7421 | ... P65: =(P55*1000000)/(P40*1000) -> 3077.4345 | R65: =(J65/D65)^(1/6)-1 -> 0.055210115 | S65: =(P65/J65)^(1/6)-1 -> 0.047757407
A66: Growth rate (%) | C66: =C65/B65-1 -> 0.070016024 | D66: =D65/C65-1 -> 0.076790769 | E66: =E65/D65-1 -> 0.06640735 | F66: =F65/E65-1 -> 0.063040756 | G66: =G65/F65-1 -> 0.026873075 | H66: =H65/G65-1 -> 0.045565307 | I66: =I65/H65-1 -> 0.0682172 | J66: =J65/I65-1 -> 0.061776556 | ... P66: =P65/O65-1 -> 0.047951154
A68: Public cloud (by model) (€ m)
A69: SaaS | B69: =Poland!B69+Austria!B69+'Czech Republic'!B69+Greece!B69+Hungary!B69+Slovakia!B69+Croatia!B69 -> 287.56805 | C69: =Poland!C69+Austria!C69+'Czech Republic'!C69+Greece!C69+Hungary!C69+Slovakia!C69+Croatia!C69 -> 363.94196 | D69: =Poland!D69+Austria!D69+'Czech Republic'!D69+Greece!D69+Hungary!D69+Slovakia!D69+Croatia!D69 -> 459.57879 | E69: =Poland!E69+Austria!E69+'Czech Republic'!E69+Greece!E69+Hungary!E69+Slovakia!E69+Croatia!E69 -> 591.51152 | F69: =Poland!F69+Austria!F69+'Czech Republic'!F69+Greece!F69+Hungary!F69+Slovakia!F69+Croatia!F69 -> 738.77218 | G69: =Poland!G69+Austria!G69+'Czech Republic'!G69+Greece!G69+Hungary!G69+Slovakia!G69+Croatia!G69 -> 933.92758 | H69: =Poland!H69+Austria!H69+'Czech Republic'!H69+Greece!H69+Hungary!H69+Slovakia!H69+Croatia!H69 -> 1183.9028 | I69: =Poland!I69+Austria!I69+'Czech Republic'!I69+Greece!I69+Hungary!I69+Slovakia!I69+Croatia!I69 -> 1481.3078 | ... P69: =Poland!P69+Austria!P69+'Czech Republic'!P69+Greece!P69+Hungary!P69+Slovakia!P69+Croatia!P69 -> 4999.3394 | R69: =(J69/D69)^(1/6)-1 -> 0.25870572 | S69: =(P69/J69)^(1/6)-1 -> 0.182591
A70: Growth rate (%) | C70: =C69/B69-1 -> 0.26558552 | D70: =D69/C69-1 -> 0.26278042 | E70: =E69/D69-1 -> 0.28707316 | F70: =F69/E69-1 -> 0.24895654 | G70: =G69/F69-1 -> 0.26416181 | H70: =H69/G69-1 -> 0.2676602 | I70: =I69/H69-1 -> 0.25120727 | J70: =J69/I69-1 -> 0.233843 | ... P70: =P69/O69-1 -> 0.14725658
A71: IaaS | B71: =Poland!B71+Austria!B71+'Czech Republic'!B71+Greece!B71+Hungary!B71+Slovakia!B71+Croatia!B71 -> 138.48392 | C71: œ | D71: =Poland!D71+Austria!D71+'Czech Republic'!D71+Greece!D71+Hungary!D71+Slovakia!D71+Croatia!D71 -> 226.6922 | E71: =Poland!E71+Austria!E71+'Czech Republic'!E71+Greece!E71+Hungary!E71+Slovakia!E71+Croatia!E71 -> 297.85705 | F71: =Poland!F71+Austria!F71+'Czech Republic'!F71+Greece!F71+Hungary!F71+Slovakia!F71+Croatia!F71 -> 378.02106 | G71: =Poland!G71+Austria!G71+'Czech Republic'!G71+Greece!G71+Hungary!G71+Slovakia!G71+Croatia!G71 -> 489.71701 | H71: =Poland!H71+Austria!H71+'Czech Republic'!H71+Greece!H71+Hungary!H71+Slovakia!H71+Croatia!H71 -> 629.81949 | I71: =Poland!I71+Austria!I71+'Czech Republic'!I71+Greece!I71+Hungary!I71+Slovakia!I71+Croatia!I71 -> 787.00029 | J71: =Poland!J71+Austria!J71+'Czech Republic'!J71+Greece!J71+Hungary!J71+Slovakia!J71+Croatia!J71 -> 971.90566 | K71: =Poland!K71+Austria!K71+'Czech Republic'!K71+Greece!K71+Hungary!K71+Slovakia!K71+Croatia!K71 -> 1160.888 | ... P71: =Poland!P71+Austria!P71+'Czech Republic'!P71+Greece!P71+Hungary!P71+Slovakia!P71+Croatia!P71 -> 2534.8545 | R71: =(J71/D71)^(1/6)-1 -> 0.27457263 | S71: =(P71/J71)^(1/6)-1 -> 0.17324349
A72: Growth rate (%) | C72: =C71/B71-1 -> #VALUE! | D72: =D71/C71-1 -> #VALUE! | E72: =E71/D71-1 -> 0.31392719 | F72: =F71/E71-1 -> 0.26913588 | G72: =G71/F71-1 -> 0.29547545 | H72: =H71/G71-1 -> 0.28608865 | I72: =I71/H71-1 -> 0.24956485 | J72: =J71/I71-1 -> 0.23494956 | ... P72: =P71/O71-1 -> 0.14050309
A73: PaaS | B73: =Poland!B73+Austria!B73+'Czech Republic'!B73+Greece!B73+Hungary!B73+Slovakia!B73+Croatia!B73 -> 19.428443 | C73: =Poland!C73+Austria!C73+'Czech Republic'!C73+Greece!C73+Hungary!C73+Slovakia!C73+Croatia!C73 -> 25.495293 | D73: =Poland!D73+Austria!D73+'Czech Republic'!D73+Greece!D73+Hungary!D73+Slovakia!D73+Croatia!D73 -> 33.720118 | E73: =Poland!E73+Austria!E73+'Czech Republic'!E73+Greece!E73+Hungary!E73+Slovakia!E73+Croatia!E73 -> 44.922069 | F73: =Poland!F73+Austria!F73+'Czech Republic'!F73+Greece!F73+Hungary!F73+Slovakia!F73+Croatia!F73 -> 57.892538 | G73: =Poland!G73+Austria!G73+'Czech Republic'!G73+Greece!G73+Hungary!G73+Slovakia!G73+Croatia!G73 -> 76.713666 | H73: =Poland!H73+Austria!H73+'Czech Republic'!H73+Greece!H73+Hungary!H73+Slovakia!H73+Croatia!H73 -> 99.789046 | I73: =Poland!I73+Austria!I73+'Czech Republic'!I73+Greece!I73+Hungary!I73+Slovakia!I73+Croatia!I73 -> 128.98433 | ... P73: =Poland!P73+Austria!P73+'Czech Republic'!P73+Greece!P73+Hungary!P73+Slovakia!P73+Croatia!P73 -> 608.60173 | R73: =(J73/D73)^(1/6)-1 -> 0.30673771 | S73: =(P73/J73)^(1/6)-1 -> 0.23942121
A74: Growth rate (%) | C74: =C73/B73-1 -> 0.31226636 | D74: =D73/C73-1 -> 0.32260173 | E74: =E73/D73-1 -> 0.33220378 | F74: =F73/E73-1 -> 0.28873267 | G74: =G73/F73-1 -> 0.32510456 | H74: =H73/G73-1 -> 0.30079882 | I74: =I73/H73-1 -> 0.29257007 | J74: =J73/I73-1 -> 0.30161536 | ... P74: =P73/O73-1 -> 0.18814974
A75: Total | B75: =B69+B71+B73 -> 445.48041 | C75: =C69+C71+C73 -> #VALUE! | D75: =D69+D71+D73 -> 719.9911 | E75: =E69+E71+E73 -> 934.29064 | F75: =F69+F71+F73 -> 1174.6858 | G75: =G69+G71+G73 -> 1500.3583 | H75: =H69+H71+H73 -> 1913.5114 | I75: =I69+I71+I73 -> 2397.2924 | ... P75: =P69+P71+P73 -> 8142.7956 | R75: =(J75/D75)^(1/6)-1 -> 0.26622381 | S75: =(P75/J75)^(1/6)-1 -> 0.1832157
A76: Growth rate (%) | C76: =C75/B75-1 -> #VALUE! | D76: =D75/C75-1 -> #VALUE! | E76: =E75/D75-1 -> 0.29764192 | F76: =F75/E75-1 -> 0.25730232 | G76: =G75/F75-1 -> 0.2772422 | H76: =H75/G75-1 -> 0.27536963 | I76: =I75/H75-1 -> 0.25282373 | J76: =J75/I75-1 -> 0.2378527 | ... P76: =P75/O75-1 -> 0.14809359
A78: SaaS spending (by advanced and basic solutions) (€ m)
A79: Basic | B79: =Poland!B79+Austria!B79+'Czech Republic'!B79+Greece!B79+Hungary!B79+Slovakia!B79+Croatia!B79 -> 195.9654 | C79: =Poland!C79+Austria!C79+'Czech Republic'!C79+Greece!C79+Hungary!C79+Slovakia!C79+Croatia!C79 -> 242.89977 | D79: =Poland!D79+Austria!D79+'Czech Republic'!D79+Greece!D79+Hungary!D79+Slovakia!D79+Croatia!D79 -> 302.49235 | E79: =Poland!E79+Austria!E79+'Czech Republic'!E79+Greece!E79+Hungary!E79+Slovakia!E79+Croatia!E79 -> 377.06691 | F79: =Poland!F79+Austria!F79+'Czech Republic'!F79+Greece!F79+Hungary!F79+Slovakia!F79+Croatia!F79 -> 459.93715 | G79: =Poland!G79+Austria!G79+'Czech Republic'!G79+Greece!G79+Hungary!G79+Slovakia!G79+Croatia!G79 -> 561.81896 | H79: =Poland!H79+Austria!H79+'Czech Republic'!H79+Greece!H79+Hungary!H79+Slovakia!H79+Croatia!H79 -> 700.70801 | I79: =Poland!I79+Austria!I79+'Czech Republic'!I79+Greece!I79+Hungary!I79+Slovakia!I79+Croatia!I79 -> 865.82944 | ... P79: =Poland!P79+Austria!P79+'Czech Republic'!P79+Greece!P79+Hungary!P79+Slovakia!P79+Croatia!P79 -> 2599.4363 | R79: =(J79/D79)^(1/6)-1 -> 0.22953321 | S79: =(P79/J79)^(1/6)-1 -> 0.16400237
A80: Growth rate (%) | C80: =C79/B79-1 -> 0.23950335 | D80: =D79/C79-1 -> 0.24533818 | E80: =E79/D79-1 -> 0.2465337 | F80: =F79/E79-1 -> 0.21977596 | G80: =G79/F79-1 -> 0.22151245 | H80: =H79/G79-1 -> 0.24721319 | I80: =I79/H79-1 -> 0.23564941 | J80: =J79/I79-1 -> 0.20704549 | ... P80: =P79/O79-1 -> 0.13473156
A81: Advanced | B81: =Poland!B81+Austria!B81+'Czech Republic'!B81+Greece!B81+Hungary!B81+Slovakia!B81+Croatia!B81 -> 91.602655 | C81: =Poland!C81+Austria!C81+'Czech Republic'!C81+Greece!C81+Hungary!C81+Slovakia!C81+Croatia!C81 -> 121.0422 | D81: =Poland!D81+Austria!D81+'Czech Republic'!D81+Greece!D81+Hungary!D81+Slovakia!D81+Croatia!D81 -> 157.08643 | E81: =Poland!E81+Austria!E81+'Czech Republic'!E81+Greece!E81+Hungary!E81+Slovakia!E81+Croatia!E81 -> 214.44461 | F81: =Poland!F81+Austria!F81+'Czech Republic'!F81+Greece!F81+Hungary!F81+Slovakia!F81+Croatia!F81 -> 278.83503 | G81: =Poland!G81+Austria!G81+'Czech Republic'!G81+Greece!G81+Hungary!G81+Slovakia!G81+Croatia!G81 -> 372.10862 | H81: =Poland!H81+Austria!H81+'Czech Republic'!H81+Greece!H81+Hungary!H81+Slovakia!H81+Croatia!H81 -> 483.19481 | I81: =Poland!I81+Austria!I81+'Czech Republic'!I81+Greece!I81+Hungary!I81+Slovakia!I81+Croatia!I81 -> 615.47837 | ... P81: =Poland!P81+Austria!P81+'Czech Republic'!P81+Greece!P81+Hungary!P81+Slovakia!P81+Croatia!P81 -> 2399.9031 | R81: =(J81/D81)^(1/6)-1 -> 0.30687503 | S81: =(P81/J81)^(1/6)-1 -> 0.20533688
A82: Growth rate (%) | C82: =C81/B81-1 -> 0.32138307 | D82: =D81/C81-1 -> 0.2977824 | E82: =E81/D81-1 -> 0.36513769 | F82: =F81/E81-1 -> 0.30026597 | G82: =G81/F81-1 -> 0.33451175 | H82: =H81/G81-1 -> 0.29853161 | I82: =I81/H81-1 -> 0.27376858 | J82: =J81/I81-1 -> 0.27154062 | ... P82: =P81/O81-1 -> 0.16113868
A83: Total | B83: =B79+B81 -> 287.56805 | C83: =C79+C81 -> 363.94196 | D83: =D79+D81 -> 459.57879 | E83: =E79+E81 -> 591.51152 | F83: =F79+F81 -> 738.77218 | G83: =G79+G81 -> 933.92758 | H83: =H79+H81 -> 1183.9028 | I83: =I79+I81 -> 1481.3078 | ... P83: =P79+P81 -> 4999.3394 | R83: =(J83/D83)^(1/6)-1 -> 0.25870572 | S83: =(P83/J83)^(1/6)-1 -> 0.182591
A84: Growth rate (%) | C84: =C83/B83-1 -> 0.26558552 | D84: =D83/C83-1 -> 0.26278042 | E84: =E83/D83-1 -> 0.28707316 | F84: =F83/E83-1 -> 0.24895654 | G84: =G83/F83-1 -> 0.26416181 | H84: =H83/G83-1 -> 0.2676602 | I84: =I83/H83-1 -> 0.25120727 | J84: =J83/I83-1 -> 0.233843 | ... P84: =P83/O83-1 -> 0.14725658
A86: IaaS spending (by hyper and shared solutions) (€ m)
A87: Hyper | B87: =Poland!B87+Austria!B87+'Czech Republic'!B87+Greece!B87+Hungary!B87+Slovakia!B87+Croatia!B87 -> 55.812284 | C87: =Poland!C87+Austria!C87+'Czech Republic'!C87+Greece!C87+Hungary!C87+Slovakia!C87+Croatia!C87 -> 71.922029 | D87: =Poland!D87+Austria!D87+'Czech Republic'!D87+Greece!D87+Hungary!D87+Slovakia!D87+Croatia!D87 -> 97.837853 | E87: =Poland!E87+Austria!E87+'Czech Republic'!E87+Greece!E87+Hungary!E87+Slovakia!E87+Croatia!E87 -> 133.16902 | F87: =Poland!F87+Austria!F87+'Czech Republic'!F87+Greece!F87+Hungary!F87+Slovakia!F87+Croatia!F87 -> 175.67277 | G87: =Poland!G87+Austria!G87+'Czech Republic'!G87+Greece!G87+Hungary!G87+Slovakia!G87+Croatia!G87 -> 237.19935 | H87: =Poland!H87+Austria!H87+'Czech Republic'!H87+Greece!H87+Hungary!H87+Slovakia!H87+Croatia!H87 -> 315.93959 | I87: =Poland!I87+Austria!I87+'Czech Republic'!I87+Greece!I87+Hungary!I87+Slovakia!I87+Croatia!I87 -> 407.91516 | ... P87: =Poland!P87+Austria!P87+'Czech Republic'!P87+Greece!P87+Hungary!P87+Slovakia!P87+Croatia!P87 -> 1673.0555 | R87: =(J87/D87)^(1/6)-1 -> 0.32243345 | S87: =(P87/J87)^(1/6)-1 -> 0.21374302
A88: Growth rate (%) | C88: =C87/B87-1 -> 0.28864157 | D88: =D87/C87-1 -> 0.3603322 | E88: =E87/D87-1 -> 0.36111959 | F88: =F87/E87-1 -> 0.31917147 | G88: =G87/F87-1 -> 0.35023401 | H88: =H87/G87-1 -> 0.33195808 | I88: =I87/H87-1 -> 0.29111758 | J88: =J87/I87-1 -> 0.28286226 | ... P88: =P87/O87-1 -> 0.17764654
A89: Shared | B89: =Poland!B89+Austria!B89+'Czech Republic'!B89+Greece!B89+Hungary!B89+Slovakia!B89+Croatia!B89 -> 82.671636 | C89: =Poland!C89+Austria!C89+'Czech Republic'!C89+Greece!C89+Hungary!C89+Slovakia!C89+Croatia!C89 -> 100.27368 | D89: =Poland!D89+Austria!D89+'Czech Republic'!D89+Greece!D89+Hungary!D89+Slovakia!D89+Croatia!D89 -> 128.85435 | E89: =Poland!E89+Austria!E89+'Czech Republic'!E89+Greece!E89+Hungary!E89+Slovakia!E89+Croatia!E89 -> 164.68803 | F89: =Poland!F89+Austria!F89+'Czech Republic'!F89+Greece!F89+Hungary!F89+Slovakia!F89+Croatia!F89 -> 202.34829 | G89: =Poland!G89+Austria!G89+'Czech Republic'!G89+Greece!G89+Hungary!G89+Slovakia!G89+Croatia!G89 -> 252.51766 | H89: =Poland!H89+Austria!H89+'Czech Republic'!H89+Greece!H89+Hungary!H89+Slovakia!H89+Croatia!H89 -> 313.8799 | I89: =Poland!I89+Austria!I89+'Czech Republic'!I89+Greece!I89+Hungary!I89+Slovakia!I89+Croatia!I89 -> 379.08514 | ... P89: =Poland!P89+Austria!P89+'Czech Republic'!P89+Greece!P89+Hungary!P89+Slovakia!P89+Croatia!P89 -> 861.79902 | R89: =(J89/D89)^(1/6)-1 -> 0.23110316 | S89: =(P89/J89)^(1/6)-1 -> 0.11495338
A90: Growth rate (%) | C90: =C89/B89-1 -> 0.21291515 | D90: =D89/C89-1 -> 0.28502663 | E90: =E89/D89-1 -> 0.27809446 | F90: =F89/E89-1 -> 0.2286764 | G90: =G89/F89-1 -> 0.2479357 | H90: =H89/G89-1 -> 0.24300176 | I90: =I89/H89-1 -> 0.20773945 | J90: =J89/I89-1 -> 0.18339302 | ... P90: =P89/O89-1 -> 0.074698196
A91: Total | B91: =B89+B87 -> 138.48392 | C91: =C89+C87 -> 172.19571 | D91: =D89+D87 -> 226.6922 | E91: =E89+E87 -> 297.85705 | F91: =F89+F87 -> 378.02106 | G91: =G89+G87 -> 489.71701 | H91: =H89+H87 -> 629.81949 | I91: =I89+I87 -> 787.00029 | ... P91: =P89+P87 -> 2534.8545 | R91: =(J91/D91)^(1/6)-1 -> 0.27457263 | S91: =(P91/J91)^(1/6)-1 -> 0.17324349
A92: Growth rate (%) | C92: =C91/B91-1 -> 0.24343468 | D92: =D91/C91-1 -> 0.31647997 | E92: =E91/D91-1 -> 0.31392719 | F92: =F91/E91-1 -> 0.26913588 | G92: =G91/F91-1 -> 0.29547545 | H92: =H91/G91-1 -> 0.28608865 | I92: =I91/H91-1 -> 0.24956485 | J92: =J91/I91-1 -> 0.23494956 | ... P92: =P91/O91-1 -> 0.14050309
A94: PaaS spending (by hyper and shared solutions) (€ m)
A95: Hyper | B95: =Poland!B95+Austria!B95+'Czech Republic'!B95+Greece!B95+Hungary!B95+Slovakia!B95+Croatia!B95 -> 10.234813 | C95: =Poland!C95+Austria!C95+'Czech Republic'!C95+Greece!C95+Hungary!C95+Slovakia!C95+Croatia!C95 -> 13.904102 | D95: =Poland!D95+Austria!D95+'Czech Republic'!D95+Greece!D95+Hungary!D95+Slovakia!D95+Croatia!D95 -> 18.967298 | E95: =Poland!E95+Austria!E95+'Czech Republic'!E95+Greece!E95+Hungary!E95+Slovakia!E95+Croatia!E95 -> 26.071541 | F95: =Poland!F95+Austria!F95+'Czech Republic'!F95+Greece!F95+Hungary!F95+Slovakia!F95+Croatia!F95 -> 34.653335 | G95: =Poland!G95+Austria!G95+'Czech Republic'!G95+Greece!G95+Hungary!G95+Slovakia!G95+Croatia!G95 -> 47.431025 | H95: =Poland!H95+Austria!H95+'Czech Republic'!H95+Greece!H95+Hungary!H95+Slovakia!H95+Croatia!H95 -> 63.703847 | I95: =Poland!I95+Austria!I95+'Czech Republic'!I95+Greece!I95+Hungary!I95+Slovakia!I95+Croatia!I95 -> 85.109312 | ... P95: =Poland!P95+Austria!P95+'Czech Republic'!P95+Greece!P95+Hungary!P95+Slovakia!P95+Croatia!P95 -> 483.00765 | R95: =(J95/D95)^(1/6)-1 -> 0.34946421 | S95: =(P95/J95)^(1/6)-1 -> 0.27105221
A96: Growth rate (%) | C96: =C95/B95-1 -> 0.35851056 | D96: =D95/C95-1 -> 0.36415123 | E96: =E95/D95-1 -> 0.37455221 | F96: =F95/E95-1 -> 0.32916328 | G96: =G95/F95-1 -> 0.36872904 | H96: =H95/G95-1 -> 0.34308392 | I96: =I95/H95-1 -> 0.33601525 | J96: =J95/I95-1 -> 0.34584981 | ... P96: =P95/O95-1 -> 0.21515534
A97: Shared | B97: =Poland!B97+Austria!B97+'Czech Republic'!B97+Greece!B97+Hungary!B97+Slovakia!B97+Croatia!B97 -> 9.1936301 | C97: =Poland!C97+Austria!C97+'Czech Republic'!C97+Greece!C97+Hungary!C97+Slovakia!C97+Croatia!C97 -> 11.591191 | D97: =Poland!D97+Austria!D97+'Czech Republic'!D97+Greece!D97+Hungary!D97+Slovakia!D97+Croatia!D97 -> 14.752821 | E97: =Poland!E97+Austria!E97+'Czech Republic'!E97+Greece!E97+Hungary!E97+Slovakia!E97+Croatia!E97 -> 18.850528 | F97: =Poland!F97+Austria!F97+'Czech Republic'!F97+Greece!F97+Hungary!F97+Slovakia!F97+Croatia!F97 -> 23.239203 | G97: =Poland!G97+Austria!G97+'Czech Republic'!G97+Greece!G97+Hungary!G97+Slovakia!G97+Croatia!G97 -> 29.282641 | H97: =Poland!H97+Austria!H97+'Czech Republic'!H97+Greece!H97+Hungary!H97+Slovakia!H97+Croatia!H97 -> 36.085199 | I97: =Poland!I97+Austria!I97+'Czech Republic'!I97+Greece!I97+Hungary!I97+Slovakia!I97+Croatia!I97 -> 43.875022 | ... P97: =Poland!P97+Austria!P97+'Czech Republic'!P97+Greece!P97+Hungary!P97+Slovakia!P97+Croatia!P97 -> 125.59408 | R97: =(J97/D97)^(1/6)-1 -> 0.23889528 | S97: =(P97/J97)^(1/6)-1 -> 0.15340303
A98: Growth rate (%) | C98: =C97/B97-1 -> 0.26078498 | D98: =D97/C97-1 -> 0.27276142 | E98: =E97/D97-1 -> 0.27775756 | F98: =F97/E97-1 -> 0.23281444 | G98: =G97/F97-1 -> 0.26005356 | H98: =H97/G97-1 -> 0.23230685 | I98: =I97/H97-1 -> 0.21587309 | J98: =J97/I97-1 -> 0.21580884 | ... P98: =P97/O97-1 -> 0.094596097
A99: Total | B99: =B97+B95 -> 19.428443 | C99: =C97+C95 -> 25.495293 | D99: =D97+D95 -> 33.720118 | E99: =E97+E95 -> 44.922069 | F99: =F97+F95 -> 57.892538 | G99: =G97+G95 -> 76.713666 | H99: =H97+H95 -> 99.789046 | I99: =I97+I95 -> 128.98433 | ... P99: =P97+P95 -> 608.60173 | R99: =(J99/D99)^(1/6)-1 -> 0.30673771 | S99: =(P99/J99)^(1/6)-1 -> 0.23942121
A100: Growth rate (%) | C100: =C99/B99-1 -> 0.31226636 | D100: =D99/C99-1 -> 0.32260173 | E100: =E99/D99-1 -> 0.33220378 | F100: =F99/E99-1 -> 0.28873267 | G100: =G99/F99-1 -> 0.32510456 | H100: =H99/G99-1 -> 0.30079882 | I100: =I99/H99-1 -> 0.29257007 | J100: =J99/I99-1 -> 0.30161536 | ... P100: =P99/O99-1 -> 0.18814974
A102: Private cloud (by size of enterprises) (€ m)
A103: Microenterprises (0-9 employees) | B103: =Poland!B103+Austria!B103+'Czech Republic'!B103+Greece!B103+Hungary!B103+Slovakia!B103+Croatia!B103 -> 0.0055089333 | C103: =Poland!C103+Austria!C103+'Czech Republic'!C103+Greece!C103+Hungary!C103+Slovakia!C103+Croatia!C103 -> 0.0082482178 | D103: =Poland!D103+Austria!D103+'Czech Republic'!D103+Greece!D103+Hungary!D103+Slovakia!D103+Croatia!D103 -> 0.01124802 | E103: =Poland!E103+Austria!E103+'Czech Republic'!E103+Greece!E103+Hungary!E103+Slovakia!E103+Croatia!E103 -> 0.017069487 | F103: =Poland!F103+Austria!F103+'Czech Republic'!F103+Greece!F103+Hungary!F103+Slovakia!F103+Croatia!F103 -> 0.022581517 | G103: =Poland!G103+Austria!G103+'Czech Republic'!G103+Greece!G103+Hungary!G103+Slovakia!G103+Croatia!G103 -> 0.032235735 | H103: =Poland!H103+Austria!H103+'Czech Republic'!H103+Greece!H103+Hungary!H103+Slovakia!H103+Croatia!H103 -> 0.04364262 | I103: =Poland!I103+Austria!I103+'Czech Republic'!I103+Greece!I103+Hungary!I103+Slovakia!I103+Croatia!I103 -> 0.055844606 | ... P103: =Poland!P103+Austria!P103+'Czech Republic'!P103+Greece!P103+Hungary!P103+Slovakia!P103+Croatia!P103 -> 0.20721544 | R103: =(J103/D103)^(1/6)-1 -> 0.35640348 | S103: =(P103/J103)^(1/6)-1 -> 0.19812495
A104: Growth rate (%) | C104: =C103/B103-1 -> 0.49724408 | D104: =D103/C103-1 -> 0.36369094 | E104: =E103/D103-1 -> 0.51755483 | F104: =F103/E103-1 -> 0.32291715 | G104: =G103/F103-1 -> 0.42752746 | H104: =H103/G103-1 -> 0.35385838 | I104: =I103/H103-1 -> 0.27958877 | J104: =J103/I103-1 -> 0.25437735 | ... P104: =P103/O103-1 -> 0.16428553
A105: SME (10-249 employees) | B105: =Poland!B105+Austria!B105+'Czech Republic'!B105+Greece!B105+Hungary!B105+Slovakia!B105+Croatia!B105 -> 25.694036 | C105: =Poland!C105+Austria!C105+'Czech Republic'!C105+Greece!C105+Hungary!C105+Slovakia!C105+Croatia!C105 -> 32.181614 | D105: =Poland!D105+Austria!D105+'Czech Republic'!D105+Greece!D105+Hungary!D105+Slovakia!D105+Croatia!D105 -> 40.538972 | E105: =Poland!E105+Austria!E105+'Czech Republic'!E105+Greece!E105+Hungary!E105+Slovakia!E105+Croatia!E105 -> 51.685321 | F105: =Poland!F105+Austria!F105+'Czech Republic'!F105+Greece!F105+Hungary!F105+Slovakia!F105+Croatia!F105 -> 61.667528 | G105: =Poland!G105+Austria!G105+'Czech Republic'!G105+Greece!G105+Hungary!G105+Slovakia!G105+Croatia!G105 -> 75.722025 | H105: =Poland!H105+Austria!H105+'Czech Republic'!H105+Greece!H105+Hungary!H105+Slovakia!H105+Croatia!H105 -> 94.54346 | I105: =Poland!I105+Austria!I105+'Czech Republic'!I105+Greece!I105+Hungary!I105+Slovakia!I105+Croatia!I105 -> 114.86421 | ... P105: =Poland!P105+Austria!P105+'Czech Republic'!P105+Greece!P105+Hungary!P105+Slovakia!P105+Croatia!P105 -> 322.56932 | R105: =(J105/D105)^(1/6)-1 -> 0.22494366 | S105: =(P105/J105)^(1/6)-1 -> 0.153477
A106: Growth rate (%) | C106: =C105/B105-1 -> 0.25249351 | D106: =D105/C105-1 -> 0.2596936 | E106: =E105/D105-1 -> 0.27495389 | F106: =F105/E105-1 -> 0.19313429 | G106: =G105/F105-1 -> 0.22790756 | H106: =H105/G105-1 -> 0.24855959 | I106: =I105/H105-1 -> 0.21493559 | J106: =J105/I105-1 -> 0.19229763 | ... P106: =P105/O105-1 -> 0.13736708
A107: Large enterprises (250+ employees) | B107: =Poland!B107+Austria!B107+'Czech Republic'!B107+Greece!B107+Hungary!B107+Slovakia!B107+Croatia!B107 -> 115.98915 | C107: =Poland!C107+Austria!C107+'Czech Republic'!C107+Greece!C107+Hungary!C107+Slovakia!C107+Croatia!C107 -> 149.99157 | D107: =Poland!D107+Austria!D107+'Czech Republic'!D107+Greece!D107+Hungary!D107+Slovakia!D107+Croatia!D107 -> 192.10442 | E107: =Poland!E107+Austria!E107+'Czech Republic'!E107+Greece!E107+Hungary!E107+Slovakia!E107+Croatia!E107 -> 243.9312 | F107: =Poland!F107+Austria!F107+'Czech Republic'!F107+Greece!F107+Hungary!F107+Slovakia!F107+Croatia!F107 -> 287.77774 | G107: =Poland!G107+Austria!G107+'Czech Republic'!G107+Greece!G107+Hungary!G107+Slovakia!G107+Croatia!G107 -> 350.16772 | H107: =Poland!H107+Austria!H107+'Czech Republic'!H107+Greece!H107+Hungary!H107+Slovakia!H107+Croatia!H107 -> 434.65966 | I107: =Poland!I107+Austria!I107+'Czech Republic'!I107+Greece!I107+Hungary!I107+Slovakia!I107+Croatia!I107 -> 537.1334 | ... P107: =Poland!P107+Austria!P107+'Czech Republic'!P107+Greece!P107+Hungary!P107+Slovakia!P107+Croatia!P107 -> 1540.8834 | R107: =(J107/D107)^(1/6)-1 -> 0.22585483 | S107: =(P107/J107)^(1/6)-1 -> 0.15416092
A108: Growth rate (%) | C108: =C107/B107-1 -> 0.29315169 | D108: =D107/C107-1 -> 0.28076809 | E108: =E107/D107-1 -> 0.26978446 | F108: =F107/E107-1 -> 0.17974959 | G108: =G107/F107-1 -> 0.21679922 | H108: =H107/G107-1 -> 0.2412899 | I108: =I107/H107-1 -> 0.23575628 | J108: =J107/I107-1 -> 0.21363874 | ... P108: =P107/O107-1 -> 0.12637288
A109: Public administration | B109: =Poland!B109+Austria!B109+'Czech Republic'!B109+Greece!B109+Hungary!B109+Slovakia!B109+Croatia!B109 -> 17.234146 | C109: =Poland!C109+Austria!C109+'Czech Republic'!C109+Greece!C109+Hungary!C109+Slovakia!C109+Croatia!C109 -> 22.774042 | D109: =Poland!D109+Austria!D109+'Czech Republic'!D109+Greece!D109+Hungary!D109+Slovakia!D109+Croatia!D109 -> 29.773972 | E109: =Poland!E109+Austria!E109+'Czech Republic'!E109+Greece!E109+Hungary!E109+Slovakia!E109+Croatia!E109 -> 39.157079 | F109: =Poland!F109+Austria!F109+'Czech Republic'!F109+Greece!F109+Hungary!F109+Slovakia!F109+Croatia!F109 -> 47.562091 | G109: =Poland!G109+Austria!G109+'Czech Republic'!G109+Greece!G109+Hungary!G109+Slovakia!G109+Croatia!G109 -> 60.701066 | H109: =Poland!H109+Austria!H109+'Czech Republic'!H109+Greece!H109+Hungary!H109+Slovakia!H109+Croatia!H109 -> 78.00617 | I109: =Poland!I109+Austria!I109+'Czech Republic'!I109+Greece!I109+Hungary!I109+Slovakia!I109+Croatia!I109 -> 98.092085 | ... P109: =Poland!P109+Austria!P109+'Czech Republic'!P109+Greece!P109+Hungary!P109+Slovakia!P109+Croatia!P109 -> 325.33706 | R109: =(J109/D109)^(1/6)-1 -> 0.26423555 | S109: =(P109/J109)^(1/6)-1 -> 0.17829707
A110: Growth rate (%) | C110: =C109/B109-1 -> 0.32144879 | D110: =D109/C109-1 -> 0.30736444 | E110: =E109/D109-1 -> 0.31514462 | F110: =F109/E109-1 -> 0.21464859 | G110: =G109/F109-1 -> 0.27624889 | H110: =H109/G109-1 -> 0.28508732 | I110: =I109/H109-1 -> 0.25749136 | J110: =J109/I109-1 -> 0.23928387 | ... P110: =P109/O109-1 -> 0.14165595
A111: Total | B111: =B109+B107+B105+B103 -> 158.92284 | C111: =C109+C107+C105+C103 -> 204.95547 | D111: =D109+D107+D105+D103 -> 262.42861 | E111: =E109+E107+E105+E103 -> 334.79067 | F111: =F109+F107+F105+F103 -> 397.02994 | G111: =G109+G107+G105+G103 -> 486.62305 | H111: =H109+H107+H105+H103 -> 607.25293 | I111: =I109+I107+I105+I103 -> 750.14555 | ... P111: =P109+P107+P105+P103 -> 2188.997 | R111: =(J111/D111)^(1/6)-1 -> 0.23038942 | S111: =(P111/J111)^(1/6)-1 -> 0.15743447
A112: Growth rate (%) | C112: =C111/B111-1 -> 0.28965394 | D112: =D111/C111-1 -> 0.28041767 | E112: =E111/D111-1 -> 0.27574 | F112: =F111/E111-1 -> 0.18590502 | G112: =G111/F111-1 -> 0.22565833 | H112: =H111/G111-1 -> 0.24789183 | I112: =I111/H111-1 -> 0.23530988 | J112: =J111/I111-1 -> 0.21372743 | ... P112: =P111/O111-1 -> 0.13023501
A114: Private cloud spending per capita (by size of enterprises) (€ )
...

Sheet Poland
A1: Year | B1: 2016 | C1: 2017 | D1: 2018 | E1: 2019 | F1: 2020 | G1: 2021 | H1: 2022 | I1: 2023 | J1: 2024 | K1: 2025e | L1: 2026f | M1: 2027f | N1: 2028f | O1: 2029f | P1: 2030f | R1: CAGR 2019-2024 | S1: CAGR 2025-2030
A2: Total IT market size (€ m) | B2: =B4+B6+B8 -> 9299.5443 | C2: =C4+C6+C8 -> 9981.5665 | D2: =D4+D6+D8 -> 10760.683 | E2: =E4+E6+E8 -> 11431.027 | F2: =F4+F6+F8 -> 11596.75 | G2: =G4+G6+G8 -> 13106.045 | H2: =H4+H6+H8 -> 14005.695 | I2: =I4+I6+I8 -> 15104.365 | ... P2: =P4+P6+P8 -> 24173.034 | R2: =(J2/D2)^(1/6)-1 -> 0.079094117 | S2: =(P2/J2)^(1/6)-1 -> 0.06052904
A3: Growth rate (%) | C3: =C2/B2-1 -> 0.073339313 | D3: =D2/C2-1 -> 0.078055502 | E3: =E2/D2-1 -> 0.06229573 | F3: =F2/E2-1 -> 0.014497591 | G3: =G2/F2-1 -> 0.13014815 | H3: =H2/G2-1 -> 0.068643857 | I3: =I2/H2-1 -> 0.078444524 | J3: =J2/I2-1 -> 0.12484663 | ... P3: =P2/O2-1 -> 0.047895339
A4: Software | B4: 1615.0109 | C4: 1735.2955 | D4: 1836.4424 | E4: 1935.2326 | F4: 1984.855 | G4: 2061.9576 | H4: 2184.3829 | I4: 2468.5777 | J4: 2793.5177 | K4: 3059.759 | L4: 3316.0726 | M4: 3515.321 | N4: 3744.933 | O4: 3983.355 | P4: 4223.0619 | R4: =(J4/D4)^(1/6)-1 -> 0.072413692 | S4: =(P4/J4)^(1/6)-1 -> 0.071303863
A5: Growth rate (%) | C5: =C4/B4-1 -> 0.074479107 | D5: =D4/C4-1 -> 0.05828801 | E5: =E4/D4-1 -> 0.053794332 | F5: =F4/E4-1 -> 0.025641567 | G5: =G4/F4-1 -> 0.038845463 | H5: =H4/G4-1 -> 0.059373294 | I5: =I4/H4-1 -> 0.13010303 | J5: =J4/I4-1 -> 0.13163045 | ... P5: =P4/O4-1 -> 0.060177131
A6: Hardware | B6: 4613.2157 | C6: 5023.8411 | D6: 5551.5202 | E6: 5930.3369 | F6: 6034.5517 | G6: 7324.7373 | H6: 7655.2593 | I6: 7876.4597 | J6: 8788.142 | K6: 9453.3222 | L6: 9974.3679 | M6: 10338.013 | N6: 10680.834 | O6: 10999.15 | P6: 11289.958 | R6: =(J6/D6)^(1/6)-1 -> 0.079561836 | S6: =(P6/J6)^(1/6)-1 -> 0.042635585
A7: Growth rate (%) | C7: =C6/B6-1 -> 0.08901066 | D7: =D6/C6-1 -> 0.105035 | E7: =E6/D6-1 -> 0.068236567 | F7: =F6/E6-1 -> 0.017573168 | G7: =G6/F6-1 -> 0.21379974 | H7: =H6/G6-1 -> 0.045124083 | I7: =I6/H6-1 -> 0.028895211 | J7: =J6/I6-1 -> 0.11574773 | ... P7: =P6/O6-1 -> 0.026439124
A8: Services | B8: 3071.3176 | C8: 3222.4299 | D8: 3372.72 | E8: 3565.4577 | F8: 3577.3428 | G8: 3719.3501 | H8: 4166.0524 | I8: 4759.3272 | J8: 5408.4339 | K8: 5980.7669 | L8: 6517.1645 | M8: 6982.5556 | N8: 7515.4869 | O8: 8085.6707 | P8: 8660.0141 | R8: =(J8/D8)^(1/6)-1 -> 0.081886929 | S8: =(P8/J8)^(1/6)-1 -> 0.081619508
A9: Growth rate (%) | C9: =C8/B8-1 -> 0.049201112 | D9: =D8/C8-1 -> 0.046638747 | E9: =E8/D8-1 -> 0.057146074 | F9: =F8/E8-1 -> 0.0033334168 | G9: =G8/F8-1 -> 0.039696311 | H9: =H8/G8-1 -> 0.12010222 | I9: =I8/H8-1 -> 0.14240697 | J9: =J8/I8-1 -> 0.13638622 | ... P9: =P8/O8-1 -> 0.071032244
A11: Smartphones market size (€ m) | B11: 1873.6856 | C11: 2216.8136 | D11: 2573.1413 | E11: 2707.7522 | F11: 2319.8336 | G11: 3181.3587 | H11: 3148.4867 | I11: 3212.213 | J11: 3512.037 | K11: 3731.3699 | L11: 3900.0517 | M11: 4000.0416 | N11: 4085.0589 | O11: 4158.5832 | P11: 4219.8889 | R11: =(J11/D11)^(1/6)-1 -> 0.053212267 | S11: =(P11/J11)^(1/6)-1 -> 0.031075156
A12: Growth rate (%) | C12: =C11/B11-1 -> 0.18312999 | D12: =D11/C11-1 -> 0.16073865 | E12: =E11/D11-1 -> 0.052313853 | F12: =F11/E11-1 -> -0.14326224 | G12: =G11/F11-1 -> 0.37137368 | H12: =H11/G11-1 -> -0.010332688 | I12: =I11/H11-1 -> 0.020240299 | J12: =J11/I11-1 -> 0.093338759 | ... P12: =P11/O11-1 -> 0.014741964
A14: Cybersecurity market size (€ m) | B14: 253.95765 | C14: 284.89601 | D14: 327.05276 | E14: 360.93874 | F14: 370.35188 | G14: 402.23624 | H14: 475.00383 | I14: 542.01077 | J14: 627.45755 | K14: 791.42892 | L14: 956.75508 | M14: 963.34559 | N14: 976.29511 | O14: 1040.3916 | P14: 1144.4307 | R14: =(J14/D14)^(1/6)-1 -> 0.11470793 | S14: =(P14/J14)^(1/6)-1 -> 0.10535266
A15: Growth rate (%) | C15: =C14/B14-1 -> 0.1218249 | D15: =D14/C14-1 -> 0.1479724 | E15: =E14/D14-1 -> 0.10361013 | F15: =F14/E14-1 -> 0.026079609 | G15: =G14/F14-1 -> 0.086092069 | H15: =H14/G14-1 -> 0.18090761 | I15: =I14/H14-1 -> 0.14106609 | J15: =J14/I14-1 -> 0.15764777 | ... P15: =P14/O14-1 -> 0.1
A17: Enterprises (by size) (number of enterprises in thousands)
A18: Microenterprises (0-9 employees) | B18: 726.01385 | C18: 743.81869 | D18: 745.12372 | E18: 754.48772 | F18: 768.18886 | G18: 780.17634 | H18: 852.96648 | I18: 873.93681 | J18: 869.01861 | K18: 876.49216 | L18: 885.99723 | M18: 895.37264 | N18: 903.00275 | O18: 912.42158 | P18: 920.39335 | R18: =(J18/D18)^(1/6)-1 -> 0.025967132 | S18: =(P18/J18)^(1/6)-1 -> 0.0096187316
A19: Growth rate (%) | C19: =C18/B18-1 -> 0.024524111 | D19: =D18/C18-1 -> 0.0017544952 | E19: =E18/D18-1 -> 0.012567037 | F19: =F18/E18-1 -> 0.018159527 | G19: =G18/F18-1 -> 0.015604857 | H19: =H18/G18-1 -> 0.09329961 | I19: =I18/H18-1 -> 0.024585174 | J19: =J18/I18-1 -> -0.0056276423 | ... P19: =P18/O18-1 -> 0.0087369419
A20: SME (10-249 employees) | B20: 140.52218 | C20: 145.54094 | D20: 150.46679 | E20: 151.81671 | F20: 150.68485 | G20: 156.5012 | H20: 154.56408 | I20: 154.96105 | J20: 155.78067 | K20: 157.84591 | L20: 159.87826 | M20: 161.91875 | N20: 163.48488 | O20: 165.0677 | P20: 166.14508 | R20: =(J20/D20)^(1/6)-1 -> 0.0058012051 | S20: =(P20/J20)^(1/6)-1 -> 0.010793223
A21: Growth rate (%) | C21: =C20/B20-1 -> 0.035715077 | D21: =D20/C20-1 -> 0.033845108 | E21: =E20/D20-1 -> 0.0089715382 | F21: =F20/E20-1 -> -0.0074554485 | G21: =G20/F20-1 -> 0.038599476 | H21: =H20/G20-1 -> -0.012377675 | I21: =I20/H20-1 -> 0.0025683163 | J21: =J20/I20-1 -> 0.0052891874 | ... P21: =P20/O20-1 -> 0.0065268973
A22: Large enterprises (250+ employees) | B22: 4.6965969 | C22: 4.8727765 | D22: 5.0567755 | E22: 5.1072507 | F22: 4.9719012 | G22: 5.1352403 | H22: 5.2112487 | I22: 5.1343709 | J22: 5.2249167 | K22: 5.3311406 | L22: 5.41576 | M22: 5.4901257 | N22: 5.559907 | O22: 5.6221213 | P22: 5.6703803 | R22: =(J22/D22)^(1/6)-1 -> 0.0054665255 | S22: =(P22/J22)^(1/6)-1 -> 0.013729621
A23: Growth rate (%) | C23: =C22/B22-1 -> 0.03751218 | D23: =D22/C22-1 -> 0.037760602 | E23: =E22/D22-1 -> 0.0099817139 | F23: =F22/E22-1 -> -0.026501457 | G23: =G22/F22-1 -> 0.032852444 | H23: =H22/G22-1 -> 0.014801334 | I23: =I22/H22-1 -> -0.014752266 | J23: =J22/I22-1 -> 0.017635212 | ... P23: =P22/O22-1 -> 0.0085837792
A24: Number of all enterprises | B24: =B18+B20+B22 -> 871.23263 | C24: =C18+C20+C22 -> 894.23241 | D24: =D18+D20+D22 -> 900.64729 | E24: =E18+E20+E22 -> 911.41168 | F24: =F18+F20+F22 -> 923.84561 | G24: =G18+G20+G22 -> 941.81278 | H24: =H18+H20+H22 -> 1012.7418 | I24: =I18+I20+I22 -> 1034.0322 | ... P24: =P18+P20+P22 -> 1092.2088 | R24: =(J24/D24)^(1/6)-1 -> 0.022622743 | S24: =(P24/J24)^(1/6)-1 -> 0.009817847
A25: Growth rate (%) | C25: =C24/B24-1 -> 0.026399131 | D25: =D24/C24-1 -> 0.0071736095 | E25: =E24/D24-1 -> 0.011951839 | F25: =F24/E24-1 -> 0.013642495 | G25: =G24/F24-1 -> 0.019448242 | H25: =H24/G24-1 -> 0.075311184 | I25: =I24/H24-1 -> 0.021022556 | J25: =J24/I24-1 -> -0.0038761268 | ... P25: =P24/O24-1 -> 0.008399333
A27: Percentage of enterprises using cloud computing
A28: Percent of microenterprises using cloud computing | B28: 0.032269528 | C28: 0.045014604 | D28: 0.062468499 | E28: 0.086079932 | F28: 0.11749738 | G28: 0.15839424 | H28: 0.2101364 | I28: 0.27329233 | J28: 0.34708865 | K28: 0.42904711 | L28: 0.5150907 | M28: 0.6002489 | N28: 0.67975006 | O28: 0.7500248 | P28: 0.809207
A29: Percent of SME using cloud computing | B29: 0.06662654 | C29: 0.09290258 | D29: 0.12811888 | E29: 0.17412205 | F29: 0.23224345 | G29: 0.30265588 | H29: 0.38374595 | I29: 0.47186112 | J29: 0.56176526 | K29: 0.64778872 | L29: 0.72518673 | M29: 0.79106242 | N29: 0.84453234 | O29: 0.8862856 | P29: 0.91791528
A30: Percent of large enterprises using cloud computing | B30: 0.26270054 | C30: 0.34893304 | D30: 0.4463361 | E30: 0.54804167 | F30: 0.64588694 | G30: 0.73287435 | H30: 0.80494651 | I30: 0.86125452 | J30: 0.90326108 | K30: 0.93353126 | L30: 0.95480366 | M30: 0.96949062 | N30: 0.97950735 | O30: 0.98628196 | P30: 0.99083791
A31: Percent of all enterprises using cloud computing | B31: 0.039053209 | C31: 0.054464706 | D31: 0.075591655 | E31: 0.10333407 | F31: 0.13905682 | G31: 0.18549858 | H31: 0.2396933 | I31: 0.3059695 | J31: 0.38237755 | K31: 0.46484402 | L31: 0.54930688 | M31: 0.63122748 | N31: 0.70643361 | O31: 0.77201748 | P31: 0.8266865
A33: Number of enterprises using cloud computing (thousands)
A34: Number of microenterprises using cloud computing | B34: =B28*B18 -> 23.428124 | C34: =C28*C18 -> 33.482704 | D34: =D28*D18 -> 46.54676 | E34: =E28*E18 -> 64.946251 | F34: =F28*F18 -> 90.260182 | G34: =G28*G18 -> 123.57544 | H34: =H28*H18 -> 179.23931 | I34: =I28*I18 -> 238.84023 | ... P34: =P28*P18 -> 744.78875 | R34: =(J34/D34)^(1/6)-1 -> 0.36541082 | S34: =(P34/J34)^(1/6)-1 -> 0.16259184
A35: Growth rate (%) | C35: =C34/B34-1 -> 0.42916706 | D35: =D34/C34-1 -> 0.39017328 | E35: =E34/D34-1 -> 0.39529048 | F35: =F34/E34-1 -> 0.38976739 | G35: =G34/F34-1 -> 0.3691025 | H35: =H34/G34-1 -> 0.45044443 | I35: =I34/H34-1 -> 0.33252146 | J35: =J34/I34-1 -> 0.2628798 | ... P35: =P34/O34-1 -> 0.088333341
A36: Number of SME using cloud computing | B36: =B29*B20 -> 9.3625066 | C36: =C29*C20 -> 13.521129 | D36: =D29*D20 -> 19.277637 | E36: =E29*E20 -> 26.434637 | F36: =F29*F20 -> 34.995569 | G36: =G29*G20 -> 47.36601 | H36: =H29*H20 -> 59.31334 | I36: =I29*I20 -> 73.120094 | ... P36: =P29*P20 -> 152.50711 | R36: =(J36/D36)^(1/6)-1 -> 0.28677448 | S36: =(P36/J36)^(1/6)-1 -> 0.096992373
A37: Growth rate (%) | C37: =C36/B36-1 -> 0.4441783 | D37: =D36/C36-1 -> 0.42574169 | E37: =E36/D36-1 -> 0.37125918 | F37: =F36/E36-1 -> 0.32385282 | G37: =G36/F36-1 -> 0.35348593 | H37: =H36/G36-1 -> 0.25223425 | I37: =I36/H36-1 -> 0.23277655 | J37: =J36/I36-1 -> 0.19682789 | ... P37: =P36/O36-1 -> 0.042447733
A38: Number of large enterprises using cloud computing | B38: =B30*B22 -> 1.2337986 | C38: =C30*C22 -> 1.7002727 | D38: =D30*D22 -> 2.2570214 | E38: =E30*E22 -> 2.7989862 | F38: =F30*F22 -> 3.211286 | G38: =G30*G22 -> 3.7634859 | H38: =H30*H22 -> 4.1947764 | I38: =I30*I22 -> 4.4220002 | ... P38: =P30*P22 -> 5.6184278 | R38: =(J38/D38)^(1/6)-1 -> 0.1308183 | S38: =(P38/J38)^(1/6)-1 -> 0.02948579
A39: Growth rate (%) | C39: =C38/B38-1 -> 0.37807966 | D39: =D38/C38-1 -> 0.32744673 | E39: =E38/D38-1 -> 0.24012389 | F39: =F38/E38-1 -> 0.14730326 | G39: =G38/F38-1 -> 0.17195599 | H39: =H38/G38-1 -> 0.1145987 | I39: =I38/H38-1 -> 0.054168262 | J39: =J38/I38-1 -> 0.06726903 | ... P39: =P38/O38-1 -> 0.013242757
A40: Number of all enterprises using cloud computing | B40: =B38+B36+B34 -> 34.02443 | C40: =C38+C36+C34 -> 48.704105 | D40: =D38+D36+D34 -> 68.081419 | E40: =E38+E36+E34 -> 94.179874 | F40: =F38+F36+F34 -> 128.46704 | G40: =G38+G36+G34 -> 174.70494 | H40: =H38+H36+H34 -> 242.74743 | I40: =I38+I36+I34 -> 316.38232 | ... P40: =P38+P36+P34 -> 902.91428 | R40: =(J40/D40)^(1/6)-1 -> 0.3398367 | S40: =(P40/J40)^(1/6)-1 -> 0.14828877
A41: Growth rate (%) | C41: =C40/B40-1 -> 0.43144517 | D41: =D40/C40-1 -> 0.39785791 | E41: =E40/D40-1 -> 0.38334183 | F41: =F40/E40-1 -> 0.36406039 | G41: =G40/F40-1 -> 0.35992034 | H41: =H40/G40-1 -> 0.3894709 | I41: =I40/H40-1 -> 0.30333955 | J41: =J40/I40-1 -> 0.24488033 | ... P41: =P40/O40-1 -> 0.079807304
A43: Total cloud computing market size (€ m) | B43: =B55+B111 -> 139.4767 | C43: =C55+C111 -> 182.93872 | D43: =D55+D111 -> 239.48228 | E43: =E55+E111 -> 312.28116 | F43: =F55+F111 -> 385.49673 | G43: =G55+G111 -> 492.47464 | H43: =H55+H111 -> 621.43933 | I43: =I55+I111 -> 826.81692 | ... P43: =P55+P111 -> 3245.6834 | R43: =(J43/D43)^(1/6)-1 -> 0.28608436 | S43: =(P43/J43)^(1/6)-1 -> 0.20061197
A44: Growth rate (%) | C44: =C43/B43-1 -> 0.31160778 | D44: =D43/C43-1 -> 0.30908469 | E44: =E43/D43-1 -> 0.30398437 | F44: =F43/E43-1 -> 0.23445403 | G44: =G43/F43-1 -> 0.27750667 | H44: =H43/G43-1 -> 0.2618707 | I44: =I43/H43-1 -> 0.33048697 | J44: =J43/I43-1 -> 0.31063203 | ... P44: =P43/O43-1 -> 0.14955977
A46: Public cloud (by size of enterprises) (€ m)
A47: Microenterprises (0-9 employees) | B47: 5.5532851 | C47: 7.5330778 | D47: 10.467136 | E47: 14.656433 | F47: 20.061965 | G47: 28.087663 | H47: 39.028122 | I47: 54.942037 | J47: 77.372036 | K47: 105.18362 | L47: 138.73444 | M47: 173.90898 | N47: 213.06599 | O47: 261.51338 | P47: 311.31858 | R47: =(J47/D47)^(1/6)-1 -> 0.39570198 | S47: =(P47/J47)^(1/6)-1 -> 0.26115995
A48: Growth rate (%) | C48: =C47/B47-1 -> 0.35650838 | D48: =D47/C47-1 -> 0.3894899 | E48: =E47/D47-1 -> 0.40023337 | F48: =F47/E47-1 -> 0.3688164 | G48: =G47/F47-1 -> 0.40004546 | H48: =H47/G47-1 -> 0.38951118 | I48: =I47/H47-1 -> 0.40775507 | J48: =J47/I47-1 -> 0.4082484 | ... P48: =P47/O47-1 -> 0.19044991
A49: SME (10-249 employees) | B49: 58.976967 | C49: 76.359993 | D49: 99.39216 | E49: 128.2664 | F49: 160.77269 | G49: 207.61741 | H49: 260.16448 | I49: 342.85328 | J49: 445.15988 | K49: 559.15024 | L49: 687.95303 | M49: 816.22168 | N49: 946.77377 | O49: 1101.6508 | P49: 1259.5743 | R49: =(J49/D49)^(1/6)-1 -> 0.28388852 | S49: =(P49/J49)^(1/6)-1 -> 0.1892814
A50: Growth rate (%) | C50: =C49/B49-1 -> 0.29474262 | D50: =D49/C49-1 -> 0.30162611 | E50: =E49/D49-1 -> 0.29050824 | F50: =F49/E49-1 -> 0.25342794 | G50: =G49/F49-1 -> 0.29137238 | H50: =H49/G49-1 -> 0.25309565 | I50: =I49/H49-1 -> 0.31783277 | J50: =J49/I49-1 -> 0.29839763 | ... P50: =P49/O49-1 -> 0.14335165
A51: Large enterprises (250+ employees) | B51: 18.571429 | C51: 25.027125 | D51: 33.814987 | E51: 45.49401 | F51: 59.942215 | G51: 80.822913 | H51: 105.58117 | I51: 144.62607 | J51: 195.78032 | K51: 254.54494 | L51: 328.19602 | M51: 402.492 | N51: 477.37762 | O51: 571.53722 | P51: 668.73571 | R51: =(J51/D51)^(1/6)-1 -> 0.34001596 | S51: =(P51/J51)^(1/6)-1 -> 0.22719689
A52: Growth rate (%) | C52: =C51/B51-1 -> 0.34761442 | D52: =D51/C51-1 -> 0.35113349 | E52: =E51/D51-1 -> 0.34538009 | F52: =F51/E51-1 -> 0.31758478 | G52: =G51/F51-1 -> 0.34834712 | H52: =H51/G51-1 -> 0.30632715 | I52: =I51/H51-1 -> 0.36980942 | J52: =J51/I51-1 -> 0.35370003 | ... P52: =P51/O51-1 -> 0.17006503
A53: Public administration | B53: 4.9607291 | C53: 6.3800361 | D53: 8.7036896 | E53: 12.436107 | F53: 18.686874 | G53: 27.112579 | H53: 36.294746 | I53: 50.952844 | J53: 71.994647 | K53: 98.460692 | L53: 124.84722 | M53: 149.47994 | N53: 178.86122 | O53: 211.79946 | P53: 243.01225 | R53: =(J53/D53)^(1/6)-1 -> 0.42210873 | S53: =(P53/J53)^(1/6)-1 -> 0.22477034
A54: Growth rate (%) | C54: =C53/B53-1 -> 0.28610854 | D54: =D53/C53-1 -> 0.36420696 | E54: =E53/D53-1 -> 0.42883158 | F54: =F53/E53-1 -> 0.50263056 | G54: =G53/F53-1 -> 0.45088897 | H54: =H53/G53-1 -> 0.33866813 | I54: =I53/H53-1 -> 0.40386281 | J54: =J53/I53-1 -> 0.41296622 | ... P54: =P53/O53-1 -> 0.14736955
A55: Total | B55: =B53+B51+B49+B47 -> 88.06241 | C55: =C53+C51+C49+C47 -> 115.30023 | D55: =D53+D51+D49+D47 -> 152.37797 | E55: =E53+E51+E49+E47 -> 200.85295 | F55: =F53+F51+F49+F47 -> 259.46375 | G55: =G53+G51+G49+G47 -> 343.64057 | H55: =H53+H51+H49+H47 -> 441.06851 | I55: =I53+I51+I49+I47 -> 593.37423 | ... P55: =P53+P51+P49+P47 -> 2482.6408 | R55: =(J55/D55)^(1/6)-1 -> 0.31566583 | S55: =(P55/J55)^(1/6)-1 -> 0.2101885
A56: Growth rate (%) | C56: =C55/B55-1 -> 0.30930134 | D56: =D55/C55-1 -> 0.3215756 | E56: =E55/D55-1 -> 0.31812327 | F56: =F55/E55-1 -> 0.29180948 | G56: =G55/F55-1 -> 0.32442615 | H56: =H55/G55-1 -> 0.28351699 | I56: =I55/H55-1 -> 0.3453108 | J56: =J55/I55-1 -> 0.33188609 | ... P56: =P55/O55-1 -> 0.15659903
A58: Public cloud spending per capita (by size of enterprises) (€ )
A59: Microenterprises (0-9 employees) | B59: =(B47*1000000)/(B34*1000) -> 237.03498 | C59: =(C47*1000000)/(C34*1000) -> 224.98416 | D59: =(D47*1000000)/(D34*1000) -> 224.87356 | E59: =(E47*1000000)/(E34*1000) -> 225.67018 | F59: =(F47*1000000)/(F34*1000) -> 222.26817 | G59: =(G47*1000000)/(G34*1000) -> 227.29163 | H59: =(H47*1000000)/(H34*1000) -> 217.7431 | I59: =(I47*1000000)/(I34*1000) -> 230.03678 | ... P59: =(P47*1000000)/(P34*1000) -> 417.99582 | R59: =(J59/D59)^(1/6)-1 -> 0.022184655 | S59: =(P59/J59)^(1/6)-1 -> 0.084783076
A60: Growth rate (%) | C60: =C59/B59-1 -> -0.050839875 | D60: =D59/C59-1 -> -0.00049158005 | E60: =E59/D59-1 -> 0.0035425547 | F60: =F59/E59-1 -> -0.015075174 | G60: =G59/F59-1 -> 0.022600907 | H60: =H59/G59-1 -> -0.042010051 | I60: =I59/H59-1 -> 0.056459584 | J60: =J59/I59-1 -> 0.11510882 | ... P60: =P59/O59-1 -> 0.093828397
A61: SME (10-249 employees) | B61: =(B49*1000000)/(B36*1000) -> 6299.2711 | C61: =(C49*1000000)/(C36*1000) -> 5647.4569 | D61: =(D49*1000000)/(D36*1000) -> 5155.8269 | E61: =(E49*1000000)/(E36*1000) -> 4852.2097 | F61: =(F49*1000000)/(F36*1000) -> 4594.0871 | G61: =(G49*1000000)/(G36*1000) -> 4383.2574 | H61: =(H49*1000000)/(H36*1000) -> 4386.2726 | I61: =(I49*1000000)/(I36*1000) -> 4688.9064 | ... P61: =(P49*1000000)/(P36*1000) -> 8259.1182 | R61: =(J61/D61)^(1/6)-1 -> -0.0022427911 | S61: =(P61/J61)^(1/6)-1 -> 0.084129141
A62: Growth rate (%) | C62: =C61/B61-1 -> -0.10347454 | D62: =D61/C61-1 -> -0.087053345 | E62: =E61/D61-1 -> -0.058888164 | F62: =F61/E61-1 -> -0.05319691 | G62: =G61/F61-1 -> -0.045891534 | H62: =H61/G61-1 -> 0.00068788518 | I62: =I61/H61-1 -> 0.068995654 | J62: =J61/I61-1 -> 0.084865787 | ... P62: =P61/O61-1 -> 0.096795183
A63: Large enterprises (250+ employees) | B63: =(B51*1000000)/(B38*1000) -> 15052.237 | C63: =(C51*1000000)/(C38*1000) -> 14719.477 | D63: =(D51*1000000)/(D38*1000) -> 14982.129 | E63: =(E51*1000000)/(E38*1000) -> 16253.746 | F63: =(F51*1000000)/(F38*1000) -> 18666.109 | G63: =(G51*1000000)/(G38*1000) -> 21475.546 | H63: =(H51*1000000)/(H38*1000) -> 25169.676 | I63: =(I51*1000000)/(I38*1000) -> 32706.031 | ... P63: =(P51*1000000)/(P38*1000) -> 119025.42 | R63: =(J63/D63)^(1/6)-1 -> 0.1849967 | S63: =(P63/J63)^(1/6)-1 -> 0.1920484
A64: Growth rate (%) | C64: =C63/B63-1 -> -0.02210702 | D64: =D63/C63-1 -> 0.017843851 | E64: =E63/D63-1 -> 0.084875548 | F64: =F63/E63-1 -> 0.14841893 | G64: =G63/F63-1 -> 0.15051003 | H64: =H63/G63-1 -> 0.17201568 | I64: =I63/H63-1 -> 0.29942199 | J64: =J63/I63-1 -> 0.26837751 | ... P64: =P63/O63-1 -> 0.15477265
A65: Total | B65: =(B55*1000000)/(B40*1000) -> 2588.2112 | C65: =(C55*1000000)/(C40*1000) -> 2367.3617 | D65: =(D55*1000000)/(D40*1000) -> 2238.1727 | E65: =(E55*1000000)/(E40*1000) -> 2132.6526 | F65: =(F55*1000000)/(F40*1000) -> 2019.6912 | G65: =(G55*1000000)/(G40*1000) -> 1966.9769 | H65: =(H55*1000000)/(H40*1000) -> 1816.9853 | I65: =(I55*1000000)/(I40*1000) -> 1875.4974 | ... P65: =(P55*1000000)/(P40*1000) -> 2749.5864 | R65: =(J65/D65)^(1/6)-1 -> -0.01804016 | S65: =(P65/J65)^(1/6)-1 -> 0.053906061
A66: Growth rate (%) | C66: =C65/B65-1 -> -0.085329026 | D66: =D65/C65-1 -> -0.054570864 | E66: =E65/D65-1 -> -0.047145656 | F66: =F65/E65-1 -> -0.052967533 | G66: =G65/F65-1 -> -0.026100204 | H66: =H65/G65-1 -> -0.07625486 | I66: =I65/H65-1 -> 0.032202847 | J66: =J65/I65-1 -> 0.069890862 | ... P66: =P65/O65-1 -> 0.071116136
A68: Public cloud (by model) (€ m)
A69: SaaS | B69: 53.578499 | C69: 69.73552 | D69: 90.119048 | E69: 117.27475 | F69: 150.14411 | G69: 197.57828 | H69: 257.0071 | I69: 355.1589 | J69: 481.10248 | K69: 629.21462 | L69: 799.74812 | M69: 965.74315 | N69: 1141.0558 | O69: 1351.6447 | P69: 1565.7601 | R69: =(J69/D69)^(1/6)-1 -> 0.32201637 | S69: =(P69/J69)^(1/6)-1 -> 0.2173476
A70: Growth rate (%) | C70: =C69/B69-1 -> 0.30155794 | D70: =D69/C69-1 -> 0.29229763 | E70: =E69/D69-1 -> 0.30133148 | F70: =F69/E69-1 -> 0.28027649 | G70: =G69/F69-1 -> 0.31592428 | H70: =H69/G69-1 -> 0.30078619 | I70: =I69/H69-1 -> 0.38190308 | J70: =J69/I69-1 -> 0.35461193 | ... P70: =P69/O69-1 -> 0.15841099
A71: IaaS | B71: 30.192971 | C71: 39.733383 | D71: 54.360053 | E71: 72.811365 | F71: 94.936269 | G71: 126.07643 | H71: 158.46219 | I71: 202.08535 | J71: 256.07258 | K71: 310.79494 | L71: 371.43062 | M71: 432.48275 | N71: 491.32679 | O71: 558.86862 | P71: 626.4934 | R71: =(J71/D71)^(1/6)-1 -> 0.29473395 | S71: =(P71/J71)^(1/6)-1 -> 0.16080402
A72: Growth rate (%) | C72: =C71/B71-1 -> 0.3159812 | D72: =D71/C71-1 -> 0.36812043 | E72: =E71/D71-1 -> 0.33942778 | F72: =F71/E71-1 -> 0.30386609 | G72: =G71/F71-1 -> 0.32801121 | H72: =H71/G71-1 -> 0.25687406 | I72: =I71/H71-1 -> 0.2752906 | J72: =J71/I71-1 -> 0.26715066 | ... P72: =P71/O71-1 -> 0.121003
A73: PaaS | B73: 4.2909397 | C73: 5.8313281 | D73: 7.8988717 | E73: 10.766832 | F73: 14.383367 | G73: 19.985861 | H73: 25.599221 | I73: 36.129987 | J73: 53.131826 | K73: 77.329927 | L73: 108.55197 | M73: 143.87669 | N73: 183.69604 | O73: 235.98753 | P73: 290.38733 | R73: =(J73/D73)^(1/6)-1 -> 0.37393108 | S73: =(P73/J73)^(1/6)-1 -> 0.32720238
A74: Growth rate (%) | C74: =C73/B73-1 -> 0.35898627 | D74: =D73/C73-1 -> 0.35455792 | E74: =E73/D73-1 -> 0.36308486 | F74: =F73/E73-1 -> 0.33589588 | G74: =G73/F73-1 -> 0.38951196 | H74: =H73/G73-1 -> 0.28086658 | I74: =I73/H73-1 -> 0.41137056 | J74: =J73/I73-1 -> 0.47057419 | ... P74: =P73/O73-1 -> 0.2305198
A75: Total | B75: =B69+B71+B73 -> 88.06241 | C75: =C69+C71+C73 -> 115.30023 | D75: =D69+D71+D73 -> 152.37797 | E75: =E69+E71+E73 -> 200.85295 | F75: =F69+F71+F73 -> 259.46375 | G75: =G69+G71+G73 -> 343.64057 | H75: =H69+H71+H73 -> 441.06851 | I75: =I69+I71+I73 -> 593.37423 | ... P75: =P69+P71+P73 -> 2482.6408 | R75: =(J75/D75)^(1/6)-1 -> 0.31566583 | S75: =(P75/J75)^(1/6)-1 -> 0.2101885
A76: Growth rate (%) | C76: =C75/B75-1 -> 0.30930134 | D76: =D75/C75-1 -> 0.3215756 | E76: =E75/D75-1 -> 0.31812327 | F76: =F75/E75-1 -> 0.29180948 | G76: =G75/F75-1 -> 0.32442615 | H76: =H75/G75-1 -> 0.28351699 | I76: =I75/H75-1 -> 0.3453108 | J76: =J75/I75-1 -> 0.33188609 | ... P76: =P75/O75-1 -> 0.15659903
A78: SaaS spending (by advanced and basic solutions) (€ m)
A79: Basic | B79: 38.254128 | C79: 48.405273 | D79: 61.755045 | E79: 74.887823 | F79: 90.855635 | G79: 116.5698 | H79: 148.57923 | I79: 201.46322 | J79: 261.60259 | K79: 334.05312 | L79: 415.96472 | M79: 493.88179 | N79: 575.94585 | O79: 676.04131 | P79: 779.18816 | R79: =(J79/D79)^(1/6)-1 -> 0.27202291 | S79: =(P79/J79)^(1/6)-1 -> 0.19949945
A80: Growth rate (%) | C80: =C79/B79-1 -> 0.26536078 | D80: =D79/C79-1 -> 0.27579169 | E80: =E79/D79-1 -> 0.21265919 | F80: =F79/E79-1 -> 0.21322309 | G80: =G79/F79-1 -> 0.28302224 | H80: =H79/G79-1 -> 0.27459455 | I80: =I79/H79-1 -> 0.35593119 | J80: =J79/I79-1 -> 0.29851291 | ... P80: =P79/O79-1 -> 0.15257478
A81: Advanced | B81: 15.324371 | C81: 21.330248 | D81: 28.364003 | E81: 42.386931 | F81: 59.288474 | G81: 81.008478 | H81: 108.42786 | I81: 153.69568 | J81: 219.49989 | K81: 295.1615 | L81: 383.7834 | M81: 471.86137 | N81: 565.10991 | O81: 675.60339 | P81: 786.5719 | R81: =(J81/D81)^(1/6)-1 -> 0.40640737 | S81: =(P81/J81)^(1/6)-1 -> 0.23704079
A82: Growth rate (%) | C82: =C81/B81-1 -> 0.39191668 | D82: =D81/C81-1 -> 0.32975496 | E82: =E81/D81-1 -> 0.49439174 | F82: =F81/E81-1 -> 0.3987442 | G82: =G81/F81-1 -> 0.36634445 | H82: =H81/G81-1 -> 0.3384755 | I82: =I81/H81-1 -> 0.41749249 | J82: =J81/I81-1 -> 0.42814613 | ... P82: =P81/O81-1 -> 0.16425098
A83: Total | B83: =B79+B81 -> 53.578499 | C83: =C79+C81 -> 69.73552 | D83: =D79+D81 -> 90.119048 | E83: =E79+E81 -> 117.27475 | F83: =F79+F81 -> 150.14411 | G83: =G79+G81 -> 197.57828 | H83: =H79+H81 -> 257.0071 | I83: =I79+I81 -> 355.1589 | ... P83: =P79+P81 -> 1565.7601 | R83: =(J83/D83)^(1/6)-1 -> 0.32201637 | S83: =(P83/J83)^(1/6)-1 -> 0.2173476
A84: Growth rate (%) | C84: =C83/B83-1 -> 0.30155794 | D84: =D83/C83-1 -> 0.29229763 | E84: =E83/D83-1 -> 0.30133148 | F84: =F83/E83-1 -> 0.28027649 | G84: =G83/F83-1 -> 0.31592428 | H84: =H83/G83-1 -> 0.30078619 | I84: =I83/H83-1 -> 0.38190308 | J84: =J83/I83-1 -> 0.35461193 | ... P84: =P83/O83-1 -> 0.15841099
A86: IaaS spending (by hyper and shared solutions) (€ m)
A87: Hyper | B87: 12.681048 | C87: 17.438982 | D87: 24.932265 | E87: 34.897742 | F87: 47.549572 | G87: 65.987951 | H87: 86.670779 | I87: 115.5043 | J87: 152.94761 | K87: 193.98576 | L87: 242.26456 | M87: 294.7795 | N87: 349.95743 | O87: 415.97841 | P87: 487.29713 | R87: =(J87/D87)^(1/6)-1 -> 0.35299697 | S87: =(P87/J87)^(1/6)-1 -> 0.2130402
A88: Growth rate (%) | C88: =C87/B87-1 -> 0.37520036 | D88: =D87/C87-1 -> 0.42968585 | E88: =E87/D87-1 -> 0.39970203 | F88: =F87/E87-1 -> 0.36254006 | G88: =G87/F87-1 -> 0.38777172 | H88: =H87/G87-1 -> 0.31343339 | I88: =I87/H87-1 -> 0.33267868 | J88: =J87/I87-1 -> 0.32417244 | ... P88: =P87/O87-1 -> 0.17144813
A89: Shared | B89: 17.511923 | C89: 22.294401 | D89: 29.427787 | E89: 37.913622 | F89: 47.386697 | G89: 60.088479 | H89: 71.791416 | I89: 86.581048 | J89: 103.12497 | K89: 116.80918 | L89: 129.16605 | M89: 137.70325 | N89: 141.36936 | O89: 142.89021 | P89: 139.19627 | R89: =(J89/D89)^(1/6)-1 -> 0.23244545 | S89: =(P89/J89)^(1/6)-1 -> 0.051261172
A90: Growth rate (%) | C90: =C89/B89-1 -> 0.27309837 | D90: =D89/C89-1 -> 0.31996313 | E90: =E89/D89-1 -> 0.28836129 | F90: =F89/E89-1 -> 0.2498594 | G90: =G89/F89-1 -> 0.2680453 | H90: =H89/G89-1 -> 0.19476174 | I90: =I89/H89-1 -> 0.20600837 | J90: =J89/I89-1 -> 0.19108019 | ... P90: =P89/O89-1 -> -0.025851621
A91: Total | B91: =B89+B87 -> 30.192971 | C91: =C89+C87 -> 39.733383 | D91: =D89+D87 -> 54.360053 | E91: =E89+E87 -> 72.811365 | F91: =F89+F87 -> 94.936269 | G91: =G89+G87 -> 126.07643 | H91: =H89+H87 -> 158.46219 | I91: =I89+I87 -> 202.08535 | ... P91: =P89+P87 -> 626.4934 | R91: =(J91/D91)^(1/6)-1 -> 0.29473395 | S91: =(P91/J91)^(1/6)-1 -> 0.16080402
A92: Growth rate (%) | C92: =C91/B91-1 -> 0.3159812 | D92: =D91/C91-1 -> 0.36812043 | E92: =E91/D91-1 -> 0.33942778 | F92: =F91/E91-1 -> 0.30386609 | G92: =G91/F91-1 -> 0.32801121 | H92: =H91/G91-1 -> 0.25687406 | I92: =I91/H91-1 -> 0.2752906 | J92: =J91/I91-1 -> 0.26715066 | ... P92: =P91/O91-1 -> 0.121003
A94: PaaS spending (by hyper and shared solutions) (€ m)
A95: Hyper | B95: 2.5745638 | C95: 3.5862668 | D95: 4.9792513 | E95: 6.9568206 | F95: 9.5259276 | G95: 13.5673 | H95: 17.812349 | I95: 25.76832 | J95: 38.841583 | K95: 57.94469 | L95: 83.373422 | M95: 113.26721 | N95: 148.23045 | O95: 195.18685 | P95: 246.18582 | R95: =(J95/D95)^(1/6)-1 -> 0.40827935 | S95: =(P95/J95)^(1/6)-1 -> 0.36038244
A96: Growth rate (%) | C96: =C95/B95-1 -> 0.39296093 | D96: =D95/C95-1 -> 0.38842187 | E96: =E95/D95-1 -> 0.39716198 | F96: =F95/E95-1 -> 0.36929327 | G96: =G95/F95-1 -> 0.42424976 | H96: =H95/G95-1 -> 0.31288825 | I96: =I95/H95-1 -> 0.44665482 | J96: =J95/I95-1 -> 0.50733855 | ... P96: =P95/O95-1 -> 0.26128279
A97: Shared | B97: 1.7163759 | C97: 2.2450613 | D97: 2.9196205 | E97: 3.8100119 | F97: 4.8574395 | G97: 6.4185605 | H97: 7.7868721 | I97: 10.361666 | J97: 14.290244 | K97: 19.385238 | L97: 25.178551 | M97: 30.609479 | N97: 35.465589 | O97: 40.80068 | P97: 44.201513 | R97: =(J97/D97)^(1/6)-1 -> 0.30302337 | S97: =(P97/J97)^(1/6)-1 -> 0.20707128
A98: Growth rate (%) | C98: =C97/B97-1 -> 0.30802428 | D98: =D97/C97-1 -> 0.30046356 | E98: =E97/D97-1 -> 0.30496822 | F98: =F97/E97-1 -> 0.27491452 | G98: =G97/F97-1 -> 0.32138764 | H98: =H97/G97-1 -> 0.21318045 | I98: =I97/H97-1 -> 0.33065835 | J98: =J97/I97-1 -> 0.3791453 | ... P98: =P97/O97-1 -> 0.083352346
A99: Total | B99: =B97+B95 -> 4.2909397 | C99: =C97+C95 -> 5.8313281 | D99: =D97+D95 -> 7.8988717 | E99: =E97+E95 -> 10.766832 | F99: =F97+F95 -> 14.383367 | G99: =G97+G95 -> 19.985861 | H99: =H97+H95 -> 25.599221 | I99: =I97+I95 -> 36.129987 | ... P99: =P97+P95 -> 290.38733 | R99: =(J99/D99)^(1/6)-1 -> 0.37393108 | S99: =(P99/J99)^(1/6)-1 -> 0.32720238
A100: Growth rate (%) | C100: =C99/B99-1 -> 0.35898627 | D100: =D99/C99-1 -> 0.35455792 | E100: =E99/D99-1 -> 0.36308486 | F100: =F99/E99-1 -> 0.33589588 | G100: =G99/F99-1 -> 0.38951196 | H100: =H99/G99-1 -> 0.28086658 | I100: =I99/H99-1 -> 0.41137056 | J100: =J99/I99-1 -> 0.47057419 | ... P100: =P99/O99-1 -> 0.2305198
A102: Private cloud (by size of enterprises) (€ m)
A103: Microenterprises (0-9 employees) | B103: 0.00083413181 | C103: 0.0017515455 | D103: 0.0024121129 | E103: 0.004465053 | F103: 0.0053877943 | G103: 0.0086584365 | H103: 0.011059715 | I103: 0.014074862 | J103: 0.017386201 | K103: 0.021059926 | L103: 0.024882411 | M103: 0.028663312 | N103: 0.03201332 | O103: 0.03591994 | P103: 0.039415427 | R103: =(J103/D103)^(1/6)-1 -> 0.38984972 | S103: =(P103/J103)^(1/6)-1 -> 0.14615562
A104: Growth rate (%) | C104: =C103/B103-1 -> 1.0998426 | D104: =D103/C103-1 -> 0.37713407 | E104: =E103/D103-1 -> 0.85109618 | F104: =F103/E103-1 -> 0.20665851 | G104: =G103/F103-1 -> 0.60704661 | H104: =H103/G103-1 -> 0.27733395 | I104: =I103/H103-1 -> 0.27262426 | J104: =J103/I103-1 -> 0.23526624 | ... P104: =P103/O103-1 -> 0.097313257
A105: SME (10-249 employees) | B105: 4.1706595 | C105: 5.8384847 | D105: 8.0403763 | E105: 11.162633 | F105: 13.469486 | G105: 17.316873 | H105: 22.11943 | I105: 28.149723 | J105: 34.772402 | K105: 44.010298 | L105: 55.959547 | M105: 69.457243 | N105: 84.742108 | O105: 103.23317 | P105: 124.33038 | R105: =(J105/D105)^(1/6)-1 -> 0.27641839 | S105: =(P105/J105)^(1/6)-1 -> 0.23658439
A106: Growth rate (%) | C106: =C105/B105-1 -> 0.39989483 | D106: =D105/C105-1 -> 0.3771341 | E106: =E105/D105-1 -> 0.38832218 | F106: =F105/E105-1 -> 0.20665852 | G106: =G105/F105-1 -> 0.28563726 | H106: =H105/G105-1 -> 0.27733394 | I106: =I105/H105-1 -> 0.27262428 | J106: =J105/I105-1 -> 0.23526623 | ... P106: =P105/O105-1 -> 0.20436457
A107: Large enterprises (250+ employees) | B107: 41.124595 | C107: 53.715666 | D107: 68.352345 | E107: 85.968784 | F107: 95.848113 | G107: 110.96915 | H107: 132.03405 | I107: 169.95103 | J107: 212.96724 | K107: 260.5686 | L107: 311.30325 | M107: 359.91962 | N107: 406.63907 | O107: 461.08406 | P107: 511.93775 | R107: =(J107/D107)^(1/6)-1 -> 0.20853685 | S107: =(P107/J107)^(1/6)-1 -> 0.15740155
A108: Growth rate (%) | C108: =C107/B107-1 -> 0.30616889 | D108: =D107/C107-1 -> 0.27248435 | E108: =E107/D107-1 -> 0.25772984 | F108: =F107/E107-1 -> 0.11491763 | G108: =G107/F107-1 -> 0.15776038 | H108: =H107/G107-1 -> 0.18982669 | I108: =I107/H107-1 -> 0.28717574 | J108: =J107/I107-1 -> 0.25310944 | ... P108: =P107/O107-1 -> 0.11029157
A109: Public administration | B109: 6.1182012 | C109: 8.0825906 | D109: 10.709179 | E109: 14.292323 | F109: 16.709999 | G109: 20.539396 | H109: 26.206273 | I109: 35.327865 | J109: 45.588832 | K109: 57.167162 | L109: 72.50256 | M109: 84.7617 | N109: 96.433822 | O109: 112.56021 | P109: 126.73506 | R109: =(J109/D109)^(1/6)-1 -> 0.27306443 | S109: =(P109/J109)^(1/6)-1 -> 0.18578618
A110: Growth rate (%) | C110: =C109/B109-1 -> 0.32107303 | D110: =D109/C109-1 -> 0.32496857 | E110: =E109/D109-1 -> 0.33458631 | F110: =F109/E109-1 -> 0.16915907 | G110: =G109/F109-1 -> 0.22916797 | H110: =H109/G109-1 -> 0.2759028 | I110: =I109/H109-1 -> 0.34806907 | J110: =J109/I109-1 -> 0.29044967 | ... P110: =P109/O109-1 -> 0.12593131
A111: Total | B111: =B109+B107+B105+B103 -> 51.41429 | C111: =C109+C107+C105+C103 -> 67.638493 | D111: =D109+D107+D105+D103 -> 87.104312 | E111: =E109+E107+E105+E103 -> 111.4282 | F111: =F109+F107+F105+F103 -> 126.03299 | G111: =G109+G107+G105+G103 -> 148.83408 | H111: =H109+H107+H105+H103 -> 180.37082 | I111: =I109+I107+I105+I103 -> 233.44269 | ... P111: =P109+P107+P105+P103 -> 763.0426 | R111: =(J111/D111)^(1/6)-1 -> 0.22430621 | S111: =(P111/J111)^(1/6)-1 -> 0.17272127
A112: Growth rate (%) | C112: =C111/B111-1 -> 0.31555825 | D112: =D111/C111-1 -> 0.28779202 | E112: =E111/D111-1 -> 0.27925016 | F112: =F111/E111-1 -> 0.13106898 | G112: =G111/F111-1 -> 0.18091367 | H112: =H111/G111-1 -> 0.21189194 | I112: =I111/H111-1 -> 0.29423761 | J112: =J111/I111-1 -> 0.25660759 | ... P112: =P111/O111-1 -> 0.1272382
A114: Private cloud spending per capita (by size of enterprises) (€ )
...

Sheet Austria
A1: Year | B1: 2016 | C1: 2017 | D1: 2018 | E1: 2019 | F1: 2020 | G1: 2021 | H1: 2022 | I1: 2023 | J1: 2024 | K1: 2025e | L1: 2026f | M1: 2027f | N1: 2028f | O1: 2029f | P1: 2030f | R1: CAGR 2019-2024 | S1: CAGR 2025-2030
A2: Total IT market size (€ m) | B2: =B4+B6+B8 -> 8368.9756 | C2: =C4+C6+C8 -> 8630.2134 | D2: =D4+D6+D8 -> 8986.2049 | E2: =E4+E6+E8 -> 9498.9866 | F2: =F4+F6+F8 -> 9832.2746 | G2: =G4+G6+G8 -> 10524.045 | H2: =H4+H6+H8 -> 11274.648 | I2: =I4+I6+I8 -> 12127.578 | ... P2: =P4+P6+P8 -> 18970.184 | R2: =(J2/D2)^(1/6)-1 -> 0.068402149 | S2: =(P2/J2)^(1/6)-1 -> 0.060102322
A3: Growth rate (%) | C3: =C2/B2-1 -> 0.031215027 | D3: =D2/C2-1 -> 0.04124944 | E3: =E2/D2-1 -> 0.057063212 | F3: =F2/E2-1 -> 0.035086697 | G3: =G2/F2-1 -> 0.070357078 | H3: =H2/G2-1 -> 0.071322709 | I3: =I2/H2-1 -> 0.075650242 | J3: =J2/I2-1 -> 0.102074 | ... P3: =P2/O2-1 -> 0.061319738
A4: Software | B4: 1662.9582 | C4: 1717.4788 | D4: 1800.1739 | E4: 1937.517 | F4: 2073.4693 | G4: 2211.7819 | H4: 2405.1331 | I4: 2628.633 | J4: 2950.5118 | K4: 3153.5526 | L4: 3379.7323 | M4: 3598.2954 | N4: 3848.6725 | O4: 4123.2591 | P4: 4419.714 | R4: =(J4/D4)^(1/6)-1 -> 0.08583495 | S4: =(P4/J4)^(1/6)-1 -> 0.069669149
A5: Growth rate (%) | C5: =C4/B4-1 -> 0.032785325 | D5: =D4/C4-1 -> 0.048149087 | E5: =E4/D4-1 -> 0.07629439 | F5: =F4/E4-1 -> 0.070168295 | G5: =G4/F4-1 -> 0.066705875 | H5: =H4/G4-1 -> 0.087418774 | I5: =I4/H4-1 -> 0.092926202 | J5: =J4/I4-1 -> 0.122451 | ... P5: =P4/O4-1 -> 0.071898199
A6: Hardware | B6: 2440.5791 | C6: 2529.0914 | D6: 2669.0222 | E6: 2834.7458 | F6: 2845.5733 | G6: 3107.097 | H6: 3341.4065 | I6: 3555.6523 | J6: 3874.037 | K6: 4047.8903 | L6: 4225.7339 | M6: 4388.1225 | N6: 4550.5811 | O6: 4711.3948 | P6: 4866.5709 | R6: =(J6/D6)^(1/6)-1 -> 0.064066073 | S6: =(P6/J6)^(1/6)-1 -> 0.038747234
A7: Growth rate (%) | C7: =C6/B6-1 -> 0.036266915 | D7: =D6/C6-1 -> 0.055328517 | E7: =E6/D6-1 -> 0.062091496 | F7: =F6/E6-1 -> 0.0038195704 | G7: =G6/F6-1 -> 0.091905439 | H7: =H6/G6-1 -> 0.075411068 | I7: =I6/H6-1 -> 0.064118456 | J7: =J6/I6-1 -> 0.089543263 | ... P7: =P6/O6-1 -> 0.032936326
A8: Services | B8: 4265.4383 | C8: 4383.6432 | D8: 4517.0087 | E8: 4726.7237 | F8: 4913.232 | G8: 5205.1658 | H8: 5528.1085 | I8: 5943.2926 | J8: 6540.9395 | K8: 6934.3854 | L8: 7396.5789 | M8: 7888.4795 | N8: 8439.8015 | O8: 9039.4922 | P8: 9683.8992 | R8: =(J8/D8)^(1/6)-1 -> 0.063648668 | S8: =(P8/J8)^(1/6)-1 -> 0.067583093
A9: Growth rate (%) | C9: =C8/B8-1 -> 0.027712251 | D9: =D8/C8-1 -> 0.030423451 | E9: =E8/D8-1 -> 0.04642784 | F9: =F8/E8-1 -> 0.039458257 | G9: =G8/F8-1 -> 0.059417887 | H9: =H8/G8-1 -> 0.062042713 | I9: =I8/H8-1 -> 0.075104196 | J9: =J8/I8-1 -> 0.10055822 | ... P9: =P8/O8-1 -> 0.071287966
A11: Smartphones market size (€ m) | B11: 357.45165 | C11: 357.604 | D11: 364.66455 | E11: 423.86621 | F11: 384.2223 | G11: 441.18317 | H11: 476.93773 | I11: 494.51609 | J11: 521.13991 | K11: 538.35181 | L11: 557.0896 | M11: 569.69614 | N11: 589.35989 | O11: 610.84604 | P11: 630.99353 | R11: =(J11/D11)^(1/6)-1 -> 0.061312951 | S11: =(P11/J11)^(1/6)-1 -> 0.032393106
A12: Growth rate (%) | C12: =C11/B11-1 -> 0.00042622716 | D12: =D11/C11-1 -> 0.01974404 | E12: =E11/D11-1 -> 0.16234553 | F12: =F11/E11-1 -> -0.093529285 | G12: =G11/F11-1 -> 0.14824976 | H12: =H11/G11-1 -> 0.081042431 | I12: =I11/H11-1 -> 0.036856721 | J12: =J11/I11-1 -> 0.053838126 | ... P12: =P11/O11-1 -> 0.032982916
A14: Cybersecurity market size (€ m) | B14: 232.75924 | C14: 248.63926 | D14: 275.65596 | E14: 296.51917 | F14: 292.90644 | G14: 312.74389 | H14: 356.86804 | I14: 390.10576 | J14: 426.21773 | K14: 460.35591 | L14: 501.10123 | M14: 539.77664 | N14: 575.4165 | O14: 612.43127 | P14: 656.22253 | R14: =(J14/D14)^(1/6)-1 -> 0.075335591 | S14: =(P14/J14)^(1/6)-1 -> 0.074574681
A15: Growth rate (%) | C15: =C14/B14-1 -> 0.068225083 | D15: =D14/C14-1 -> 0.10865823 | E15: =E14/D14-1 -> 0.075685669 | F15: =F14/E14-1 -> -0.012183799 | G15: =G14/F14-1 -> 0.06772623 | H15: =H14/G14-1 -> 0.14108718 | I15: =I14/H14-1 -> 0.093137281 | J15: =J14/I14-1 -> 0.092569695 | ... P15: =P14/O14-1 -> 0.071503961
A17: Enterprises (by size) (number of enterprises in thousands)
A18: Microenterprises (0-9 employees) | B18: 281.806 | C18: 289.874 | D18: 274.768 | E18: 288.827 | F18: 290.791 | G18: 362.34 | H18: 363.389 | I18: 364.029 | J18: 366.76515 | K18: 370.13611 | L18: 375.6291 | M18: 381.82012 | N18: 387.89707 | O18: 393.35244 | P18: 397.5212 | R18: =(J18/D18)^(1/6)-1 -> 0.049309614 | S18: =(P18/J18)^(1/6)-1 -> 0.013511556
A19: Growth rate (%) | C19: =C18/B18-1 -> 0.028629625 | D19: =D18/C18-1 -> -0.052112297 | E19: =E18/D18-1 -> 0.051166803 | F19: =F18/E18-1 -> 0.0067999183 | G19: =G18/F18-1 -> 0.24604957 | H19: =H18/G18-1 -> 0.0028950709 | I19: =I18/H18-1 -> 0.0017611981 | J19: =J18/I18-1 -> 0.0075163044 | ... P19: =P18/O18-1 -> 0.010598019
A20: SME (10-249 employees) | B20: 41.016 | C20: 41.754 | D20: 40.61 | E20: 41.11 | F20: 38.633 | G20: 40.821 | H20: 43.064 | I20: 42.944 | J20: 42.79749 | K20: 42.380304 | L20: 42.313408 | M20: 42.441167 | N20: 42.631269 | O20: 42.823707 | P20: 42.832461 | R20: =(J20/D20)^(1/6)-1 -> 0.0087825285 | S20: =(P20/J20)^(1/6)-1 -> 0.00013613969
A21: Growth rate (%) | C21: =C20/B20-1 -> 0.017992978 | D21: =D20/C20-1 -> -0.027398573 | E21: =E20/D20-1 -> 0.012312238 | F21: =F20/E20-1 -> -0.06025298 | G21: =G20/F20-1 -> 0.056635519 | H21: =H20/G20-1 -> 0.054947209 | I21: =I20/H20-1 -> -0.0027865503 | J21: =J20/I20-1 -> -0.0034116479 | ... P21: =P20/O20-1 -> 0.0002044233
A22: Large enterprises (250+ employees) | B22: 1.09 | C22: 1.127 | D22: 1.184 | E22: 1.208 | F22: 1.201 | G22: 1.209 | H22: 1.256 | I22: 1.301 | J22: 1.3149422 | K22: 1.3276126 | L22: 1.3456243 | M22: 1.3675578 | N22: 1.3905329 | O22: 1.413483 | P22: 1.4339748 | R22: =(J22/D22)^(1/6)-1 -> 0.017636078 | S22: =(P22/J22)^(1/6)-1 -> 0.014547705
A23: Growth rate (%) | C23: =C22/B22-1 -> 0.033944954 | D23: =D22/C22-1 -> 0.050576752 | E23: =E22/D22-1 -> 0.02027027 | F23: =F22/E22-1 -> -0.005794702 | G23: =G22/F22-1 -> 0.0066611157 | H23: =H22/G22-1 -> 0.038875103 | I23: =I22/H22-1 -> 0.035828025 | J23: =J22/I22-1 -> 0.010716555 | ... P23: =P22/O22-1 -> 0.014497362
A24: Number of all enterprises | B24: =B18+B20+B22 -> 323.912 | C24: =C18+C20+C22 -> 332.755 | D24: =D18+D20+D22 -> 316.562 | E24: =E18+E20+E22 -> 331.145 | F24: =F18+F20+F22 -> 330.625 | G24: =G18+G20+G22 -> 404.37 | H24: =H18+H20+H22 -> 407.709 | I24: =I18+I20+I22 -> 408.274 | ... P24: =P18+P20+P22 -> 441.78764 | R24: =(J24/D24)^(1/6)-1 -> 0.044421038 | S24: =(P24/J24)^(1/6)-1 -> 0.012162364
A25: Growth rate (%) | C25: =C24/B24-1 -> 0.027300625 | D25: =D24/C24-1 -> -0.048663431 | E25: =E24/D24-1 -> 0.046066805 | F25: =F24/E24-1 -> -0.0015703091 | G25: =G24/F24-1 -> 0.22304726 | H25: =H24/G24-1 -> 0.0082572891 | I25: =I24/H24-1 -> 0.0013857923 | J25: =J24/I24-1 -> 0.0063770537 | ... P25: =P24/O24-1 -> 0.0095934691
A27: Percentage of enterprises using cloud computing
A28: Percent of microenterprises using cloud computing | B28: 0.093093526 | C28: 0.10633418 | D28: 0.12120635 | E28: 0.13783776 | F28: 0.15634526 | G28: 0.17682809 | H28: 0.19936026 | I28: 0.22398235 | J28: 0.25069323 | K28: 0.27944245 | L28: 0.31012405 | M28: 0.34257279 | N28: 0.37656347 | O28: 0.41181415 | P28: 0.44799345
A29: Percent of SME using cloud computing | B29: 0.17472977 | C29: 0.20680555 | D29: 0.24303554 | E29: 0.28334532 | F29: 0.32744872 | G29: 0.37482648 | H29: 0.42473015 | I29: 0.47621687 | J29: 0.52821412 | K29: 0.57960628 | L29: 0.62932874 | M29: 0.6764531 | N29: 0.72024957 | O29: 0.76021903 | P29: 0.79609455
A30: Percent of large enterprises using cloud computing | B30: 0.31789668 | C30: 0.40648038 | D30: 0.50159636 | E30: 0.59659694 | F30: 0.68486608 | G30: 0.76154083 | H30: 0.82434478 | I30: 0.8733585 | J30: 0.91018582 | K30: 0.93707537 | L30: 0.95630094 | M30: 0.96984151 | N30: 0.97927732 | O30: 0.98580413 | P30: 0.99029562
A31: Percent of all enterprises using cloud computing | B31: 0.10418736 | C31: 0.11995785 | D31: 0.13825788 | E31: 0.15757533 | F31: 0.17825828 | G31: 0.19856415 | H31: 0.22509016 | I31: 0.25258275 | J31: 0.28171072 | K31: 0.31229085 | L31: 0.34441109 | M31: 0.37788078 | N31: 0.41242638 | O31: 0.44776407 | P31: 0.48350299
A33: Number of enterprises using cloud computing (thousands)
A34: Number of microenterprises using cloud computing | B34: =B28*B18 -> 26.234314 | C34: =C28*C18 -> 30.823513 | D34: =D28*D18 -> 33.303627 | E34: =E28*E18 -> 39.811268 | F34: =F28*F18 -> 45.463794 | G34: =G28*G18 -> 64.07189 | H34: =H28*H18 -> 72.445327 | I34: =I28*I18 -> 81.536072 | ... P34: =P28*P18 -> 178.0869 | R34: =(J34/D34)^(1/6)-1 -> 0.18442216 | S34: =(P34/J34)^(1/6)-1 -> 0.11647811
A35: Growth rate (%) | C35: =C34/B34-1 -> 0.17493116 | D35: =D34/C34-1 -> 0.080461748 | E35: =E34/D34-1 -> 0.19540336 | F35: =F34/E34-1 -> 0.14198309 | G35: =G34/F34-1 -> 0.40929482 | H35: =H34/G34-1 -> 0.13068815 | I35: =I34/H34-1 -> 0.12548422 | J35: =J34/I34-1 -> 0.12766704 | ... P35: =P34/O34-1 -> 0.099382566
A36: Number of SME using cloud computing | B36: =B29*B20 -> 7.1667162 | C36: =C29*C20 -> 8.6349588 | D36: =D29*D20 -> 9.8696734 | E36: =E29*E20 -> 11.648326 | F36: =F29*F20 -> 12.650326 | G36: =G29*G20 -> 15.300792 | H36: =H29*H20 -> 18.290579 | I36: =I29*I20 -> 20.450657 | ... P36: =P29*P20 -> 34.098689 | R36: =(J36/D36)^(1/6)-1 -> 0.14812081 | S36: =(P36/J36)^(1/6)-1 -> 0.070906518
A37: Growth rate (%) | C37: =C36/B36-1 -> 0.20486965 | D37: =D36/C36-1 -> 0.14299022 | E37: =E36/D36-1 -> 0.18021393 | F37: =F36/E36-1 -> 0.086020972 | G37: =G36/F36-1 -> 0.20951754 | H37: =H36/G36-1 -> 0.19540084 | I37: =I36/H36-1 -> 0.11809785 | J37: =J36/I36-1 -> 0.10540401 | ... P37: =P36/O36-1 -> 0.047405101
A38: Number of large enterprises using cloud computing | B38: =B30*B22 -> 0.34650739 | C38: =C30*C22 -> 0.45810339 | D38: =D30*D22 -> 0.59389009 | E38: =E30*E22 -> 0.72068911 | F38: =F30*F22 -> 0.82252416 | G38: =G30*G22 -> 0.92070286 | H38: =H30*H22 -> 1.035377 | I38: =I30*I22 -> 1.1362394 | ... P38: =P30*P22 -> 1.4200589 | R38: =(J38/D38)^(1/6)-1 -> 0.12388475 | S38: =(P38/J38)^(1/6)-1 -> 0.028912093
A39: Growth rate (%) | C39: =C38/B38-1 -> 0.32205951 | D39: =D38/C38-1 -> 0.29641061 | E39: =E38/D38-1 -> 0.21350586 | F39: =F38/E38-1 -> 0.14130234 | G39: =G38/F38-1 -> 0.1193627 | H39: =H38/G38-1 -> 0.12455069 | I39: =I38/H38-1 -> 0.097416069 | J39: =J38/I38-1 -> 0.053335921 | ... P39: =P38/O38-1 -> 0.01911959
A40: Number of all enterprises using cloud computing | B40: =B38+B36+B34 -> 33.747538 | C40: =C38+C36+C34 -> 39.916575 | D40: =D38+D36+D34 -> 43.767191 | E40: =E38+E36+E34 -> 52.180283 | F40: =F38+F36+F34 -> 58.936645 | G40: =G38+G36+G34 -> 80.293385 | H40: =H38+H36+H34 -> 91.771283 | I40: =I38+I36+I34 -> 103.12297 | ... P40: =P38+P36+P34 -> 213.60564 | R40: =(J40/D40)^(1/6)-1 -> 0.17596535 | S40: =(P40/J40)^(1/6)-1 -> 0.10751466
A41: Growth rate (%) | C41: =C40/B40-1 -> 0.18279964 | D41: =D40/C40-1 -> 0.09646657 | E41: =E40/D40-1 -> 0.19222372 | F41: =F40/E40-1 -> 0.12948113 | G41: =G40/F40-1 -> 0.36236776 | H41: =H40/G40-1 -> 0.14294949 | I41: =I40/H40-1 -> 0.1236954 | J41: =J40/I40-1 -> 0.12243299 | ... P41: =P40/O40-1 -> 0.090175588
A43: Total cloud computing market size (€ m) | B43: =B55+B111 -> 236.34883 | C43: =C55+C111 -> 288.21114 | D43: =D55+D111 -> 367.82254 | E43: =E55+E111 -> 479.91136 | F43: =F55+F111 -> 593.73796 | G43: =G55+G111 -> 726.42339 | H43: =H55+H111 -> 881.46151 | I43: =I55+I111 -> 1053.5603 | ... P43: =P55+P111 -> 3202.5393 | R43: =(J43/D43)^(1/6)-1 -> 0.22510458 | S43: =(P43/J43)^(1/6)-1 -> 0.17076444
A44: Growth rate (%) | C44: =C43/B43-1 -> 0.21943122 | D44: =D43/C43-1 -> 0.27622596 | E44: =E43/D43-1 -> 0.30473614 | F44: =F43/E43-1 -> 0.23718253 | G44: =G43/F43-1 -> 0.22347475 | H44: =H43/G43-1 -> 0.21342666 | I44: =I43/H43-1 -> 0.19524257 | J44: =J43/I43-1 -> 0.18036931 | ... P44: =P43/O43-1 -> 0.13263527
A46: Public cloud (by size of enterprises) (€ m)
A47: Microenterprises (0-9 employees) | B47: 5.180834 | C47: 6.5971936 | D47: 8.8687603 | E47: 12.20035 | F47: 15.960109 | G47: 20.456554 | H47: 25.93142 | I47: 32.477676 | J47: 40.001443 | K47: 48.579981 | L47: 61.037106 | M47: 77.181318 | N47: 93.444912 | O47: 110.68035 | P47: 129.12849 | R47: =(J47/D47)^(1/6)-1 -> 0.2853916 | S47: =(P47/J47)^(1/6)-1 -> 0.21569436
A48: Growth rate (%) | C48: =C47/B47-1 -> 0.27338449 | D48: =D47/C47-1 -> 0.34432318 | E48: =E47/D47-1 -> 0.37565448 | F48: =F47/E47-1 -> 0.30816812 | G48: =G47/F47-1 -> 0.28173021 | H48: =H47/G47-1 -> 0.26763387 | I48: =I47/H47-1 -> 0.25244494 | J48: =J47/I47-1 -> 0.23165965 | ... P48: =P47/O47-1 -> 0.16667951
A49: SME (10-249 employees) | B49: 147.50506 | C49: 172.59995 | D49: 213.62431 | E49: 270.98897 | F49: 327.31034 | G49: 387.73305 | H49: 454.59266 | I49: 526.853 | J49: 600.61818 | K49: 674.13597 | L49: 783.12619 | M49: 915.01057 | N49: 1022.7325 | O49: 1117.0334 | P49: 1199.9802 | R49: =(J49/D49)^(1/6)-1 -> 0.18802241 | S49: =(P49/J49)^(1/6)-1 -> 0.12226633
A50: Growth rate (%) | C50: =C49/B49-1 -> 0.17012902 | D50: =D49/C49-1 -> 0.23768468 | E50: =E49/D49-1 -> 0.26853057 | F50: =F49/E49-1 -> 0.20783639 | G50: =G49/F49-1 -> 0.18460374 | H50: =H49/G49-1 -> 0.17243721 | I50: =I49/H49-1 -> 0.15895625 | J50: =J49/I49-1 -> 0.14001095 | ... P50: =P49/O49-1 -> 0.07425635
A51: Large enterprises (250+ employees) | B51: 16.173232 | C51: 24.116113 | D51: 36.675309 | E51: 55.743445 | F51: 79.207904 | G51: 108.87319 | H51: 146.54522 | I51: 193.36574 | J51: 249.32447 | K51: 315.57628 | L51: 411.26601 | M51: 537.44341 | N51: 670.36576 | O51: 815.82216 | P51: 975.67225 | R51: =(J51/D51)^(1/6)-1 -> 0.3763594 | S51: =(P51/J51)^(1/6)-1 -> 0.25532595
A52: Growth rate (%) | C52: =C51/B51-1 -> 0.49111282 | D52: =D51/C51-1 -> 0.52078027 | E52: =E51/D51-1 -> 0.51991753 | F52: =F51/E51-1 -> 0.42093664 | G52: =G51/F51-1 -> 0.37452435 | H52: =H51/G51-1 -> 0.3460175 | I52: =I51/H51-1 -> 0.31949538 | J52: =J51/I51-1 -> 0.28939317 | ... P52: =P51/O51-1 -> 0.19593742
A53: Public administration | B53: 8.1740838 | C53: 10.309829 | D53: 13.378905 | E53: 18.344584 | F53: 24.33509 | G53: 32.266247 | H53: 40.358757 | I53: 48.459978 | J53: 59.291819 | K53: 72.904645 | L53: 91.321802 | M53: 115.14944 | N53: 139.04409 | O53: 164.28034 | P53: 191.21411 | R53: =(J53/D53)^(1/6)-1 -> 0.28162913 | S53: =(P53/J53)^(1/6)-1 -> 0.21549785
A54: Growth rate (%) | C54: =C53/B53-1 -> 0.2612825 | D54: =D53/C53-1 -> 0.29768445 | E54: =E53/D53-1 -> 0.37115741 | F54: =F53/E53-1 -> 0.32655449 | G54: =G53/F53-1 -> 0.32591442 | H54: =H53/G53-1 -> 0.25080419 | I54: =I53/H53-1 -> 0.20073018 | J54: =J53/I53-1 -> 0.22352139 | ... P54: =P53/O53-1 -> 0.1639501
A55: Total | B55: =B53+B51+B49+B47 -> 177.03321 | C55: =C53+C51+C49+C47 -> 213.62308 | D55: =D53+D51+D49+D47 -> 272.54728 | E55: =E53+E51+E49+E47 -> 357.27735 | F55: =F53+F51+F49+F47 -> 446.81344 | G55: =G53+G51+G49+G47 -> 549.32904 | H55: =H53+H51+H49+H47 -> 667.42806 | I55: =I53+I51+I49+I47 -> 801.1564 | ... P55: =P53+P51+P49+P47 -> 2495.9951 | R55: =(J55/D55)^(1/6)-1 -> 0.23118141 | S55: =(P55/J55)^(1/6)-1 -> 0.17483874
A56: Growth rate (%) | C56: =C55/B55-1 -> 0.20668369 | D56: =D55/C55-1 -> 0.27583256 | E56: =E55/D55-1 -> 0.31088207 | F56: =F55/E55-1 -> 0.25060669 | G56: =G55/F55-1 -> 0.22943715 | H56: =H55/G55-1 -> 0.21498775 | I56: =I55/H55-1 -> 0.20036368 | J56: =J55/I55-1 -> 0.18483223 | ... P56: =P55/O55-1 -> 0.13052664
A58: Public cloud spending per capita (by size of enterprises) (€ )
A59: Microenterprises (0-9 employees) | B59: =(B47*1000000)/(B34*1000) -> 197.48311 | C59: =(C47*1000000)/(C34*1000) -> 214.0312 | D59: =(D47*1000000)/(D34*1000) -> 266.30013 | E59: =(E47*1000000)/(E34*1000) -> 306.45469 | F59: =(F47*1000000)/(F34*1000) -> 351.05096 | G59: =(G47*1000000)/(G34*1000) -> 319.27501 | H59: =(H47*1000000)/(H34*1000) -> 357.94469 | I59: =(I47*1000000)/(I34*1000) -> 398.32279 | ... P59: =(P47*1000000)/(P34*1000) -> 725.087 | R59: =(J59/D59)^(1/6)-1 -> 0.085247849 | S59: =(P59/J59)^(1/6)-1 -> 0.088865378
A60: Growth rate (%) | C60: =C59/B59-1 -> 0.083794975 | D60: =D59/C59-1 -> 0.24421173 | E60: =E59/D59-1 -> 0.15078687 | F60: =F59/E59-1 -> 0.1455232 | G60: =G59/F59-1 -> -0.090516629 | H60: =H59/G59-1 -> 0.12111714 | I60: =I59/H59-1 -> 0.11280542 | J60: =J59/I59-1 -> 0.092219252 | ... P60: =P59/O59-1 -> 0.061213402
A61: SME (10-249 employees) | B61: =(B49*1000000)/(B36*1000) -> 20581.959 | C61: =(C49*1000000)/(C36*1000) -> 19988.509 | D61: =(D49*1000000)/(D36*1000) -> 21644.517 | E61: =(E49*1000000)/(E36*1000) -> 23264.198 | F61: =(F49*1000000)/(F36*1000) -> 25873.668 | G61: =(G49*1000000)/(G36*1000) -> 25340.718 | H61: =(H49*1000000)/(H36*1000) -> 24853.924 | I61: =(I49*1000000)/(I36*1000) -> 25762.155 | ... P61: =(P49*1000000)/(P36*1000) -> 35191.388 | R61: =(J61/D61)^(1/6)-1 -> 0.03475384 | S61: =(P61/J61)^(1/6)-1 -> 0.047959193
A62: Growth rate (%) | C62: =C61/B61-1 -> -0.028833519 | D62: =D61/C61-1 -> 0.082848005 | E62: =E61/D61-1 -> 0.074831048 | F62: =F61/E61-1 -> 0.11216673 | G62: =G61/F61-1 -> -0.020598134 | H62: =H61/G61-1 -> -0.019209982 | I62: =I61/H61-1 -> 0.036542771 | J62: =J61/I61-1 -> 0.03130705 | ... P62: =P61/O61-1 -> 0.025635973
A63: Large enterprises (250+ employees) | B63: =(B51*1000000)/(B38*1000) -> 46674.999 | C63: =(C51*1000000)/(C38*1000) -> 52643.386 | D63: =(D51*1000000)/(D38*1000) -> 61754.371 | E63: =(E51*1000000)/(E38*1000) -> 77347.423 | F63: =(F51*1000000)/(F38*1000) -> 96298.574 | G63: =(G51*1000000)/(G38*1000) -> 118250.09 | H63: =(H51*1000000)/(H38*1000) -> 141538.03 | I63: =(I51*1000000)/(I38*1000) -> 170180.46 | ... P63: =(P51*1000000)/(P38*1000) -> 687064.61 | R63: =(J63/D63)^(1/6)-1 -> 0.22464461 | S63: =(P63/J63)^(1/6)-1 -> 0.2200517
A64: Growth rate (%) | C64: =C63/B63-1 -> 0.12787118 | D64: =D63/C63-1 -> 0.17306991 | E64: =E63/D63-1 -> 0.25250118 | F64: =F63/E63-1 -> 0.24501335 | G64: =G63/F63-1 -> 0.22795261 | H64: =H63/G63-1 -> 0.19693804 | I64: =I63/H63-1 -> 0.20236564 | J64: =J63/I63-1 -> 0.22410444 | ... P64: =P63/O63-1 -> 0.17350057
A65: Total | B65: =(B55*1000000)/(B40*1000) -> 5245.8111 | C65: =(C55*1000000)/(C40*1000) -> 5351.7387 | D65: =(D55*1000000)/(D40*1000) -> 6227.2054 | E65: =(E55*1000000)/(E40*1000) -> 6846.9799 | F65: =(F55*1000000)/(F40*1000) -> 7581.25 | G65: =(G55*1000000)/(G40*1000) -> 6841.5231 | H65: =(H55*1000000)/(H40*1000) -> 7272.7332 | I65: =(I55*1000000)/(I40*1000) -> 7768.9423 | ... P65: =(P55*1000000)/(P40*1000) -> 11685.061 | R65: =(J65/D65)^(1/6)-1 -> 0.046953816 | S65: =(P65/J65)^(1/6)-1 -> 0.060788438
A66: Growth rate (%) | C66: =C65/B65-1 -> 0.020192814 | D66: =D65/C65-1 -> 0.16358546 | E66: =E65/D65-1 -> 0.099526914 | F66: =F65/E65-1 -> 0.10724 | G66: =G65/F65-1 -> -0.097573219 | H66: =H65/G65-1 -> 0.063028376 | I66: =I65/H65-1 -> 0.068228699 | J66: =J65/I65-1 -> 0.055592846 | ... P66: =P65/O65-1 -> 0.037013351
A68: Public cloud (by model) (€ m)
A69: SaaS | B69: 115.21961 | C69: 142.18616 | D69: 179.31435 | E69: 233.34934 | F69: 290.67711 | G69: 354.38307 | H69: 427.6934 | I69: 509.02868 | J69: 598.50838 | K69: 694.61431 | L69: 839.38528 | M69: 1024.2173 | N69: 1198.0916 | O69: 1372.4814 | P69: 1549.792 | R69: =(J69/D69)^(1/6)-1 -> 0.22248216 | S69: =(P69/J69)^(1/6)-1 -> 0.17183697
A70: Growth rate (%) | C70: =C69/B69-1 -> 0.23404487 | D70: =D69/C69-1 -> 0.26112376 | E70: =E69/D69-1 -> 0.30134223 | F70: =F69/E69-1 -> 0.2456736 | G70: =G69/F69-1 -> 0.21916401 | H70: =H69/G69-1 -> 0.20686748 | I70: =I69/H69-1 -> 0.19017193 | J70: =J69/I69-1 -> 0.17578518 | ... P70: =P69/O69-1 -> 0.12918981
A71: IaaS | B71: 54.20969 | C71: 61.753304 | D71: 80.549037 | E71: 106.90113 | F71: 134.44013 | G71: 167.42416 | H71: 205.55909 | I71: 250.21079 | J71: 299.95091 | K71: 356.49803 | L71: 433.89829 | M71: 530.5586 | N71: 621.9035 | O71: 713.99616 | P71: 808.47799 | R71: =(J71/D71)^(1/6)-1 -> 0.24498745 | S71: =(P71/J71)^(1/6)-1 -> 0.17969481
A72: Growth rate (%) | C72: =C71/B71-1 -> 0.13915618 | D72: =D71/C71-1 -> 0.30436806 | E72: =E71/D71-1 -> 0.3271559 | F72: =F71/E71-1 -> 0.25761184 | G72: =G71/F71-1 -> 0.2453437 | H72: =H71/G71-1 -> 0.22777435 | I72: =I71/H71-1 -> 0.21722075 | J72: =J71/I71-1 -> 0.19879286 | ... P72: =P71/O71-1 -> 0.13232821
A73: PaaS | B73: 7.60391 | C73: 9.683615 | D73: 12.683898 | E73: 17.026883 | F73: 21.696209 | G73: 27.521813 | H73: 34.175563 | I73: 41.916924 | J73: 50.776627 | K73: 60.084529 | L73: 73.467546 | M73: 90.008825 | N73: 105.59213 | O73: 121.33869 | P73: 137.72509 | R73: =(J73/D73)^(1/6)-1 -> 0.26009083 | S73: =(P73/J73)^(1/6)-1 -> 0.18093194
A74: Growth rate (%) | C74: =C73/B73-1 -> 0.27350469 | D74: =D73/C73-1 -> 0.3098309 | E74: =E73/D73-1 -> 0.34240141 | F74: =F73/E73-1 -> 0.27423261 | G74: =G73/F73-1 -> 0.26850789 | H74: =H73/G73-1 -> 0.24176279 | I74: =I73/H73-1 -> 0.22651745 | J74: =J73/I73-1 -> 0.21136338 | ... P74: =P73/O73-1 -> 0.13504673
A75: Total | B75: =B69+B71+B73 -> 177.03321 | C75: =C69+C71+C73 -> 213.62308 | D75: =D69+D71+D73 -> 272.54728 | E75: =E69+E71+E73 -> 357.27735 | F75: =F69+F71+F73 -> 446.81344 | G75: =G69+G71+G73 -> 549.32904 | H75: =H69+H71+H73 -> 667.42806 | I75: =I69+I71+I73 -> 801.1564 | ... P75: =P69+P71+P73 -> 2495.9951 | R75: =(J75/D75)^(1/6)-1 -> 0.23118141 | S75: =(P75/J75)^(1/6)-1 -> 0.17483874
A76: Growth rate (%) | C76: =C75/B75-1 -> 0.20668369 | D76: =D75/C75-1 -> 0.27583256 | E76: =E75/D75-1 -> 0.31088207 | F76: =F75/E75-1 -> 0.25060669 | G76: =G75/F75-1 -> 0.22943715 | H76: =H75/G75-1 -> 0.21498775 | I76: =I75/H75-1 -> 0.20036368 | J76: =J75/I75-1 -> 0.18483223 | ... P76: =P75/O75-1 -> 0.13052664
A78: SaaS spending (by advanced and basic solutions) (€ m)
A79: Basic | B79: 76.327873 | C79: 92.14233 | D79: 114.4557 | E79: 144.97404 | F79: 176.79821 | G79: 207.68364 | H79: 246.04547 | I79: 289.34951 | J79: 334.05054 | K79: 380.25874 | L79: 451.06272 | M79: 540.72578 | N79: 621.97974 | O79: 701.307 | P79: 780.23747 | R79: =(J79/D79)^(1/6)-1 -> 0.1954437 | S79: =(P79/J79)^(1/6)-1 -> 0.15186727
A80: Growth rate (%) | C80: =C79/B79-1 -> 0.20719112 | D80: =D79/C79-1 -> 0.24216195 | E80: =E79/D79-1 -> 0.26663892 | F80: =F79/E79-1 -> 0.21951632 | G80: =G79/F79-1 -> 0.17469312 | H80: =H79/G79-1 -> 0.18471284 | I80: =I79/H79-1 -> 0.17600015 | J80: =J79/I79-1 -> 0.15448799 | ... P80: =P79/O79-1 -> 0.11254767
A81: Advanced | B81: 38.891734 | C81: 50.043834 | D81: 64.858654 | E81: 88.375297 | F81: 113.8789 | G81: 146.69943 | H81: 181.64793 | I81: 219.67916 | J81: 264.45784 | K81: 314.35558 | L81: 388.32256 | M81: 483.49153 | N81: 576.11185 | O81: 671.17437 | P81: 769.5545 | R81: =(J81/D81)^(1/6)-1 -> 0.26395444 | S81: =(P81/J81)^(1/6)-1 -> 0.1948512
A82: Growth rate (%) | C82: =C81/B81-1 -> 0.28674731 | D82: =D81/C81-1 -> 0.29603685 | E82: =E81/D81-1 -> 0.36258297 | F82: =F81/E81-1 -> 0.28858293 | G82: =G81/F81-1 -> 0.28820554 | H82: =H81/G81-1 -> 0.238232 | I82: =I81/H81-1 -> 0.20936786 | J82: =J81/I81-1 -> 0.2038367 | ... P82: =P81/O81-1 -> 0.1465791
A83: Total | B83: =B79+B81 -> 115.21961 | C83: =C79+C81 -> 142.18616 | D83: =D79+D81 -> 179.31435 | E83: =E79+E81 -> 233.34934 | F83: =F79+F81 -> 290.67711 | G83: =G79+G81 -> 354.38307 | H83: =H79+H81 -> 427.6934 | I83: =I79+I81 -> 509.02868 | ... P83: =P79+P81 -> 1549.792 | R83: =(J83/D83)^(1/6)-1 -> 0.22248216 | S83: =(P83/J83)^(1/6)-1 -> 0.17183697
A84: Growth rate (%) | C84: =C83/B83-1 -> 0.23404487 | D84: =D83/C83-1 -> 0.26112376 | E84: =E83/D83-1 -> 0.30134223 | F84: =F83/E83-1 -> 0.2456736 | G84: =G83/F83-1 -> 0.21916401 | H84: =H83/G83-1 -> 0.20686748 | I84: =I83/H83-1 -> 0.19017193 | J84: =J83/I83-1 -> 0.17578518 | ... P84: =P83/O83-1 -> 0.12918981
A86: IaaS spending (by hyper and shared solutions) (€ m)
A87: Hyper | B87: 21.683876 | C87: 25.318854 | D87: 33.850733 | E87: 46.048329 | F87: 59.358698 | G87: 75.77003 | H87: 95.819354 | I87: 120.1323 | J87: 151.21444 | K87: 188.70765 | L87: 241.1624 | M87: 309.63092 | N87: 381.08624 | O87: 459.39412 | P87: 546.19417 | R87: =(J87/D87)^(1/6)-1 -> 0.28332759 | S87: =(P87/J87)^(1/6)-1 -> 0.23867955
A88: Growth rate (%) | C88: =C87/B87-1 -> 0.16763509 | D88: =D87/C87-1 -> 0.33697726 | E88: =E87/D87-1 -> 0.36033479 | F88: =F87/E87-1 -> 0.28905214 | G88: =G87/F87-1 -> 0.2764773 | H88: =H87/G87-1 -> 0.26460758 | I88: =I87/H87-1 -> 0.25373737 | J88: =J87/I87-1 -> 0.2587325 | ... P88: =P87/O87-1 -> 0.18894462
A89: Shared | B89: 32.525814 | C89: 36.434449 | D89: 46.698304 | E89: 60.852799 | F89: 75.081428 | G89: 91.654134 | H89: 109.73974 | I89: 130.07849 | J89: 148.73648 | K89: 167.79038 | L89: 192.73589 | M89: 220.92768 | N89: 240.81726 | O89: 254.60203 | P89: 262.28382 | R89: =(J89/D89)^(1/6)-1 -> 0.21297746 | S89: =(P89/J89)^(1/6)-1 -> 0.099155155
A90: Growth rate (%) | C90: =C89/B89-1 -> 0.12017025 | D90: =D89/C89-1 -> 0.28170743 | E90: =E89/D89-1 -> 0.30310513 | F90: =F89/E89-1 -> 0.23382045 | G90: =G89/F89-1 -> 0.22072977 | H90: =H89/G89-1 -> 0.1973245 | I90: =I89/H89-1 -> 0.18533623 | J90: =J89/I89-1 -> 0.14343638 | ... P90: =P89/O89-1 -> 0.030171737
A91: Total | B91: =B89+B87 -> 54.20969 | C91: =C89+C87 -> 61.753304 | D91: =D89+D87 -> 80.549037 | E91: =E89+E87 -> 106.90113 | F91: =F89+F87 -> 134.44013 | G91: =G89+G87 -> 167.42416 | H91: =H89+H87 -> 205.55909 | I91: =I89+I87 -> 250.21079 | ... P91: =P89+P87 -> 808.47799 | R91: =(J91/D91)^(1/6)-1 -> 0.24498745 | S91: =(P91/J91)^(1/6)-1 -> 0.17969481
A92: Growth rate (%) | C92: =C91/B91-1 -> 0.13915618 | D92: =D91/C91-1 -> 0.30436806 | E92: =E91/D91-1 -> 0.3271559 | F92: =F91/E91-1 -> 0.25761184 | G92: =G91/F91-1 -> 0.2453437 | H92: =H91/G91-1 -> 0.22777435 | I92: =I91/H91-1 -> 0.21722075 | J92: =J91/I91-1 -> 0.19879286 | ... P92: =P91/O91-1 -> 0.13232821
A94: PaaS spending (by hyper and shared solutions) (€ m)
A95: Hyper | B95: 3.801955 | C95: 4.9870617 | D95: 6.7281738 | E95: 9.3028673 | F95: 12.209637 | G95: 15.952662 | H95: 20.799893 | I95: 26.787003 | J95: 34.071235 | K95: 42.332701 | L95: 52.796974 | M95: 65.977942 | N95: 78.948775 | O95: 92.536555 | P95: 107.13398 | R95: =(J95/D95)^(1/6)-1 -> 0.31043388 | S95: =(P95/J95)^(1/6)-1 -> 0.21038415
A96: Growth rate (%) | C96: =C95/B95-1 -> 0.31170983 | D96: =D95/C95-1 -> 0.34912583 | E96: =E95/D95-1 -> 0.38267346 | F96: =F95/E95-1 -> 0.31245959 | G96: =G95/F95-1 -> 0.30656313 | H96: =H95/G95-1 -> 0.30385093 | I96: =I95/H95-1 -> 0.28784332 | J96: =J95/I95-1 -> 0.27193155 | ... P96: =P95/O95-1 -> 0.15774767
A97: Shared | B97: 3.801955 | C97: 4.6965533 | D97: 5.9557244 | E97: 7.7240155 | F97: 9.486572 | G97: 11.569151 | H97: 13.37567 | I97: 15.129921 | J97: 16.705392 | K97: 17.751827 | L97: 20.670572 | M97: 24.030884 | N97: 26.643356 | O97: 28.802139 | P97: 30.591107 | R97: =(J97/D97)^(1/6)-1 -> 0.18755486 | S97: =(P97/J97)^(1/6)-1 -> 0.10608819
A98: Growth rate (%) | C98: =C97/B97-1 -> 0.23529955 | D98: =D97/C97-1 -> 0.26810536 | E98: =E97/D97-1 -> 0.29690614 | F98: =F97/E97-1 -> 0.22819173 | G98: =G97/F97-1 -> 0.21952912 | H98: =H97/G97-1 -> 0.15614967 | I98: =I97/H97-1 -> 0.13115239 | J98: =J97/I97-1 -> 0.10412952 | ... P98: =P97/O97-1 -> 0.062112349
A99: Total | B99: =B97+B95 -> 7.60391 | C99: =C97+C95 -> 9.683615 | D99: =D97+D95 -> 12.683898 | E99: =E97+E95 -> 17.026883 | F99: =F97+F95 -> 21.696209 | G99: =G97+G95 -> 27.521813 | H99: =H97+H95 -> 34.175563 | I99: =I97+I95 -> 41.916924 | ... P99: =P97+P95 -> 137.72509 | R99: =(J99/D99)^(1/6)-1 -> 0.26009083 | S99: =(P99/J99)^(1/6)-1 -> 0.18093194
A100: Growth rate (%) | C100: =C99/B99-1 -> 0.27350469 | D100: =D99/C99-1 -> 0.3098309 | E100: =E99/D99-1 -> 0.34240141 | F100: =F99/E99-1 -> 0.27423261 | G100: =G99/F99-1 -> 0.26850789 | H100: =H99/G99-1 -> 0.24176279 | I100: =I99/H99-1 -> 0.22651745 | J100: =J99/I99-1 -> 0.21136338 | ... P100: =P99/O99-1 -> 0.13504673
A102: Private cloud (by size of enterprises) (€ m)
A103: Microenterprises (0-9 employees) | B103: 0.001320281 | C103: 0.0018478977 | D103: 0.0025745088 | E103: 0.0035483203 | F103: 0.0044975231 | G103: 0.0056566321 | H103: 0.0071100612 | I103: 0.008709728 | J103: 0.010465242 | K103: 0.012913202 | L103: 0.015606196 | M103: 0.01898426 | N103: 0.022986338 | O103: 0.027598598 | P103: 0.032617889 | R103: =(J103/D103)^(1/6)-1 -> 0.26330771 | S103: =(P103/J103)^(1/6)-1 -> 0.20860512
A104: Growth rate (%) | C104: =C103/B103-1 -> 0.39962449 | D104: =D103/C103-1 -> 0.39320962 | E104: =E103/D103-1 -> 0.37825137 | F104: =F103/E103-1 -> 0.26750762 | G104: =G103/F103-1 -> 0.25772164 | H104: =H103/G103-1 -> 0.25694248 | I104: =I103/H103-1 -> 0.22498637 | J104: =J103/I103-1 -> 0.2015578 | ... P104: =P103/O103-1 -> 0.18186759
A105: SME (10-249 employees) | B105: 12.781314 | C105: 15.096469 | D105: 18.262957 | E105: 22.315135 | F105: 25.474536 | G105: 29.216638 | H105: 33.823671 | I105: 38.476112 | J105: 43.226941 | K105: 45.504137 | L105: 49.39616 | M105: 53.81664 | N105: 58.144812 | O105: 62.003367 | P105: 64.702879 | R105: =(J105/D105)^(1/6)-1 -> 0.15442016 | S105: =(P105/J105)^(1/6)-1 -> 0.069534626
A106: Growth rate (%) | C106: =C105/B105-1 -> 0.1811359 | D106: =D105/C105-1 -> 0.20975023 | E106: =E105/D105-1 -> 0.22187963 | F106: =F105/E105-1 -> 0.14158106 | G106: =G105/F105-1 -> 0.1468958 | H106: =H105/G105-1 -> 0.15768524 | I106: =I105/H105-1 -> 0.13754986 | J106: =J105/I105-1 -> 0.12347477 | ... P106: =P105/O105-1 -> 0.043538149
A107: Large enterprises (250+ employees) | B107: 40.549573 | C107: 51.674636 | D107: 66.955864 | E107: 87.087444 | F107: 105.27263 | G107: 127.26835 | H107: 154.69412 | I107: 184.11879 | J107: 215.76465 | K107: 251.98497 | L107: 294.35349 | M107: 346.66046 | N107: 406.97663 | O107: 474.43447 | P107: 545.11781 | R107: =(J107/D107)^(1/6)-1 -> 0.21534229 | S107: =(P107/J107)^(1/6)-1 -> 0.16703804
A108: Growth rate (%) | C108: =C107/B107-1 -> 0.2743571 | D108: =D107/C107-1 -> 0.2957201 | E108: =E107/D107-1 -> 0.3006694 | F108: =F107/E107-1 -> 0.20881529 | G108: =G107/F107-1 -> 0.20894051 | H108: =H107/G107-1 -> 0.21549558 | I108: =I107/H107-1 -> 0.19021196 | J108: =J107/I107-1 -> 0.1718774 | ... P108: =P107/O107-1 -> 0.14898442
A109: Public administration | B109: 5.9834171 | C109: 7.8151076 | D109: 10.053863 | E109: 13.227889 | F109: 16.172846 | G109: 20.603703 | H109: 25.508558 | I109: 29.800318 | J109: 35.352304 | K109: 42.165168 | L109: 49.864852 | M109: 59.433064 | N109: 70.591185 | O109: 83.22986 | P109: 96.690906 | R109: =(J109/D109)^(1/6)-1 -> 0.23314494 | S109: =(P109/J109)^(1/6)-1 -> 0.18257307
A110: Growth rate (%) | C110: =C109/B109-1 -> 0.30612785 | D110: =D109/C109-1 -> 0.28646508 | E110: =E109/D109-1 -> 0.31570214 | F110: =F109/E109-1 -> 0.22263244 | G110: =G109/F109-1 -> 0.27396889 | H110: =H109/G109-1 -> 0.23805694 | I110: =I109/H109-1 -> 0.16824786 | J110: =J109/I109-1 -> 0.18630628 | ... P110: =P109/O109-1 -> 0.16173337
A111: Total | B111: =B109+B107+B105+B103 -> 59.315624 | C111: =C109+C107+C105+C103 -> 74.588061 | D111: =D109+D107+D105+D103 -> 95.275259 | E111: =E109+E107+E105+E103 -> 122.63402 | F111: =F109+F107+F105+F103 -> 146.92451 | G111: =G109+G107+G105+G103 -> 177.09435 | H111: =H109+H107+H105+H103 -> 214.03346 | I111: =I109+I107+I105+I103 -> 252.40393 | ... P111: =P109+P107+P105+P103 -> 706.54422 | R111: =(J111/D111)^(1/6)-1 -> 0.20683637 | S111: =(P111/J111)^(1/6)-1 -> 0.15711932
A112: Growth rate (%) | C112: =C111/B111-1 -> 0.25747746 | D112: =D111/C111-1 -> 0.27735268 | E112: =E111/D111-1 -> 0.2871549 | F112: =F111/E111-1 -> 0.19807307 | G112: =G111/F111-1 -> 0.20534243 | H112: =H111/G111-1 -> 0.20858434 | I112: =I111/H111-1 -> 0.17927325 | J112: =J111/I111-1 -> 0.16620355 | ... P112: =P111/O111-1 -> 0.14014778
A114: Private cloud spending per capita (by size of enterprises) (€ )
...

Sheet Greece
A1: Year | B1: 2016 | C1: 2017 | D1: 2018 | E1: 2019 | F1: 2020 | G1: 2021 | H1: 2022 | I1: 2023 | J1: 2024 | K1: 2025e | L1: 2026f | M1: 2027f | N1: 2028f | O1: 2029f | P1: 2030f | R1: CAGR 2019-2024 | S1: CAGR 2025-2030
A2: Total IT market size (€ m) | B2: =B4+B6+B8 -> 2727.7391 | C2: =C4+C6+C8 -> 2737.0821 | D2: =D4+D6+D8 -> 2806.2099 | E2: =E4+E6+E8 -> 2965.0213 | F2: =F4+F6+F8 -> 2885.1116 | G2: =G4+G6+G8 -> 3133.1404 | H2: =H4+H6+H8 -> 3325.2016 | I2: =I4+I6+I8 -> 3517.1896 | ... P2: =P4+P6+P8 -> 5171.278 | R2: =(J2/D2)^(1/6)-1 -> 0.05064238 | S2: =(P2/J2)^(1/6)-1 -> 0.053880513
A3: Growth rate (%) | C3: =C2/B2-1 -> 0.0034251868 | D3: =D2/C2-1 -> 0.025256004 | E3: =E2/D2-1 -> 0.056592857 | F3: =F2/E2-1 -> -0.026950821 | G3: =G2/F2-1 -> 0.085968534 | H3: =H2/G2-1 -> 0.061299925 | I3: =I2/H2-1 -> 0.057737233 | J3: =J2/I2-1 -> 0.07313377 | ... P3: =P2/O2-1 -> 0.054277271
A4: Software | B4: 521.04129 | C4: 538.44974 | D4: 558.50473 | E4: 587.84387 | F4: 596.43212 | G4: 643.8548 | H4: 685.77503 | I4: 737.54004 | J4: 804.33399 | K4: 855.66763 | L4: 908.18841 | M4: 962.55675 | N4: 1019.4732 | O4: 1082.7199 | P4: 1157.5208 | R4: =(J4/D4)^(1/6)-1 -> 0.062677768 | S4: =(P4/J4)^(1/6)-1 -> 0.062548419
A5: Growth rate (%) | C5: =C4/B4-1 -> 0.03341088 | D5: =D4/C4-1 -> 0.037245794 | E5: =E4/D4-1 -> 0.05253159 | F5: =F4/E4-1 -> 0.014609755 | G5: =G4/F4-1 -> 0.079510594 | H5: =H4/G4-1 -> 0.065108217 | I5: =I4/H4-1 -> 0.075483938 | J5: =J4/I4-1 -> 0.090563162 | ... P5: =P4/O4-1 -> 0.069086096
A6: Hardware | B6: 1380.6925 | C6: 1346.1261 | D6: 1366.4645 | E6: 1452.3599 | F6: 1380.0299 | G6: 1523.7014 | H6: 1612.465 | I6: 1680.8688 | J6: 1782.3117 | K6: 1889.8643 | L6: 1979.7906 | M6: 2052.1066 | N6: 2118.9245 | O6: 2181.8166 | P6: 2241.3357 | R6: =(J6/D6)^(1/6)-1 -> 0.045275769 | S6: =(P6/J6)^(1/6)-1 -> 0.038932202
A7: Growth rate (%) | C7: =C6/B6-1 -> -0.02503549 | D7: =D6/C6-1 -> 0.015108838 | E7: =E6/D6-1 -> 0.062859566 | F7: =F6/E6-1 -> -0.049801693 | G7: =G6/F6-1 -> 0.10410748 | H7: =H6/G6-1 -> 0.058255266 | I7: =I6/H6-1 -> 0.042421909 | J7: =J6/I6-1 -> 0.060351458 | ... P7: =P6/O6-1 -> 0.027279606
A8: Services | B8: 826.00536 | C8: 852.50624 | D8: 881.24061 | E8: 924.81754 | F8: 908.6495 | G8: 965.5842 | H8: 1026.9616 | I8: 1098.7807 | J8: 1187.7692 | K8: 1261.3537 | L8: 1343.2104 | M8: 1431.2711 | N8: 1528.8935 | O8: 1640.509 | P8: 1772.4215 | R8: =(J8/D8)^(1/6)-1 -> 0.051008574 | S8: =(P8/J8)^(1/6)-1 -> 0.068987168
A9: Growth rate (%) | C9: =C8/B8-1 -> 0.032083182 | D9: =D8/C8-1 -> 0.033705756 | E9: =E8/D8-1 -> 0.049449521 | F9: =F8/E8-1 -> -0.017482403 | G9: =G8/F8-1 -> 0.062658594 | H9: =H8/G8-1 -> 0.063565044 | I9: =I8/H8-1 -> 0.069933575 | J9: =J8/I8-1 -> 0.080988399 | ... P9: =P8/O8-1 -> 0.080409492
A11: Smartphones market size (€ m) | B11: 777.61218 | C11: 723.58729 | D11: 721.4392 | E11: 783.62138 | F11: 640.84104 | G11: 726.10836 | H11: 766.2204 | I11: 766.98022 | J11: 781.74003 | K11: 830.56107 | L11: 868.10775 | M11: 890.36439 | N11: 909.28828 | O11: 925.65397 | P11: 939.29992 | R11: =(J11/D11)^(1/6)-1 -> 0.013468924 | S11: =(P11/J11)^(1/6)-1 -> 0.031075156
A12: Growth rate (%) | C12: =C11/B11-1 -> -0.069475366 | D12: =D11/C11-1 -> -0.002968675 | E12: =E11/D11-1 -> 0.086191855 | F12: =F11/E11-1 -> -0.18220577 | G12: =G11/F11-1 -> 0.13305533 | H12: =H11/G11-1 -> 0.055242509 | I12: =I11/H11-1 -> 0.00099163621 | J12: =J11/I11-1 -> 0.019244061 | ... P12: =P11/O11-1 -> 0.014741964
A14: Cybersecurity market size (€ m) | B14: 77.913977 | C14: 79.337733 | D14: 90.948024 | E14: 93.649983 | F14: 98.444425 | G14: 107.62161 | H14: 120.14458 | I14: 132.8671 | J14: 146.82005 | K14: 157.14194 | L14: 166.97076 | M14: 176.15807 | N14: 184.58999 | O14: 193.18657 | P14: 203.62844 | R14: =(J14/D14)^(1/6)-1 -> 0.083091999 | S14: =(P14/J14)^(1/6)-1 -> 0.056028192
A15: Growth rate (%) | C15: =C14/B14-1 -> 0.018273429 | D15: =D14/C14-1 -> 0.14634009 | E15: =E14/D14-1 -> 0.029708823 | F15: =F14/E14-1 -> 0.051195338 | G15: =G14/F14-1 -> 0.093221997 | H15: =H14/G14-1 -> 0.11636105 | I15: =I14/H14-1 -> 0.10589344 | J15: =J14/I14-1 -> 0.10501432 | ... P15: =P14/O14-1 -> 0.054050661
A17: Enterprises (by size) (number of enterprises in thousands)
A18: Microenterprises (0-9 employees) | B18: 766.482 | C18: 688.217 | D18: 672.143 | E18: 677.62 | F18: 675.205 | G18: 696.658 | H18: 724.394 | I18: 745.385 | J18: 762.34373 | K18: 778.86783 | L18: 784.49209 | M18: 790.57506 | N18: 796.16874 | O18: 799.53314 | P18: 803.26351 | R18: =(J18/D18)^(1/6)-1 -> 0.021209529 | S18: =(P18/J18)^(1/6)-1 -> 0.0087522923
A19: Growth rate (%) | C19: =C18/B18-1 -> -0.10210938 | D19: =D18/C18-1 -> -0.023356005 | E19: =E18/D18-1 -> 0.0081485636 | F19: =F18/E18-1 -> -0.0035639444 | G19: =G18/F18-1 -> 0.031772573 | H19: =H18/G18-1 -> 0.039812935 | I19: =I18/H18-1 -> 0.028977324 | J19: =J18/I18-1 -> 0.022751634 | ... P19: =P18/O18-1 -> 0.0046656811
A20: SME (10-249 employees) | B20: 32.846841 | C20: 34.45385 | D20: 36.033 | E20: 39.534 | F20: 35.505 | G20: 39.0935 | H20: 42.682 | I20: 45.33 | J20: 47.066775 | K20: 48.688301 | L20: 50.28446 | M20: 51.722301 | N20: 53.003003 | O20: 54.279035 | P20: 55.447471 | R20: =(J20/D20)^(1/6)-1 -> 0.045528005 | S20: =(P20/J20)^(1/6)-1 -> 0.027687836
A21: Growth rate (%) | C21: =C20/B20-1 -> 0.048924313 | D21: =D20/C20-1 -> 0.045833775 | E21: =E20/D20-1 -> 0.097160936 | F21: =F20/E20-1 -> -0.10191228 | G21: =G20/F20-1 -> 0.10107027 | H21: =H20/G20-1 -> 0.091792753 | I21: =I20/H20-1 -> 0.062040204 | J21: =J20/I20-1 -> 0.038314032 | ... P21: =P20/O20-1 -> 0.021526469
A22: Large enterprises (250+ employees) | B22: 0.51744444 | C22: 0.50333333 | D22: 0.523 | E22: 0.526 | F22: 0.461 | G22: 0.504 | H22: 0.547 | I22: 0.59 | J22: 0.60244642 | K22: 0.61186497 | L22: 0.62190009 | M22: 0.63020181 | N22: 0.63450728 | O22: 0.63913669 | P22: 0.63986116 | R22: =(J22/D22)^(1/6)-1 -> 0.023849503 | S22: =(P22/J22)^(1/6)-1 -> 0.010092671
A23: Growth rate (%) | C23: =C22/B22-1 -> -0.027270775 | D23: =D22/C22-1 -> 0.039072848 | E23: =E22/D22-1 -> 0.0057361377 | F23: =F22/E22-1 -> -0.12357414 | G23: =G22/F22-1 -> 0.093275488 | H23: =H22/G22-1 -> 0.08531746 | I23: =I22/H22-1 -> 0.078610603 | J23: =J22/I22-1 -> 0.021095634 | ... P23: =P22/O22-1 -> 0.0011335153
A24: Number of all enterprises | B24: =B18+B20+B22 -> 799.84629 | C24: =C18+C20+C22 -> 723.17418 | D24: =D18+D20+D22 -> 708.699 | E24: =E18+E20+E22 -> 717.68 | F24: =F18+F20+F22 -> 711.171 | G24: =G18+G20+G22 -> 736.2555 | H24: =H18+H20+H22 -> 767.623 | I24: =I18+I20+I22 -> 791.305 | ... P24: =P18+P20+P22 -> 859.35084 | R24: =(J24/D24)^(1/6)-1 -> 0.022519715 | S24: =(P24/J24)^(1/6)-1 -> 0.0099032215
A25: Growth rate (%) | C25: =C24/B24-1 -> -0.095858546 | D25: =D24/C24-1 -> -0.020016178 | E25: =E24/D24-1 -> 0.012672517 | F25: =F24/E24-1 -> -0.0090695017 | G25: =G24/F24-1 -> 0.035272108 | H25: =H24/G24-1 -> 0.042604096 | I25: =I24/H24-1 -> 0.030851082 | J25: =J24/I24-1 -> 0.023641893 | ... P25: =P24/O24-1 -> 0.0057341208
A27: Percentage of enterprises using cloud computing
A28: Percent of microenterprises using cloud computing | B28: 0.04865747 | C28: 0.056671316 | D28: 0.065913589 | E28: 0.076540844 | F28: 0.088718792 | G28: 0.10261899 | H28: 0.11841403 | I28: 0.13627106 | J28: 0.15634339 | K28: 0.17876041 | L28: 0.2036159 | M28: 0.23095546 | N28: 0.26076394 | O28: 0.29295414 | P28: 0.32735836
A29: Percent of SME using cloud computing | B29: 0.093268565 | C29: 0.10752675 | D29: 0.12366734 | E29: 0.14184568 | F29: 0.16220155 | G29: 0.18484938 | H29: 0.20986734 | I29: 0.23728565 | J29: 0.26707525 | K29: 0.29913795 | L29: 0.33329939 | M29: 0.36930638 | N29: 0.4068296 | O29: 0.44547248 | P29: 0.48478604
A30: Percent of large enterprises using cloud computing | B30: 0.35214962 | C30: 0.38151522 | D30: 0.41177316 | E30: 0.4427131 | F30: 0.47410408 | G30: 0.50570109 | H30: 0.53725263 | I30: 0.56850862 | J30: 0.5992283 | K30: 0.62918745 | L30: 0.65818454 | M30: 0.68604555 | N30: 0.71262716 | O30: 0.73781828 | P30: 0.76154007
A31: Percent of all enterprises using cloud computing | B31: 0.050685827 | C31: 0.059320291 | D31: 0.069105248 | E31: 0.08040659 | F31: 0.092637214 | G31: 0.10726116 | H31: 0.12379755 | I31: 0.14237997 | J31: 0.16310699 | K31: 0.18617023 | L31: 0.21176023 | M31: 0.23978496 | N31: 0.27021154 | O31: 0.30297563 | P31: 0.33783928
A33: Number of enterprises using cloud computing (thousands)
A34: Number of microenterprises using cloud computing | B34: =B28*B18 -> 37.295075 | C34: =C28*C18 -> 39.002163 | D34: =D28*D18 -> 44.303358 | E34: =E28*E18 -> 51.865607 | F34: =F28*F18 -> 59.903372 | G34: =G28*G18 -> 71.49034 | H34: =H28*H18 -> 85.778415 | I34: =I28*I18 -> 101.5744 | ... P34: =P28*P18 -> 262.95503 | R34: =(J34/D34)^(1/6)-1 -> 0.17932168 | S34: =(P34/J34)^(1/6)-1 -> 0.14097253
A35: Growth rate (%) | C35: =C34/B34-1 -> 0.045772488 | D35: =D34/C34-1 -> 0.13592052 | E35: =E34/D34-1 -> 0.17069246 | F35: =F34/E34-1 -> 0.15497293 | G35: =G34/F34-1 -> 0.19342763 | H35: =H34/G34-1 -> 0.19986023 | I35: =I34/H34-1 -> 0.18414874 | J35: =J34/I34-1 -> 0.17339997 | ... P35: =P34/O34-1 -> 0.12265257
A36: Number of SME using cloud computing | B36: =B29*B20 -> 3.0635777 | C36: =C29*C20 -> 3.7047106 | D36: =D29*D20 -> 4.4561053 | E36: =E29*E20 -> 5.6077273 | F36: =F29*F20 -> 5.7589659 | G36: =G29*G20 -> 7.2264093 | H36: =H29*H20 -> 8.9575578 | I36: =I29*I20 -> 10.756158 | ... P36: =P29*P20 -> 26.88016 | R36: =(J36/D36)^(1/6)-1 -> 0.18868132 | S36: =(P36/J36)^(1/6)-1 -> 0.1350473
A37: Growth rate (%) | C37: =C36/B36-1 -> 0.20927588 | D37: =D36/C36-1 -> 0.20282143 | E37: =E36/D36-1 -> 0.25843687 | F37: =F36/E36-1 -> 0.02696969 | G37: =G36/F36-1 -> 0.25481023 | H37: =H36/G36-1 -> 0.2395586 | I37: =I36/H36-1 -> 0.2007914 | J37: =J36/I36-1 -> 0.16866731 | ... P37: =P36/O36-1 -> 0.11167758
A38: Number of large enterprises using cloud computing | B38: =B30*B22 -> 0.18221787 | C38: =C30*C22 -> 0.19202933 | D38: =D30*D22 -> 0.21535736 | E38: =E30*E22 -> 0.23286709 | F38: =F30*F22 -> 0.21856198 | G38: =G30*G22 -> 0.25487335 | H38: =H30*H22 -> 0.29387719 | I38: =I30*I22 -> 0.33542009 | ... P38: =P30*P22 -> 0.48727992 | R38: =(J38/D38)^(1/6)-1 -> 0.089913012 | S38: =(P38/J38)^(1/6)-1 -> 0.051262793
A39: Growth rate (%) | C39: =C38/B38-1 -> 0.053844682 | D39: =D38/C38-1 -> 0.12148163 | E39: =E38/D38-1 -> 0.08130546 | F39: =F38/E38-1 -> -0.06143037 | G39: =G38/F38-1 -> 0.16613763 | H39: =H38/G38-1 -> 0.15303223 | I39: =I38/H38-1 -> 0.14136143 | J39: =J38/I38-1 -> 0.076271112 | ... P39: =P38/O38-1 -> 0.033321223
A40: Number of all enterprises using cloud computing | B40: =B38+B36+B34 -> 40.54087 | C40: =C38+C36+C34 -> 42.898903 | D40: =D38+D36+D34 -> 48.97482 | E40: =E38+E36+E34 -> 57.706201 | F40: =F38+F36+F34 -> 65.8809 | G40: =G38+G36+G34 -> 78.971622 | H40: =H38+H36+H34 -> 95.02985 | I40: =I38+I36+I34 -> 112.66598 | ... P40: =P38+P36+P34 -> 290.32247 | R40: =(J40/D40)^(1/6)-1 -> 0.17986399 | S40: =(P40/J40)^(1/6)-1 -> 0.14021308
A41: Growth rate (%) | C41: =C40/B40-1 -> 0.058164335 | D41: =D40/C40-1 -> 0.14163339 | E41: =E40/D40-1 -> 0.17828306 | F41: =F40/E40-1 -> 0.14166066 | G41: =G40/F40-1 -> 0.19870284 | H41: =H40/G40-1 -> 0.20334175 | I41: =I40/H40-1 -> 0.18558517 | J41: =J40/I40-1 -> 0.17265898 | ... P41: =P40/O40-1 -> 0.12146476
A43: Total cloud computing market size (€ m) | B43: =B55+B111 -> 50.476796 | C43: =C55+C111 -> 68.40563 | D43: =D55+D111 -> 85.198035 | E43: =E55+E111 -> 107.89146 | F43: =F55+F111 -> 128.59975 | G43: =G55+G111 -> 172.19197 | H43: =H55+H111 -> 232.87161 | I43: =I55+I111 -> 291.5586 | ... P43: =P55+P111 -> 1068.5902 | R43: =(J43/D43)^(1/6)-1 -> 0.27069197 | S43: =(P43/J43)^(1/6)-1 -> 0.1995637
A44: Growth rate (%) | C44: =C43/B43-1 -> 0.35518962 | D44: =D43/C43-1 -> 0.24548279 | E44: =E43/D43-1 -> 0.26636084 | F44: =F43/E43-1 -> 0.19193638 | G44: =G43/F43-1 -> 0.33897592 | H44: =H43/G43-1 -> 0.35239528 | I44: =I43/H43-1 -> 0.25201438 | J44: =J43/I43-1 -> 0.23011422 | ... P44: =P43/O43-1 -> 0.18112812
A46: Public cloud (by size of enterprises) (€ m)
A47: Microenterprises (0-9 employees) | B47: 2.9466189 | C47: 4.0856428 | D47: 6.9167891 | E47: 8.798452 | F47: 13.441948 | G47: 19.441939 | H47: 29.293594 | I47: 38.17877 | J47: 48.782861 | K47: 65.304932 | L47: 84.901724 | M47: 108.13611 | N47: 139.72454 | O47: 178.69843 | P47: 223.22833 | R47: =(J47/D47)^(1/6)-1 -> 0.38482147 | S47: =(P47/J47)^(1/6)-1 -> 0.28848789
A48: Growth rate (%) | C48: =C47/B47-1 -> 0.38655283 | D48: =D47/C47-1 -> 0.69295003 | E48: =E47/D47-1 -> 0.27204283 | F48: =F47/E47-1 -> 0.52776284 | G48: =G47/F47-1 -> 0.44636319 | H48: =H47/G47-1 -> 0.50672184 | I48: =I47/H47-1 -> 0.30331466 | J48: =J47/I47-1 -> 0.27774837 | ... P48: =P47/O47-1 -> 0.24919022
A49: SME (10-249 employees) | B49: 33.718097 | C49: 44.428478 | D49: 53.696667 | E49: 69.878794 | F49: 83.349214 | G49: 108.34475 | H49: 141.01703 | I49: 173.81985 | J49: 211.62984 | K49: 247.15532 | L49: 294.01419 | M49: 343.86394 | N49: 409.23389 | O49: 483.32288 | P49: 558.80488 | R49: =(J49/D49)^(1/6)-1 -> 0.25681569 | S49: =(P49/J49)^(1/6)-1 -> 0.17565677
A50: Growth rate (%) | C50: =C49/B49-1 -> 0.31764489 | D50: =D49/C49-1 -> 0.2086092 | E50: =E49/D49-1 -> 0.30136186 | F50: =F49/E49-1 -> 0.19276836 | G50: =G49/F49-1 -> 0.29988932 | H50: =H49/G49-1 -> 0.30155843 | I50: =I49/H49-1 -> 0.23261605 | J50: =J49/I49-1 -> 0.21752397 | ... P50: =P49/O49-1 -> 0.15617302
A51: Large enterprises (250+ employees) | B51: 4.5339775 | C51: 7.0230362 | D51: 8.8458797 | E51: 10.206216 | F51: 10.482262 | G51: 15.423765 | H51: 22.889123 | I51: 30.012207 | J51: 37.651116 | K51: 42.487563 | L51: 51.795341 | M51: 62.111502 | N51: 75.833946 | O51: 91.937312 | P51: 109.18066 | R51: =(J51/D51)^(1/6)-1 -> 0.27303244 | S51: =(P51/J51)^(1/6)-1 -> 0.19415667
A52: Growth rate (%) | C52: =C51/B51-1 -> 0.54897907 | D52: =D51/C51-1 -> 0.25955205 | E52: =E51/D51-1 -> 0.15378193 | F52: =F51/E51-1 -> 0.027046833 | G52: =G51/F51-1 -> 0.47141577 | H52: =H51/G51-1 -> 0.48401655 | I52: =I51/H51-1 -> 0.3111995 | J52: =J51/I51-1 -> 0.25452673 | ... P52: =P51/O51-1 -> 0.18755544
A53: Public administration | B53: 1.746759 | C53: 2.5140606 | D53: 3.3156129 | E53: 4.5467303 | F53: 5.7934261 | G53: 8.2697778 | H53: 11.987763 | I53: 15.739625 | J53: 19.800943 | K53: 25.098977 | L53: 31.871293 | M53: 39.741985 | N53: 50.375786 | O53: 63.313238 | P53: 77.840034 | R53: =(J53/D53)^(1/6)-1 -> 0.34695683 | S53: =(P53/J53)^(1/6)-1 -> 0.25627926
A54: Growth rate (%) | C54: =C53/B53-1 -> 0.43927156 | D54: =D53/C53-1 -> 0.31882779 | E54: =E53/D53-1 -> 0.37130915 | F54: =F53/E53-1 -> 0.27419612 | G54: =G53/F53-1 -> 0.42744167 | H54: =H53/G53-1 -> 0.44958702 | I54: =I53/H53-1 -> 0.31297432 | J54: =J53/I53-1 -> 0.25803149 | ... P54: =P53/O53-1 -> 0.22944326
A55: Total | B55: =B53+B51+B49+B47 -> 42.945452 | C55: =C53+C51+C49+C47 -> 58.051217 | D55: =D53+D51+D49+D47 -> 72.774949 | E55: =E53+E51+E49+E47 -> 93.430192 | F55: =F53+F51+F49+F47 -> 113.06685 | G55: =G53+G51+G49+G47 -> 151.48024 | H55: =H53+H51+H49+H47 -> 205.18751 | I55: =I53+I51+I49+I47 -> 257.75045 | ... P55: =P53+P51+P49+P47 -> 969.0539 | R55: =(J55/D55)^(1/6)-1 -> 0.27852751 | S55: =(P55/J55)^(1/6)-1 -> 0.20416017
A56: Growth rate (%) | C56: =C55/B55-1 -> 0.35174307 | D56: =D55/C55-1 -> 0.25363347 | E56: =E55/D55-1 -> 0.28382354 | F56: =F55/E55-1 -> 0.21017465 | G56: =G55/F55-1 -> 0.33974048 | H56: =H55/G55-1 -> 0.3545497 | I56: =I55/H55-1 -> 0.25617031 | J56: =J55/I55-1 -> 0.23322676 | ... P56: =P55/O55-1 -> 0.18571792
A58: Public cloud spending per capita (by size of enterprises) (€ )
A59: Microenterprises (0-9 employees) | B59: =(B47*1000000)/(B34*1000) -> 79.008258 | C59: =(C47*1000000)/(C34*1000) -> 104.75426 | D59: =(D47*1000000)/(D34*1000) -> 156.12336 | E59: =(E47*1000000)/(E34*1000) -> 169.63943 | F59: =(F47*1000000)/(F34*1000) -> 224.39384 | G59: =(G47*1000000)/(G34*1000) -> 271.95197 | H59: =(H47*1000000)/(H34*1000) -> 341.50309 | I59: =(I47*1000000)/(I34*1000) -> 375.87 | ... P59: =(P47*1000000)/(P34*1000) -> 848.92209 | R59: =(J59/D59)^(1/6)-1 -> 0.17425253 | S59: =(P59/J59)^(1/6)-1 -> 0.12928914
A60: Growth rate (%) | C60: =C59/B59-1 -> 0.32586471 | D60: =D59/C59-1 -> 0.49037718 | E60: =E59/D59-1 -> 0.086573003 | F60: =F59/E59-1 -> 0.32276939 | G60: =G59/F59-1 -> 0.21194043 | H60: =H59/G59-1 -> 0.2557478 | I60: =I59/H59-1 -> 0.10063425 | J60: =J59/I59-1 -> 0.088928241 | ... P60: =P59/O59-1 -> 0.1127131
A61: SME (10-249 employees) | B61: =(B49*1000000)/(B36*1000) -> 11006.118 | C61: =(C49*1000000)/(C36*1000) -> 11992.429 | D61: =(D49*1000000)/(D36*1000) -> 12050.134 | E61: =(E49*1000000)/(E36*1000) -> 12461.161 | F61: =(F49*1000000)/(F36*1000) -> 14472.948 | G61: =(G49*1000000)/(G36*1000) -> 14992.889 | H61: =(H49*1000000)/(H36*1000) -> 15742.799 | I61: =(I49*1000000)/(I36*1000) -> 16160.031 | ... P61: =(P49*1000000)/(P36*1000) -> 20788.748 | R61: =(J61/D61)^(1/6)-1 -> 0.057319289 | S61: =(P61/J61)^(1/6)-1 -> 0.035777777
A62: Growth rate (%) | C62: =C61/B61-1 -> 0.089614796 | D62: =D61/C61-1 -> 0.0048118289 | E62: =E61/D61-1 -> 0.034109762 | F62: =F61/E61-1 -> 0.16144456 | G62: =G61/F61-1 -> 0.035925033 | H62: =H61/G61-1 -> 0.05001767 | I62: =I61/H61-1 -> 0.026503068 | J62: =J61/I61-1 -> 0.041805445 | ... P62: =P61/O61-1 -> 0.040025486
A63: Large enterprises (250+ employees) | B63: =(B51*1000000)/(B38*1000) -> 24882.179 | C63: =(C51*1000000)/(C38*1000) -> 36572.727 | D63: =(D51*1000000)/(D38*1000) -> 41075.353 | E63: =(E51*1000000)/(E38*1000) -> 43828.503 | F63: =(F51*1000000)/(F38*1000) -> 47960.134 | G63: =(G51*1000000)/(G38*1000) -> 60515.411 | H63: =(H51*1000000)/(H38*1000) -> 77886.696 | I63: =(I51*1000000)/(I38*1000) -> 89476.475 | ... P63: =(P51*1000000)/(P38*1000) -> 224061.47 | R63: =(J63/D63)^(1/6)-1 -> 0.16801288 | S63: =(P63/J63)^(1/6)-1 -> 0.13592593
A64: Growth rate (%) | C64: =C63/B63-1 -> 0.46983621 | D64: =D63/C63-1 -> 0.1231143 | E64: =E63/D63-1 -> 0.067026819 | F64: =F63/E63-1 -> 0.094268129 | G64: =G63/F63-1 -> 0.2617857 | H64: =H63/G63-1 -> 0.28705557 | I64: =I63/H63-1 -> 0.14880306 | J64: =J63/I63-1 -> 0.16562334 | ... P64: =P63/O63-1 -> 0.14926067
A65: Total | B65: =(B55*1000000)/(B40*1000) -> 1059.3125 | C65: =(C55*1000000)/(C40*1000) -> 1353.2098 | D65: =(D55*1000000)/(D40*1000) -> 1485.9666 | E65: =(E55*1000000)/(E40*1000) -> 1619.0668 | F65: =(F55*1000000)/(F40*1000) -> 1716.2311 | G65: =(G55*1000000)/(G40*1000) -> 1918.1604 | H65: =(H55*1000000)/(H40*1000) -> 2159.1901 | I65: =(I55*1000000)/(I40*1000) -> 2287.7399 | ... P65: =(P55*1000000)/(P40*1000) -> 3337.8536 | R65: =(J65/D65)^(1/6)-1 -> 0.083622793 | S65: =(P65/J65)^(1/6)-1 -> 0.056083459
A66: Growth rate (%) | C66: =C65/B65-1 -> 0.27744154 | D66: =D65/C65-1 -> 0.098105112 | E66: =E65/D65-1 -> 0.089571417 | F66: =F65/E65-1 -> 0.060012568 | G66: =G65/F65-1 -> 0.11765855 | H66: =H65/G65-1 -> 0.12565669 | I66: =I65/H65-1 -> 0.059536118 | J66: =J65/I65-1 -> 0.051649947 | ... P66: =P65/O65-1 -> 0.057293968
A68: Public cloud (by model) (€ m)
A69: SaaS | B69: 29.001698 | C69: 38.549885 | D69: 47.684522 | E69: 60.706521 | F69: 72.616272 | G69: 95.679096 | H69: 126.84794 | I69: 157.86269 | J69: 191.85151 | K69: 227.8312 | L69: 273.91122 | M69: 326.09529 | N69: 400.218 | O69: 488.00478 | P69: 579.56638 | R69: =(J69/D69)^(1/6)-1 -> 0.26114387 | S69: =(P69/J69)^(1/6)-1 -> 0.20232809
A70: Growth rate (%) | C70: =C69/B69-1 -> 0.32922857 | D70: =D69/C69-1 -> 0.23695626 | E70: =E69/D69-1 -> 0.27308651 | F70: =F69/E69-1 -> 0.19618568 | G70: =G69/F69-1 -> 0.31759858 | H70: =H69/G69-1 -> 0.3257644 | I70: =I69/H69-1 -> 0.24450337 | J70: =J69/I69-1 -> 0.21530625 | ... P70: =P69/O69-1 -> 0.18762437
A71: IaaS | B71: 12.30525 | C71: 17.169737 | D71: 22.052686 | E71: 28.706785 | F71: 35.432583 | G71: 48.763455 | H71: 68.235062 | I71: 86.939728 | J71: 109.49473 | K71: 132.07368 | L71: 163.52478 | M71: 196.78172 | N71: 237.3534 | O71: 284.01579 | P71: 335.68455 | R71: =(J71/D71)^(1/6)-1 -> 0.30613666 | S71: =(P71/J71)^(1/6)-1 -> 0.20528483
A72: Growth rate (%) | C72: =C71/B71-1 -> 0.39531799 | D72: =D71/C71-1 -> 0.28439279 | E72: =E71/D71-1 -> 0.30173641 | F72: =F71/E71-1 -> 0.23429298 | G72: =G71/F71-1 -> 0.37623203 | H72: =H71/G71-1 -> 0.39930736 | I72: =I71/H71-1 -> 0.27412104 | J72: =J71/I71-1 -> 0.25943261 | ... P72: =P71/O71-1 -> 0.18192214
A73: PaaS | B73: 1.638504 | C73: 2.331595 | D73: 3.0377403 | E73: 4.0168862 | F73: 5.0179958 | G73: 7.0376843 | H73: 10.104506 | I73: 12.948038 | J73: 16.518516 | K73: 20.141919 | L73: 25.146547 | M73: 30.976523 | N73: 37.596757 | O73: 45.251295 | P73: 53.802977 | R73: =(J73/D73)^(1/6)-1 -> 0.32608103 | S73: =(P73/J73)^(1/6)-1 -> 0.21751003
A74: Growth rate (%) | C74: =C73/B73-1 -> 0.42300232 | D74: =D73/C73-1 -> 0.30285933 | E74: =E73/D73-1 -> 0.32232704 | F74: =F73/E73-1 -> 0.24922529 | G74: =G73/F73-1 -> 0.40248906 | H74: =H73/G73-1 -> 0.43577147 | I74: =I73/H73-1 -> 0.28141225 | J74: =J73/I73-1 -> 0.27575435 | ... P74: =P73/O73-1 -> 0.18898203
A75: Total | B75: =B69+B71+B73 -> 42.945452 | C75: =C69+C71+C73 -> 58.051217 | D75: =D69+D71+D73 -> 72.774949 | E75: =E69+E71+E73 -> 93.430192 | F75: =F69+F71+F73 -> 113.06685 | G75: =G69+G71+G73 -> 151.48024 | H75: =H69+H71+H73 -> 205.18751 | I75: =I69+I71+I73 -> 257.75045 | ... P75: =P69+P71+P73 -> 969.0539 | R75: =(J75/D75)^(1/6)-1 -> 0.27852751 | S75: =(P75/J75)^(1/6)-1 -> 0.20416017
A76: Growth rate (%) | C76: =C75/B75-1 -> 0.35174307 | D76: =D75/C75-1 -> 0.25363347 | E76: =E75/D75-1 -> 0.28382354 | F76: =F75/E75-1 -> 0.21017465 | G76: =G75/F75-1 -> 0.33974048 | H76: =H75/G75-1 -> 0.3545497 | I76: =I75/H75-1 -> 0.25617031 | J76: =J75/I75-1 -> 0.23322676 | ... P76: =P75/O75-1 -> 0.18571792
A78: SaaS spending (by advanced and basic solutions) (€ m)
A79: Basic | B79: 19.664559 | C79: 25.456685 | D79: 31.545923 | E79: 38.913523 | F79: 46.044029 | G79: 58.763167 | H79: 77.104229 | I79: 94.927727 | J79: 113.98046 | K79: 133.5236 | L79: 158.48981 | M79: 186.45112 | N79: 226.33043 | O79: 273.2166 | P79: 321.54865 | R79: =(J79/D79)^(1/6)-1 -> 0.23874295 | S79: =(P79/J79)^(1/6)-1 -> 0.18869211
A80: Growth rate (%) | C80: =C79/B79-1 -> 0.29454642 | D80: =D79/C79-1 -> 0.23919994 | E80: =E79/D79-1 -> 0.23355159 | F80: =F79/E79-1 -> 0.1832398 | G80: =G79/F79-1 -> 0.27623861 | H80: =H79/G79-1 -> 0.31211833 | I80: =I79/H79-1 -> 0.2311611 | J80: =J79/I79-1 -> 0.20070778 | ... P80: =P79/O79-1 -> 0.17690009
A81: Advanced | B81: 9.3371382 | C81: 13.0932 | D81: 16.138599 | E81: 21.792998 | F81: 26.572243 | G81: 36.915929 | H81: 49.743711 | I81: 62.934961 | J81: 77.871052 | K81: 94.307596 | L81: 115.42141 | M81: 139.64417 | N81: 173.88757 | O81: 214.78818 | P81: 258.01773 | R81: =(J81/D81)^(1/6)-1 -> 0.29992521 | S81: =(P81/J81)^(1/6)-1 -> 0.22099041
A82: Growth rate (%) | C82: =C81/B81-1 -> 0.40227121 | D82: =D81/C81-1 -> 0.23259395 | E82: =E81/D81-1 -> 0.35036492 | F82: =F81/E81-1 -> 0.21930182 | G82: =G81/F81-1 -> 0.38926659 | H82: =H81/G81-1 -> 0.34748636 | I82: =I81/H81-1 -> 0.26518428 | J82: =J81/I81-1 -> 0.23732581 | ... P82: =P81/O81-1 -> 0.20126596
A83: Total | B83: =B79+B81 -> 29.001698 | C83: =C79+C81 -> 38.549885 | D83: =D79+D81 -> 47.684522 | E83: =E79+E81 -> 60.706521 | F83: =F79+F81 -> 72.616272 | G83: =G79+G81 -> 95.679096 | H83: =H79+H81 -> 126.84794 | I83: =I79+I81 -> 157.86269 | ... P83: =P79+P81 -> 579.56638 | R83: =(J83/D83)^(1/6)-1 -> 0.26114387 | S83: =(P83/J83)^(1/6)-1 -> 0.20232809
A84: Growth rate (%) | C84: =C83/B83-1 -> 0.32922857 | D84: =D83/C83-1 -> 0.23695626 | E84: =E83/D83-1 -> 0.27308651 | F84: =F83/E83-1 -> 0.19618568 | G84: =G83/F83-1 -> 0.31759858 | H84: =H83/G83-1 -> 0.3257644 | I84: =I83/H83-1 -> 0.24450337 | J84: =J83/I83-1 -> 0.21530625 | ... P84: =P83/O83-1 -> 0.18762437
A86: IaaS spending (by hyper and shared solutions) (€ m)
A87: Hyper | B87: 6.8909401 | C87: 9.7054342 | D87: 12.582766 | E87: 16.854449 | F87: 21.916306 | G87: 31.775585 | H87: 45.75326 | I87: 59.985752 | J87: 77.738905 | K87: 96.488787 | L87: 122.93047 | M87: 152.22153 | N87: 188.93054 | O87: 232.62938 | P87: 282.92336 | R87: =(J87/D87)^(1/6)-1 -> 0.35459785 | S87: =(P87/J87)^(1/6)-1 -> 0.24023809
A88: Growth rate (%) | C88: =C87/B87-1 -> 0.40843398 | D88: =D87/C87-1 -> 0.29646608 | E88: =E87/D87-1 -> 0.33948677 | F88: =F87/E87-1 -> 0.30032765 | G88: =G87/F87-1 -> 0.44986044 | H88: =H87/G87-1 -> 0.43988727 | I88: =I87/H87-1 -> 0.31107055 | J88: =J87/I87-1 -> 0.29595616 | ... P88: =P87/O87-1 -> 0.21619788
A89: Shared | B89: 5.4143101 | C89: 7.4643028 | D89: 9.4699201 | E89: 11.852336 | F89: 13.516277 | G89: 16.98787 | H89: 22.481802 | I89: 26.953976 | J89: 31.755824 | K89: 35.584889 | L89: 40.594314 | M89: 44.56019 | N89: 48.422861 | O89: 51.386408 | P89: 52.761188 | R89: =(J89/D89)^(1/6)-1 -> 0.22343108 | S89: =(P89/J89)^(1/6)-1 -> 0.088299755
A90: Growth rate (%) | C90: =C89/B89-1 -> 0.37862491 | D90: =D89/C89-1 -> 0.26869453 | E90: =E89/D89-1 -> 0.25157718 | F90: =F89/E89-1 -> 0.14038929 | G90: =G89/F89-1 -> 0.25684539 | H90: =H89/G89-1 -> 0.32340317 | I90: =I89/H89-1 -> 0.19892419 | J90: =J89/I89-1 -> 0.1781499 | ... P90: =P89/O89-1 -> 0.026753782
A91: Total | B91: =B89+B87 -> 12.30525 | C91: =C89+C87 -> 17.169737 | D91: =D89+D87 -> 22.052686 | E91: =E89+E87 -> 28.706785 | F91: =F89+F87 -> 35.432583 | G91: =G89+G87 -> 48.763455 | H91: =H89+H87 -> 68.235062 | I91: =I89+I87 -> 86.939728 | ... P91: =P89+P87 -> 335.68455 | R91: =(J91/D91)^(1/6)-1 -> 0.30613666 | S91: =(P91/J91)^(1/6)-1 -> 0.20528483
A92: Growth rate (%) | C92: =C91/B91-1 -> 0.39531799 | D92: =D91/C91-1 -> 0.28439279 | E92: =E91/D91-1 -> 0.30173641 | F92: =F91/E91-1 -> 0.23429298 | G92: =G91/F91-1 -> 0.37623203 | H92: =H91/G91-1 -> 0.39930736 | I92: =I91/H91-1 -> 0.27412104 | J92: =J91/I91-1 -> 0.25943261 | ... P92: =P91/O91-1 -> 0.18192214
A94: PaaS spending (by hyper and shared solutions) (€ m)
A95: Hyper | B95: 1.1469528 | C95: 1.6474584 | D95: 2.1665828 | E95: 2.8918614 | F95: 3.6465447 | G95: 5.1623129 | H95: 7.4815734 | I95: 9.6770974 | J95: 12.461648 | K95: 15.63582 | L95: 20.086929 | M95: 25.461456 | N95: 31.79921 | O95: 39.383321 | P95: 48.184016 | R95: =(J95/D95)^(1/6)-1 -> 0.33854619 | S95: =(P95/J95)^(1/6)-1 -> 0.25281782
A96: Growth rate (%) | C96: =C95/B95-1 -> 0.43637855 | D96: =D95/C95-1 -> 0.3151062 | E96: =E95/D95-1 -> 0.33475691 | F96: =F95/E95-1 -> 0.26096801 | G96: =G95/F95-1 -> 0.41567246 | H96: =H95/G95-1 -> 0.44926772 | I96: =I95/H95-1 -> 0.29345752 | J96: =J95/I95-1 -> 0.28774644 | ... P96: =P95/O95-1 -> 0.22346251
A97: Shared | B97: 0.49155121 | C97: 0.68413662 | D97: 0.87115755 | E97: 1.1250248 | F97: 1.3714512 | G97: 1.8753714 | H97: 2.6229329 | I97: 3.2709407 | J97: 4.0568682 | K97: 4.5060989 | L97: 5.0596177 | M97: 5.5150669 | N97: 5.7975472 | O97: 5.8679746 | P97: 5.6189606 | R97: =(J97/D97)^(1/6)-1 -> 0.29225741 | S97: =(P97/J97)^(1/6)-1 -> 0.055789926
A98: Growth rate (%) | C98: =C97/B97-1 -> 0.39179114 | D98: =D97/C97-1 -> 0.27336782 | E98: =E97/D97-1 -> 0.29141374 | F98: =F97/E97-1 -> 0.21904079 | G98: =G97/F97-1 -> 0.36743579 | H98: =H97/G97-1 -> 0.3986205 | I98: =I97/H97-1 -> 0.24705467 | J98: =J97/I97-1 -> 0.24027567 | ... P98: =P97/O97-1 -> -0.042436112
A99: Total | B99: =B97+B95 -> 1.638504 | C99: =C97+C95 -> 2.331595 | D99: =D97+D95 -> 3.0377403 | E99: =E97+E95 -> 4.0168862 | F99: =F97+F95 -> 5.0179958 | G99: =G97+G95 -> 7.0376843 | H99: =H97+H95 -> 10.104506 | I99: =I97+I95 -> 12.948038 | ... P99: =P97+P95 -> 53.802977 | R99: =(J99/D99)^(1/6)-1 -> 0.32608103 | S99: =(P99/J99)^(1/6)-1 -> 0.21751003
A100: Growth rate (%) | C100: =C99/B99-1 -> 0.42300232 | D100: =D99/C99-1 -> 0.30285933 | E100: =E99/D99-1 -> 0.32232704 | F100: =F99/E99-1 -> 0.24922529 | G100: =G99/F99-1 -> 0.40248906 | H100: =H99/G99-1 -> 0.43577147 | I100: =I99/H99-1 -> 0.28141225 | J100: =J99/I99-1 -> 0.27575435 | ... P100: =P99/O99-1 -> 0.18898203
A102: Private cloud (by size of enterprises) (€ m)
A103: Microenterprises (0-9 employees) | B103: 0.00081058632 | C103: 0.0010693366 | D103: 0.0012596613 | E103: 0.0018361873 | F103: 0.0026582062 | G103: 0.0039012062 | H103: 0.0059890523 | I103: 0.0079609526 | J103: 0.010554279 | K103: 0.013307469 | L103: 0.016909625 | M103: 0.021115941 | N103: 0.025964398 | O103: 0.031618838 | P103: 0.03813369 | R103: =(J103/D103)^(1/6)-1 -> 0.42515618 | S103: =(P103/J103)^(1/6)-1 -> 0.23873967
A104: Growth rate (%) | C104: =C103/B103-1 -> 0.31921374 | D104: =D103/C103-1 -> 0.17798392 | E104: =E103/D103-1 -> 0.45768329 | F104: =F103/E103-1 -> 0.44767708 | G104: =G103/F103-1 -> 0.46760856 | H104: =H103/G103-1 -> 0.53517962 | I104: =I103/H103-1 -> 0.32925081 | J104: =J103/I103-1 -> 0.32575574 | ... P104: =P103/O103-1 -> 0.20604338
A105: SME (10-249 employees) | B105: 1.266138 | C105: 1.7308327 | D105: 2.1403491 | E105: 2.8828162 | F105: 3.5098531 | G105: 4.723082 | H105: 6.4034792 | I105: 8.137299 | J105: 10.186184 | K105: 12.901399 | L105: 15.862959 | M105: 19.235867 | N105: 23.037288 | O105: 27.3942 | P105: 32.332039 | R105: =(J105/D105)^(1/6)-1 -> 0.29694379 | S105: =(P105/J105)^(1/6)-1 -> 0.21228183
A106: Growth rate (%) | C106: =C105/B105-1 -> 0.3670174 | D106: =D105/C105-1 -> 0.23660074 | E106: =E105/D105-1 -> 0.34689069 | F106: =F105/E105-1 -> 0.21750845 | G106: =G105/F105-1 -> 0.34566371 | H106: =H105/G105-1 -> 0.35578404 | I106: =I105/H105-1 -> 0.27076217 | J106: =J105/I105-1 -> 0.25178933 | ... P106: =P105/O105-1 -> 0.18025123
A107: Large enterprises (250+ employees) | B107: 5.5415779 | C107: 7.5860269 | D107: 9.0114608 | E107: 10.073523 | F107: 10.399129 | G107: 13.741394 | H107: 18.126099 | I107: 21.765902 | J107: 25.861445 | K107: 29.636493 | L107: 34.122344 | M107: 38.791684 | N107: 43.598103 | O107: 48.694146 | P107: 54.018885 | R107: =(J107/D107)^(1/6)-1 -> 0.19209152 | S107: =(P107/J107)^(1/6)-1 -> 0.1306169
A108: Growth rate (%) | C108: =C107/B107-1 -> 0.36892904 | D108: =D107/C107-1 -> 0.18790256 | E108: =E107/D107-1 -> 0.11785684 | F108: =F107/E107-1 -> 0.032322962 | G108: =G107/F107-1 -> 0.32139852 | H108: =H107/G107-1 -> 0.31908733 | I108: =I107/H107-1 -> 0.20080455 | J108: =J107/I107-1 -> 0.18816326 | ... P108: =P107/O107-1 -> 0.10935072
A109: Public administration | B109: 0.72281786 | C109: 1.0364841 | D109: 1.270017 | E109: 1.5030874 | F109: 1.6212603 | G109: 2.2433573 | H109: 3.148533 | I109: 3.8969849 | J109: 4.7274411 | K109: 5.7676813 | L109: 6.9421188 | M109: 8.2513114 | N109: 9.6973932 | O109: 11.328151 | P109: 13.147252 | R109: =(J109/D109)^(1/6)-1 -> 0.24490468 | S109: =(P109/J109)^(1/6)-1 -> 0.18586379
A110: Growth rate (%) | C110: =C109/B109-1 -> 0.43394921 | D110: =D109/C109-1 -> 0.22531253 | E110: =E109/D109-1 -> 0.18351761 | F110: =F109/E109-1 -> 0.078620055 | G110: =G109/F109-1 -> 0.38371203 | H110: =H109/G109-1 -> 0.40349152 | I110: =I109/H109-1 -> 0.2377145 | J110: =J109/I109-1 -> 0.21310223 | ... P110: =P109/O109-1 -> 0.16058236
A111: Total | B111: =B109+B107+B105+B103 -> 7.5313444 | C111: =C109+C107+C105+C103 -> 10.354413 | D111: =D109+D107+D105+D103 -> 12.423086 | E111: =E109+E107+E105+E103 -> 14.461263 | F111: =F109+F107+F105+F103 -> 15.532901 | G111: =G109+G107+G105+G103 -> 20.711734 | H111: =H109+H107+H105+H103 -> 27.6841 | I111: =I109+I107+I105+I103 -> 33.808147 | ... P111: =P109+P107+P105+P103 -> 99.536309 | R111: =(J111/D111)^(1/6)-1 -> 0.21911947 | S111: =(P111/J111)^(1/6)-1 -> 0.16032345
A112: Growth rate (%) | C112: =C111/B111-1 -> 0.3748426 | D112: =D111/C111-1 -> 0.19978664 | E112: =E111/D111-1 -> 0.16406361 | F112: =F111/E111-1 -> 0.074104027 | G112: =G111/F111-1 -> 0.33341059 | H112: =H111/G111-1 -> 0.33663841 | I112: =I111/H111-1 -> 0.2212117 | J112: =J111/I111-1 -> 0.2063845 | ... P112: =P111/O111-1 -> 0.13823276
A114: Private cloud spending per capita (by size of enterprises) (€ )
...

Sheet Czech Republic
A1: Year | B1: 2016 | C1: 2017 | D1: 2018 | E1: 2019 | F1: 2020 | G1: 2021 | H1: 2022 | I1: 2023 | J1: 2024 | K1: 2025e | L1: 2026f | M1: 2027f | N1: 2028f | O1: 2029f | P1: 2030f | R1: CAGR 2019-2024 | S1: CAGR 2025-2030
A2: Total IT market size (€ m) | B2: =B4+B6+B8 -> 5099.4372 | C2: =C4+C6+C8 -> 5299.258 | D2: =D4+D6+D8 -> 5507.3186 | E2: =E4+E6+E8 -> 5840.0348 | F2: =F4+F6+F8 -> 6019.9458 | G2: =G4+G6+G8 -> 6439.378 | H2: =H4+H6+H8 -> 6804.8176 | I2: =I4+I6+I8 -> 7327.0026 | ... P2: =P4+P6+P8 -> 11004.718 | R2: =(J2/D2)^(1/6)-1 -> 0.062174429 | S2: =(P2/J2)^(1/6)-1 -> 0.056600009
A3: Growth rate (%) | C3: =C2/B2-1 -> 0.03918487 | D3: =D2/C2-1 -> 0.039262214 | E3: =E2/D2-1 -> 0.060413452 | F3: =F2/E2-1 -> 0.030806503 | G3: =G2/F2-1 -> 0.069673742 | H3: =H2/G2-1 -> 0.056750768 | I3: =I2/H2-1 -> 0.076737539 | J3: =J2/I2-1 -> 0.079416149 | ... P3: =P2/O2-1 -> 0.057713428
A4: Software | B4: 1088.8779 | C4: 1151.0288 | D4: 1202.7616 | E4: 1270.2152 | F4: 1324.9869 | G4: 1388.4517 | H4: 1456.4678 | I4: 1582.6504 | J4: 1716.6336 | K4: 1825.1558 | L4: 1946.5849 | M4: 2073.6731 | N4: 2217.6299 | O4: 2381.367 | P4: 2552.1423 | R4: =(J4/D4)^(1/6)-1 -> 0.061083782 | S4: =(P4/J4)^(1/6)-1 -> 0.068327846
A5: Growth rate (%) | C5: =C4/B4-1 -> 0.057077944 | D5: =D4/C4-1 -> 0.044944787 | E5: =E4/D4-1 -> 0.056082308 | F5: =F4/E4-1 -> 0.043119986 | G5: =G4/F4-1 -> 0.047898491 | H5: =H4/G4-1 -> 0.048986955 | I5: =I4/H4-1 -> 0.086636062 | J5: =J4/I4-1 -> 0.084657468 | ... P5: =P4/O4-1 -> 0.071713137
A6: Hardware | B6: 2021.5963 | C6: 2069.6314 | D6: 2141.7343 | E6: 2293.3671 | F6: 2410.8101 | G6: 2712.4784 | H6: 2879.4063 | I6: 3093.9146 | J6: 3349.8864 | K6: 3502.4852 | L6: 3664.4887 | M6: 3777.3053 | N6: 3944.9022 | O6: 4124.8603 | P6: 4269.9579 | R6: =(J6/D6)^(1/6)-1 -> 0.077401099 | S6: =(P6/J6)^(1/6)-1 -> 0.041275344
A7: Growth rate (%) | C7: =C6/B6-1 -> 0.02376098 | D7: =D6/C6-1 -> 0.034838522 | E7: =E6/D6-1 -> 0.070799064 | F7: =F6/E6-1 -> 0.051209856 | G7: =G6/F6-1 -> 0.12513152 | H7: =H6/G6-1 -> 0.061540728 | I7: =I6/H6-1 -> 0.074497392 | J7: =J6/I6-1 -> 0.082733957 | ... P7: =P6/O6-1 -> 0.035176367
A8: Services | B8: 1988.963 | C8: 2078.5978 | D8: 2162.8227 | E8: 2276.4524 | F8: 2284.1488 | G8: 2338.4478 | H8: 2468.9435 | I8: 2650.4376 | J8: 2842.3649 | K8: 3013.3515 | L8: 3200.3907 | M8: 3398.1291 | N8: 3630.3205 | O8: 3898.0255 | P8: 4182.6177 | R8: =(J8/D8)^(1/6)-1 -> 0.046589767 | S8: =(P8/J8)^(1/6)-1 -> 0.066501301
A9: Growth rate (%) | C9: =C8/B8-1 -> 0.045066078 | D9: =D8/C8-1 -> 0.040520084 | E9: =E8/D8-1 -> 0.052537683 | F9: =F8/E8-1 -> 0.003380868 | G9: =G8/F8-1 -> 0.023772068 | H9: =H8/G8-1 -> 0.05580442 | I9: =I8/H8-1 -> 0.073510821 | J9: =J8/I8-1 -> 0.07241346 | ... P9: =P8/O8-1 -> 0.073009321
A11: Smartphones market size (€ m) | B11: 670.19347 | C11: 639.02292 | D11: 645.66272 | E11: 730.75951 | F11: 663.45362 | G11: 821.44649 | H11: 906.53522 | I11: 942.59479 | J11: 995.86649 | K11: 1024.7731 | L11: 1062.9221 | M11: 1104.5106 | N11: 1148.1069 | O11: 1192.6683 | P11: 1233.2664 | R11: =(J11/D11)^(1/6)-1 -> 0.074894649 | S11: =(P11/J11)^(1/6)-1 -> 0.036277246
A12: Growth rate (%) | C12: =C11/B11-1 -> -0.04650978 | D12: =D11/C11-1 -> 0.010390562 | E12: =E11/D11-1 -> 0.13179758 | F12: =F11/E11-1 -> -0.092104017 | G12: =G11/F11-1 -> 0.23813702 | H12: =H11/G11-1 -> 0.10358402 | I12: =I11/H11-1 -> 0.039777353 | J12: =J11/I11-1 -> 0.056516014 | ... P12: =P11/O11-1 -> 0.034039718
A14: Cybersecurity market size (€ m) | B14: 132.48539 | C14: 148.2222 | D14: 169.45147 | E14: 187.47729 | F14: 189.88736 | G14: 202.76213 | H14: 237.8993 | I14: 266.55438 | J14: 287.31383 | K14: 309.07274 | L14: 335.76889 | M14: 359.53255 | N14: 384.12857 | O14: 411.0471 | P14: 442.61712 | R14: =(J14/D14)^(1/6)-1 -> 0.091989678 | S14: =(P14/J14)^(1/6)-1 -> 0.07467863
A15: Growth rate (%) | C15: =C14/B14-1 -> 0.11878149 | D15: =D14/C14-1 -> 0.14322598 | E15: =E14/D14-1 -> 0.10637747 | F15: =F14/E14-1 -> 0.012855262 | G15: =G14/F14-1 -> 0.067802193 | H15: =H14/G14-1 -> 0.17329255 | I15: =I14/H14-1 -> 0.12045047 | J15: =J14/I14-1 -> 0.077880718 | ... P15: =P14/O14-1 -> 0.076803898
A17: Enterprises (by size) (number of enterprises in thousands)
A18: Microenterprises (0-9 employees) | B18: 978.289 | C18: 978.967 | D18: 1001.856 | E18: 1017.047 | F18: 1027.516 | G18: 1056.265 | H18: 1080.92 | I18: 1093.393 | J18: 1100.9392 | K18: 1109.1063 | L18: 1121.3682 | M18: 1136.261 | N18: 1150.8738 | O18: 1165.2025 | P18: 1178.3824 | R18: =(J18/D18)^(1/6)-1 -> 0.015842413 | S18: =(P18/J18)^(1/6)-1 -> 0.011394261
A19: Growth rate (%) | C19: =C18/B18-1 -> 0.00069304674 | D19: =D18/C18-1 -> 0.023380768 | E19: =E18/D18-1 -> 0.015162858 | F19: =F18/E18-1 -> 0.010293526 | G19: =G18/F18-1 -> 0.027979126 | H19: =H18/G18-1 -> 0.02334168 | I19: =I18/H18-1 -> 0.011539244 | J19: =J18/I18-1 -> 0.0069016701 | ... P19: =P18/O18-1 -> 0.011311279
A20: SME (10-249 employees) | B20: 38.607 | C20: 39.187 | D20: 39.82 | E20: 40.066 | F20: 39.316 | G20: 40.968 | H20: 41.819 | I20: 41.363 | J20: 41.536688 | K20: 41.831757 | L20: 42.197443 | M20: 42.595759 | N20: 42.982816 | O20: 43.358698 | P20: 43.704219 | R20: =(J20/D20)^(1/6)-1 -> 0.0070594342 | S20: =(P20/J20)^(1/6)-1 -> 0.0085139639
A21: Growth rate (%) | C21: =C20/B20-1 -> 0.015023182 | D21: =D20/C20-1 -> 0.016153316 | E21: =E20/D20-1 -> 0.0061778001 | F21: =F20/E20-1 -> -0.018719113 | G21: =G20/F20-1 -> 0.042018517 | H21: =H20/G20-1 -> 0.02077231 | I21: =I20/H20-1 -> -0.010904134 | J21: =J20/I20-1 -> 0.004199127 | ... P21: =P20/O20-1 -> 0.0079688958
A22: Large enterprises (250+ employees) | B22: 1.577 | C22: 1.619 | D22: 1.654 | E22: 1.663 | F22: 1.614 | G22: 1.618 | H22: 1.667 | I22: 1.654 | J22: 1.6541017 | K22: 1.6624641 | L22: 1.6730493 | M22: 1.684344 | N22: 1.6946518 | O22: 1.7043265 | P22: 1.7127888 | R22: =(J22/D22)^(1/6)-1 -> 1.0244608e-05 | S22: =(P22/J22)^(1/6)-1 -> 0.0058277254
A23: Growth rate (%) | C23: =C22/B22-1 -> 0.026632847 | D23: =D22/C22-1 -> 0.021618283 | E23: =E22/D22-1 -> 0.0054413543 | F23: =F22/E22-1 -> -0.029464823 | G23: =G22/F22-1 -> 0.0024783147 | H23: =H22/G22-1 -> 0.030284302 | I23: =I22/H22-1 -> -0.0077984403 | J23: =J22/I22-1 -> 6.1469222e-05 | ... P23: =P22/O22-1 -> 0.0049651996
A24: Number of all enterprises | B24: =B18+B20+B22 -> 1018.473 | C24: =C18+C20+C22 -> 1019.773 | D24: =D18+D20+D22 -> 1043.33 | E24: =E18+E20+E22 -> 1058.776 | F24: =F18+F20+F22 -> 1068.446 | G24: =G18+G20+G22 -> 1098.851 | H24: =H18+H20+H22 -> 1124.406 | I24: =I18+I20+I22 -> 1136.41 | ... P24: =P18+P20+P22 -> 1223.7994 | R24: =(J24/D24)^(1/6)-1 -> 0.015489915 | S24: =(P24/J24)^(1/6)-1 -> 0.011282467
A25: Growth rate (%) | C25: =C24/B24-1 -> 0.0012764207 | D25: =D24/C24-1 -> 0.023100239 | E25: =E24/D24-1 -> 0.01480452 | F25: =F24/E24-1 -> 0.0091331878 | G25: =G24/F24-1 -> 0.028457217 | H25: =H24/G24-1 -> 0.02325611 | I25: =I24/H24-1 -> 0.010675859 | J25: =J24/I24-1 -> 0.0067933474 | ... P25: =P24/O24-1 -> 0.011182599
A27: Percentage of enterprises using cloud computing
A28: Percent of microenterprises using cloud computing | B28: 0.095469504 | C28: 0.10740833 | D28: 0.12064101 | E28: 0.13525693 | F28: 0.15133884 | G28: 0.16895928 | H28: 0.18817637 | I28: 0.20902941 | J28: 0.23153425 | K28: 0.25567882 | L28: 0.28141916 | M28: 0.30867623 | N28: 0.33733396 | O28: 0.36723896 | P28: 0.39820198
A29: Percent of SME using cloud computing | B29: 0.1766168 | C29: 0.20818811 | D29: 0.24373241 | E29: 0.28317495 | F29: 0.32624687 | G29: 0.37246603 | H29: 0.42114021 | I29: 0.47139701 | J29: 0.52224043 | K29: 0.57262714 | L29: 0.62155071 | M29: 0.66811967 | N29: 0.71161699 | O29: 0.75153351 | P29: 0.78757427
A30: Percent of large enterprises using cloud computing | B30: 0.29689057 | C30: 0.36268532 | D30: 0.43405957 | E30: 0.50827771 | F30: 0.58213277 | G30: 0.65247943 | H30: 0.71674583 | I30: 0.77325759 | J30: 0.82130565 | K30: 0.86100226 | L30: 0.89302892 | M30: 0.91837583 | N30: 0.93813285 | O30: 0.95335062 | P30: 0.964965
A31: Percent of all enterprises using cloud computing | B31: 0.098857414 | C31: 0.11168629 | D31: 0.12583582 | E31: 0.14144031 | F31: 0.15842576 | G31: 0.17725849 | H31: 0.19762442 | I31: 0.21940027 | J31: 0.24294074 | K31: 0.26805504 | L31: 0.29461469 | M31: 0.3225154 | N31: 0.35164191 | O31: 0.38183198 | P31: 0.41290044
A33: Number of enterprises using cloud computing (thousands)
A34: Number of microenterprises using cloud computing | B34: =B28*B18 -> 93.396766 | C34: =C28*C18 -> 105.14921 | D34: =D28*D18 -> 120.86492 | E34: =E28*E18 -> 137.56265 | F34: =F28*F18 -> 155.50308 | G34: =G28*G18 -> 178.46577 | H34: =H28*H18 -> 203.4036 | I34: =I28*I18 -> 228.55129 | ... P34: =P28*P18 -> 469.23422 | R34: =(J34/D34)^(1/6)-1 -> 0.13243439 | S34: =(P34/J34)^(1/6)-1 -> 0.10705326
A35: Growth rate (%) | C35: =C34/B34-1 -> 0.12583348 | D35: =D34/C34-1 -> 0.14946111 | E35: =E34/D34-1 -> 0.13815199 | F35: =F34/E34-1 -> 0.13041643 | G35: =G34/F34-1 -> 0.14766711 | H35: =H34/G34-1 -> 0.13973453 | I35: =I34/H34-1 -> 0.12363444 | J35: =J34/I34-1 -> 0.11530822 | ... P35: =P34/O34-1 -> 0.096577995
A36: Number of SME using cloud computing | B36: =B29*B20 -> 6.8186448 | C36: =C29*C20 -> 8.1582674 | D36: =D29*D20 -> 9.7054244 | E36: =E29*E20 -> 11.345688 | F36: =F29*F20 -> 12.826722 | G36: =G29*G20 -> 15.259189 | H36: =H29*H20 -> 17.611662 | I36: =I29*I20 -> 19.498395 | ... P36: =P29*P20 -> 34.420319 | R36: =(J36/D36)^(1/6)-1 -> 0.14344331 | S36: =(P36/J36)^(1/6)-1 -> 0.079987563
A37: Growth rate (%) | C37: =C36/B36-1 -> 0.19646463 | D37: =D36/C36-1 -> 0.18964284 | E37: =E36/D36-1 -> 0.1690048 | F37: =F36/E36-1 -> 0.13053718 | G37: =G36/F36-1 -> 0.18964056 | H37: =H36/G36-1 -> 0.15416769 | I37: =I36/H36-1 -> 0.1071297 | J37: =J36/I36-1 -> 0.11250893 | ... P37: =P36/O36-1 -> 0.056307352
A38: Number of large enterprises using cloud computing | B38: =B30*B22 -> 0.46819643 | C38: =C30*C22 -> 0.58718753 | D38: =D30*D22 -> 0.71793452 | E38: =E30*E22 -> 0.84526584 | F38: =F30*F22 -> 0.9395623 | G38: =G30*G22 -> 1.0557117 | H38: =H30*H22 -> 1.1948153 | I38: =I30*I22 -> 1.2789681 | ... P38: =P30*P22 -> 1.6527812 | R38: =(J38/D38)^(1/6)-1 -> 0.11215084 | S38: =(P38/J38)^(1/6)-1 -> 0.033216645
A39: Growth rate (%) | C39: =C38/B38-1 -> 0.25414781 | D39: =D38/C38-1 -> 0.22266651 | E39: =E38/D38-1 -> 0.17735784 | F39: =F38/E38-1 -> 0.11155835 | G39: =G38/F38-1 -> 0.12362077 | H39: =H38/G38-1 -> 0.13176285 | I39: =I38/H38-1 -> 0.070431598 | J39: =J38/I38-1 -> 0.06220249 | ... P39: =P38/O38-1 -> 0.017208375
A40: Number of all enterprises using cloud computing | B40: =B38+B36+B34 -> 100.68361 | C40: =C38+C36+C34 -> 113.89466 | D40: =D38+D36+D34 -> 131.28828 | E40: =E38+E36+E34 -> 149.75361 | F40: =F38+F36+F34 -> 169.26937 | G40: =G38+G36+G34 -> 194.78067 | H40: =H38+H36+H34 -> 222.21008 | I40: =I38+I36+I34 -> 249.32866 | ... P40: =P38+P36+P34 -> 505.30732 | R40: =(J40/D40)^(1/6)-1 -> 0.13316103 | S40: =(P40/J40)^(1/6)-1 -> 0.10474822
A41: Growth rate (%) | C41: =C40/B40-1 -> 0.13121355 | D41: =D40/C40-1 -> 0.15271674 | E41: =E40/D40-1 -> 0.14064716 | F41: =F40/E40-1 -> 0.13031914 | G41: =G40/F40-1 -> 0.15071425 | H41: =H40/G40-1 -> 0.14082202 | I41: =I40/H40-1 -> 0.12204026 | J41: =J40/I40-1 -> 0.11481689 | ... P41: =P40/O40-1 -> 0.09345931
A43: Total cloud computing market size (€ m) | B43: =B55+B111 -> 77.002881 | C43: =C55+C111 -> 98.854043 | D43: =D55+D111 -> 126.73646 | E43: =E55+E111 -> 162.44468 | F43: =F55+F111 -> 206.47892 | G43: =G55+G111 -> 266.44934 | H43: =H55+H111 -> 354.04675 | I43: =I55+I111 -> 442.15888 | ... P43: =P55+P111 -> 1238.0938 | R43: =(J43/D43)^(1/6)-1 -> 0.27424215 | S43: =(P43/J43)^(1/6)-1 -> 0.1474225
A44: Growth rate (%) | C44: =C43/B43-1 -> 0.2837707 | D44: =D43/C43-1 -> 0.28205644 | E44: =E43/D43-1 -> 0.28175174 | F44: =F43/E43-1 -> 0.2710722 | G44: =G43/F43-1 -> 0.29044331 | H44: =H43/G43-1 -> 0.3287582 | I44: =I43/H43-1 -> 0.24887147 | J44: =J43/I43-1 -> 0.22697309 | ... P44: =P43/O43-1 -> 0.13243632
A46: Public cloud (by size of enterprises) (€ m)
A47: Microenterprises (0-9 employees) | B47: 4.5573626 | C47: 5.9435609 | D47: 7.772092 | E47: 10.268585 | F47: 13.314834 | G47: 17.394595 | H47: 23.142811 | I47: 29.042583 | J47: 35.82016 | K47: 42.717391 | L47: 50.170799 | M47: 57.83611 | N47: 67.9217 | O47: 79.827173 | P47: 91.862065 | R47: =(J47/D47)^(1/6)-1 -> 0.29002541 | S47: =(P47/J47)^(1/6)-1 -> 0.16995219
A48: Growth rate (%) | C48: =C47/B47-1 -> 0.30416678 | D48: =D47/C47-1 -> 0.3076491 | E48: =E47/D47-1 -> 0.32121247 | F48: =F47/E47-1 -> 0.29665718 | G48: =G47/F47-1 -> 0.30640716 | H48: =H47/G47-1 -> 0.33045987 | I48: =I47/H47-1 -> 0.25492896 | J48: =J47/I47-1 -> 0.23336687 | ... P48: =P47/O47-1 -> 0.15076184
A49: SME (10-249 employees) | B49: 42.830301 | C49: 53.728663 | D49: 67.20519 | E49: 84.137232 | F49: 104.70251 | G49: 131.25023 | H49: 173.53646 | I49: 215.50644 | J49: 262.13707 | K49: 292.26415 | L49: 331.81869 | M49: 369.6577 | N49: 419.39325 | O49: 476.0211 | P49: 528.82622 | R49: =(J49/D49)^(1/6)-1 -> 0.25464522 | S49: =(P49/J49)^(1/6)-1 -> 0.12408052
A50: Growth rate (%) | C50: =C49/B49-1 -> 0.25445448 | D50: =D49/C49-1 -> 0.25082566 | E50: =E49/D49-1 -> 0.25194545 | F50: =F49/E49-1 -> 0.24442547 | G50: =G49/F49-1 -> 0.25355377 | H50: =H49/G49-1 -> 0.32218018 | I50: =I49/H49-1 -> 0.24185109 | J50: =J49/I49-1 -> 0.21637698 | ... P50: =P49/O49-1 -> 0.1109302
A51: Large enterprises (250+ employees) | B51: 7.9920237 | C51: 11.147015 | D51: 15.492695 | E51: 21.308037 | F51: 28.836969 | G51: 40.281993 | H51: 54.64087 | I51: 69.287562 | J51: 86.87107 | K51: 109.23764 | L51: 131.99427 | M51: 156.31558 | N51: 188.33265 | O51: 226.79983 | P51: 267.11929 | R51: =(J51/D51)^(1/6)-1 -> 0.33288097 | S51: =(P51/J51)^(1/6)-1 -> 0.20588256
A52: Growth rate (%) | C52: =C51/B51-1 -> 0.39476747 | D52: =D51/C51-1 -> 0.38985147 | E52: =E51/D51-1 -> 0.37536031 | F52: =F51/E51-1 -> 0.35333762 | G52: =G51/F51-1 -> 0.39688723 | H52: =H51/G51-1 -> 0.35645893 | I52: =I51/H51-1 -> 0.26805379 | J52: =J51/I51-1 -> 0.25377583 | ... P52: =P51/O51-1 -> 0.17777554
A53: Public administration | B53: 3.3473789 | C53: 4.4842586 | D53: 5.9963371 | E53: 8.0343901 | F53: 10.658929 | G53: 14.35894 | H53: 19.130048 | I53: 24.155227 | J53: 30.122437 | K53: 36.738254 | L53: 43.725585 | M53: 51.054855 | N53: 60.700868 | O53: 72.192494 | P53: 84.032959 | R53: =(J53/D53)^(1/6)-1 -> 0.30868164 | S53: =(P53/J53)^(1/6)-1 -> 0.18647864
A54: Growth rate (%) | C54: =C53/B53-1 -> 0.33963281 | D54: =D53/C53-1 -> 0.33719698 | E54: =E53/D53-1 -> 0.33988299 | F54: =F53/E53-1 -> 0.32666316 | G54: =G53/F53-1 -> 0.3471278 | H54: =H53/G53-1 -> 0.3322744 | I54: =I53/H53-1 -> 0.26268511 | J54: =J53/I53-1 -> 0.24703597 | ... P54: =P53/O53-1 -> 0.1640124
A55: Total | B55: =B53+B51+B49+B47 -> 58.727066 | C55: =C53+C51+C49+C47 -> 75.303497 | D55: =D53+D51+D49+D47 -> 96.466314 | E55: =E53+E51+E49+E47 -> 123.74824 | F55: =F53+F51+F49+F47 -> 157.51325 | G55: =G53+G51+G49+G47 -> 203.28576 | H55: =H53+H51+H49+H47 -> 270.45018 | I55: =I53+I51+I49+I47 -> 337.99181 | ... P55: =P53+P51+P49+P47 -> 971.84053 | R55: =(J55/D55)^(1/6)-1 -> 0.27527391 | S55: =(P55/J55)^(1/6)-1 -> 0.1523907
A56: Growth rate (%) | C56: =C55/B55-1 -> 0.2822622 | D56: =D55/C55-1 -> 0.28103366 | E56: =E55/D55-1 -> 0.28281303 | F56: =F55/E55-1 -> 0.27285237 | G56: =G55/F55-1 -> 0.29059469 | H56: =H55/G55-1 -> 0.33039414 | I56: =I55/H55-1 -> 0.24973776 | J56: =J55/I55-1 -> 0.22769465 | ... P56: =P55/O55-1 -> 0.13686755
A58: Public cloud spending per capita (by size of enterprises) (€ )
A59: Microenterprises (0-9 employees) | B59: =(B47*1000000)/(B34*1000) -> 48.795721 | C59: =(C47*1000000)/(C34*1000) -> 56.525019 | D59: =(D47*1000000)/(D34*1000) -> 64.30395 | E59: =(E47*1000000)/(E34*1000) -> 74.646604 | F59: =(F47*1000000)/(F34*1000) -> 85.624247 | G59: =(G47*1000000)/(G34*1000) -> 97.4674 | H59: =(H47*1000000)/(H34*1000) -> 113.77778 | I59: =(I47*1000000)/(I34*1000) -> 127.07249 | ... P59: =(P47*1000000)/(P34*1000) -> 195.77017 | R59: =(J59/D59)^(1/6)-1 -> 0.13916128 | S59: =(P59/J59)^(1/6)-1 -> 0.056816532
A60: Growth rate (%) | C60: =C59/B59-1 -> 0.15840114 | D60: =D59/C59-1 -> 0.13761926 | E60: =E59/D59-1 -> 0.1608401 | F60: =F59/E59-1 -> 0.14706151 | G60: =G59/F59-1 -> 0.13831542 | H60: =H59/G59-1 -> 0.1673419 | I60: =I59/H59-1 -> 0.11684807 | J60: =J59/I59-1 -> 0.10585294 | ... P60: =P59/O59-1 -> 0.04941176
A61: SME (10-249 employees) | B61: =(B49*1000000)/(B36*1000) -> 6281.3509 | C61: =(C49*1000000)/(C36*1000) -> 6585.7933 | D61: =(D49*1000000)/(D36*1000) -> 6924.4978 | E61: =(E49*1000000)/(E36*1000) -> 7415.7895 | F61: =(F49*1000000)/(F36*1000) -> 8162.8428 | G61: =(G49*1000000)/(G36*1000) -> 8601.39 | H61: =(H49*1000000)/(H36*1000) -> 9853.4966 | I61: =(I49*1000000)/(I36*1000) -> 11052.522 | ... P61: =(P49*1000000)/(P36*1000) -> 15363.78 | R61: =(J61/D61)^(1/6)-1 -> 0.097251793 | S61: =(P61/J61)^(1/6)-1 -> 0.040827286
A62: Growth rate (%) | C62: =C61/B61-1 -> 0.048467663 | D62: =D61/C61-1 -> 0.051429568 | E62: =E61/D61-1 -> 0.070949795 | F62: =F61/E61-1 -> 0.1007382 | G62: =G61/F61-1 -> 0.053724814 | H62: =H61/G61-1 -> 0.14557026 | I62: =I61/H61-1 -> 0.12168528 | J62: =J61/I61-1 -> 0.093363791 | ... P62: =P61/O61-1 -> 0.051711133
A63: Large enterprises (250+ employees) | B63: =(B51*1000000)/(B38*1000) -> 17069.809 | C63: =(C51*1000000)/(C38*1000) -> 18983.739 | D63: =(D51*1000000)/(D38*1000) -> 21579.537 | E63: =(E51*1000000)/(E38*1000) -> 25208.682 | F63: =(F51*1000000)/(F38*1000) -> 30691.918 | G63: =(G51*1000000)/(G38*1000) -> 38156.244 | H63: =(H51*1000000)/(H38*1000) -> 45731.645 | I63: =(I51*1000000)/(I38*1000) -> 54174.583 | ... P63: =(P51*1000000)/(P38*1000) -> 161618.05 | R63: =(J63/D63)^(1/6)-1 -> 0.19847139 | S63: =(P63/J63)^(1/6)-1 -> 0.16711491
A64: Growth rate (%) | C64: =C63/B63-1 -> 0.11212368 | D64: =D63/C63-1 -> 0.13673799 | E64: =E63/D63-1 -> 0.16817527 | F64: =F63/E63-1 -> 0.21751379 | G64: =G63/F63-1 -> 0.24320168 | H64: =H63/G63-1 -> 0.19853636 | I64: =I63/H63-1 -> 0.18461917 | J64: =J63/I63-1 -> 0.18035482 | ... P64: =P63/O63-1 -> 0.15785081
A65: Total | B65: =(B55*1000000)/(B40*1000) -> 583.28329 | C65: =(C55*1000000)/(C40*1000) -> 661.16793 | D65: =(D55*1000000)/(D40*1000) -> 734.76713 | E65: =(E55*1000000)/(E40*1000) -> 826.34567 | F65: =(F55*1000000)/(F40*1000) -> 930.54785 | G65: =(G55*1000000)/(G40*1000) -> 1043.6649 | H65: =(H55*1000000)/(H40*1000) -> 1217.0923 | I65: =(I55*1000000)/(I40*1000) -> 1355.6075 | ... P65: =(P55*1000000)/(P40*1000) -> 1923.2663 | R65: =(J65/D65)^(1/6)-1 -> 0.12541279 | S65: =(P65/J65)^(1/6)-1 -> 0.043125196
A66: Growth rate (%) | C66: =C65/B65-1 -> 0.13352797 | D66: =D65/C65-1 -> 0.11131695 | E66: =E65/D65-1 -> 0.12463615 | F66: =F65/E65-1 -> 0.12609999 | G66: =G65/F65-1 -> 0.12155967 | H66: =H65/G65-1 -> 0.16617151 | I66: =I65/H65-1 -> 0.11380831 | J66: =J65/I65-1 -> 0.10125229 | ... P66: =P65/O65-1 -> 0.039698083
A68: Public cloud (by model) (€ m)
A69: SaaS | B69: 36.453438 | C69: 46.470722 | D69: 58.342857 | E69: 74.723892 | F69: 94.113211 | G69: 120.25147 | H69: 157.95145 | I69: 195.60089 | J69: 237.6405 | K69: 273.01554 | L69: 314.1382 | M69: 355.23056 | N69: 408.5261 | O69: 469.9576 | P69: 529.6447 | R69: =(J69/D69)^(1/6)-1 -> 0.26373339 | S69: =(P69/J69)^(1/6)-1 -> 0.14290648
A70: Growth rate (%) | C70: =C69/B69-1 -> 0.27479668 | D70: =D69/C69-1 -> 0.25547558 | E70: =E69/D69-1 -> 0.28077191 | F70: =F69/E69-1 -> 0.25947951 | G70: =G69/F69-1 -> 0.27773206 | H70: =H69/G69-1 -> 0.31350953 | I70: =I69/H69-1 -> 0.23836087 | J70: =J69/I69-1 -> 0.21492544 | ... P70: =P69/O69-1 -> 0.1270053
A71: IaaS | B71: 19.431245 | C71: 25.112092 | D71: 33.142683 | E71: 42.550394 | F71: 54.934994 | G71: 71.817402 | H71: 97.22378 | I71: 122.8336 | J71: 152.73835 | K71: 178.48102 | L71: 208.51715 | M71: 239.99849 | N71: 280.78761 | O71: 328.43519 | P71: 377.28599 | R71: =(J71/D71)^(1/6)-1 -> 0.29001098 | S71: =(P71/J71)^(1/6)-1 -> 0.16266276
A72: Growth rate (%) | C72: =C71/B71-1 -> 0.29235632 | D72: =D71/C71-1 -> 0.31978979 | E72: =E71/D71-1 -> 0.28385486 | F72: =F71/E71-1 -> 0.29105722 | G72: =G71/F71-1 -> 0.30731611 | H72: =H71/G71-1 -> 0.35376353 | I72: =I71/H71-1 -> 0.26341107 | J72: =J71/I71-1 -> 0.24345745 | ... P72: =P71/O71-1 -> 0.14873805
A73: PaaS | B73: 2.8423829 | C73: 3.7206825 | D73: 4.9807742 | E73: 6.4739581 | F73: 8.4650419 | G73: 11.216891 | H73: 15.274956 | I73: 19.557316 | J73: 24.57188 | K73: 29.460878 | L73: 35.05399 | M73: 39.635195 | N73: 47.034756 | O73: 56.447809 | P73: 64.909829 | R73: =(J73/D73)^(1/6)-1 -> 0.30473883 | S73: =(P73/J73)^(1/6)-1 -> 0.17574195
A74: Growth rate (%) | C74: =C73/B73-1 -> 0.30900116 | D74: =D73/C73-1 -> 0.33867217 | E74: =E73/D73-1 -> 0.29978954 | F74: =F73/E73-1 -> 0.30755277 | G74: =G73/F73-1 -> 0.3250839 | H74: =H73/G73-1 -> 0.3617816 | I74: =I73/H73-1 -> 0.28035173 | J74: =J73/I73-1 -> 0.25640349 | ... P74: =P73/O73-1 -> 0.14990875
A75: Total | B75: =B69+B71+B73 -> 58.727066 | C75: =C69+C71+C73 -> 75.303497 | D75: =D69+D71+D73 -> 96.466314 | E75: =E69+E71+E73 -> 123.74824 | F75: =F69+F71+F73 -> 157.51325 | G75: =G69+G71+G73 -> 203.28576 | H75: =H69+H71+H73 -> 270.45018 | I75: =I69+I71+I73 -> 337.99181 | ... P75: =P69+P71+P73 -> 971.84053 | R75: =(J75/D75)^(1/6)-1 -> 0.27527391 | S75: =(P75/J75)^(1/6)-1 -> 0.1523907
A76: Growth rate (%) | C76: =C75/B75-1 -> 0.2822622 | D76: =D75/C75-1 -> 0.28103366 | E76: =E75/D75-1 -> 0.28281303 | F76: =F75/E75-1 -> 0.27285237 | G76: =G75/F75-1 -> 0.29059469 | H76: =H75/G75-1 -> 0.33039414 | I76: =I75/H75-1 -> 0.24973776 | J76: =J75/I75-1 -> 0.22769465 | ... P76: =P75/O75-1 -> 0.13686755
A78: SaaS spending (by advanced and basic solutions) (€ m)
A79: Basic | B79: 24.608799 | C79: 30.976301 | D79: 38.013984 | E79: 47.804384 | F79: 59.782575 | G79: 72.074281 | H79: 93.50803 | I79: 114.87382 | J79: 137.74837 | K79: 155.25 | L79: 175.30732 | M79: 194.6227 | N79: 219.83056 | O79: 248.48828 | P79: 275.30721 | R79: =(J79/D79)^(1/6)-1 -> 0.23934014 | S79: =(P79/J79)^(1/6)-1 -> 0.12233331
A80: Growth rate (%) | C80: =C79/B79-1 -> 0.258749 | D80: =D79/C79-1 -> 0.22719571 | E80: =E79/D79-1 -> 0.25754733 | F80: =F79/E79-1 -> 0.25056678 | G80: =G79/F79-1 -> 0.20560683 | H80: =H79/G79-1 -> 0.29738416 | I80: =I79/H79-1 -> 0.22849154 | J80: =J79/I79-1 -> 0.19912759 | ... P80: =P79/O79-1 -> 0.10792836
A81: Advanced | B81: 11.844639 | C81: 15.494421 | D81: 20.328873 | E81: 26.919508 | F81: 34.330636 | G81: 48.177187 | H81: 64.443418 | I81: 80.727068 | J81: 99.892129 | K81: 117.76553 | L81: 138.83088 | M81: 160.60786 | N81: 188.69554 | O81: 221.46932 | P81: 254.33749 | R81: =(J81/D81)^(1/6)-1 -> 0.30387611 | S81: =(P81/J81)^(1/6)-1 -> 0.1685479
A82: Growth rate (%) | C82: =C81/B81-1 -> 0.30813786 | D82: =D81/C81-1 -> 0.31201244 | E82: =E81/D81-1 -> 0.32420071 | F82: =F81/E81-1 -> 0.27530698 | G82: =G81/F81-1 -> 0.40332928 | H82: =H81/G81-1 -> 0.33763348 | I82: =I81/H81-1 -> 0.25268136 | J82: =J81/I81-1 -> 0.23740563 | ... P82: =P81/O81-1 -> 0.1484096
A83: Total | B83: =B79+B81 -> 36.453438 | C83: =C79+C81 -> 46.470722 | D83: =D79+D81 -> 58.342857 | E83: =E79+E81 -> 74.723892 | F83: =F79+F81 -> 94.113211 | G83: =G79+G81 -> 120.25147 | H83: =H79+H81 -> 157.95145 | I83: =I79+I81 -> 195.60089 | ... P83: =P79+P81 -> 529.6447 | R83: =(J83/D83)^(1/6)-1 -> 0.26373339 | S83: =(P83/J83)^(1/6)-1 -> 0.14290648
A84: Growth rate (%) | C84: =C83/B83-1 -> 0.27479668 | D84: =D83/C83-1 -> 0.25547558 | E84: =E83/D83-1 -> 0.28077191 | F84: =F83/E83-1 -> 0.25947951 | G84: =G83/F83-1 -> 0.27773206 | H84: =H83/G83-1 -> 0.31350953 | I84: =I83/H83-1 -> 0.23836087 | J84: =J83/I83-1 -> 0.21492544 | ... P84: =P83/O83-1 -> 0.1270053
A86: IaaS spending (by hyper and shared solutions) (€ m)
A87: Hyper | B87: 7.7724979 | C87: 10.547079 | D87: 14.615923 | E87: 19.70296 | F87: 26.709531 | G87: 36.66369 | H87: 50.874816 | I87: 65.882701 | J87: 83.970393 | K87: 100.0853 | L87: 119.26698 | M87: 140.01904 | N87: 165.45425 | O87: 195.46591 | P87: 226.78452 | R87: =(J87/D87)^(1/6)-1 -> 0.33828925 | S87: =(P87/J87)^(1/6)-1 -> 0.18008838
A88: Growth rate (%) | C88: =C87/B87-1 -> 0.35697414 | D88: =D87/C87-1 -> 0.38577928 | E88: =E87/D87-1 -> 0.3480476 | F88: =F87/E87-1 -> 0.35561008 | G88: =G87/F87-1 -> 0.37268192 | H88: =H87/G87-1 -> 0.38760762 | I88: =I87/H87-1 -> 0.29499634 | J88: =J87/I87-1 -> 0.27454388 | ... P88: =P87/O87-1 -> 0.16022543
A89: Shared | B89: 11.658747 | C89: 14.565013 | D89: 18.52676 | E89: 22.847434 | F89: 28.225462 | G89: 35.153712 | H89: 46.348963 | I89: 56.950898 | J89: 68.76796 | K89: 78.395721 | L89: 89.250176 | M89: 99.979445 | N89: 115.33337 | O89: 132.96928 | P89: 150.50148 | R89: =(J89/D89)^(1/6)-1 -> 0.24431722 | S89: =(P89/J89)^(1/6)-1 -> 0.13944256
A90: Growth rate (%) | C90: =C89/B89-1 -> 0.24927778 | D90: =D89/C89-1 -> 0.2720043 | E90: =E89/D89-1 -> 0.23321264 | F90: =F89/E89-1 -> 0.23538872 | G90: =G89/F89-1 -> 0.24546097 | H90: =H89/G89-1 -> 0.31846571 | I90: =I89/H89-1 -> 0.22874157 | J90: =J89/I89-1 -> 0.20749562 | ... P90: =P89/O89-1 -> 0.13185151
A91: Total | B91: =B89+B87 -> 19.431245 | C91: =C89+C87 -> 25.112092 | D91: =D89+D87 -> 33.142683 | E91: =E89+E87 -> 42.550394 | F91: =F89+F87 -> 54.934994 | G91: =G89+G87 -> 71.817402 | H91: =H89+H87 -> 97.22378 | I91: =I89+I87 -> 122.8336 | ... P91: =P89+P87 -> 377.28599 | R91: =(J91/D91)^(1/6)-1 -> 0.29001098 | S91: =(P91/J91)^(1/6)-1 -> 0.16266276
A92: Growth rate (%) | C92: =C91/B91-1 -> 0.29235632 | D92: =D91/C91-1 -> 0.31978979 | E92: =E91/D91-1 -> 0.28385486 | F92: =F91/E91-1 -> 0.29105722 | G92: =G91/F91-1 -> 0.30731611 | H92: =H91/G91-1 -> 0.35376353 | I92: =I91/H91-1 -> 0.26341107 | J92: =J91/I91-1 -> 0.24345745 | ... P92: =P91/O91-1 -> 0.14873805
A94: PaaS spending (by hyper and shared solutions) (€ m)
A95: Hyper | B95: 1.4211914 | C95: 1.9533583 | D95: 2.7456518 | E95: 3.7472079 | F95: 5.1446557 | G95: 7.1579554 | H95: 9.9912613 | I95: 13.112137 | J95: 16.885988 | K95: 20.75189 | L95: 25.185443 | M95: 29.046466 | N95: 35.158584 | O95: 43.038759 | P95: 50.480458 | R95: =(J95/D95)^(1/6)-1 -> 0.35356829 | S95: =(P95/J95)^(1/6)-1 -> 0.20023458
A96: Growth rate (%) | C96: =C95/B95-1 -> 0.37445122 | D96: =D95/C95-1 -> 0.40560578 | E96: =E95/D95-1 -> 0.36477902 | F96: =F95/E95-1 -> 0.37293041 | G96: =G95/F95-1 -> 0.3913381 | H96: =H95/G95-1 -> 0.39582614 | I96: =I95/H95-1 -> 0.31236053 | J96: =J95/I95-1 -> 0.28781358 | ... P96: =P95/O95-1 -> 0.17290692
A97: Shared | B97: 1.4211914 | C97: 1.7673242 | D97: 2.2351224 | E97: 2.7267502 | F97: 3.3203862 | G97: 4.0589353 | H97: 5.2836942 | I97: 6.4451788 | J97: 7.6858917 | K97: 8.7089886 | L97: 9.8685471 | M97: 10.588729 | N97: 11.876172 | O97: 13.40905 | P97: 14.429371 | R97: =(J97/D97)^(1/6)-1 -> 0.22856694 | S97: =(P97/J97)^(1/6)-1 -> 0.11068828
A98: Growth rate (%) | C98: =C97/B97-1 -> 0.24355111 | D98: =D97/C97-1 -> 0.26469292 | E98: =E97/D97-1 -> 0.21995567 | F98: =F97/E97-1 -> 0.21770824 | G98: =G97/F97-1 -> 0.22242867 | H98: =H97/G97-1 -> 0.30174387 | I98: =I97/H97-1 -> 0.21982434 | J98: =J97/I97-1 -> 0.19250249 | ... P98: =P97/O97-1 -> 0.076091969
A99: Total | B99: =B97+B95 -> 2.8423829 | C99: =C97+C95 -> 3.7206825 | D99: =D97+D95 -> 4.9807742 | E99: =E97+E95 -> 6.4739581 | F99: =F97+F95 -> 8.4650419 | G99: =G97+G95 -> 11.216891 | H99: =H97+H95 -> 15.274956 | I99: =I97+I95 -> 19.557316 | ... P99: =P97+P95 -> 64.909829 | R99: =(J99/D99)^(1/6)-1 -> 0.30473883 | S99: =(P99/J99)^(1/6)-1 -> 0.17574195
A100: Growth rate (%) | C100: =C99/B99-1 -> 0.30900116 | D100: =D99/C99-1 -> 0.33867217 | E100: =E99/D99-1 -> 0.29978954 | F100: =F99/E99-1 -> 0.30755277 | G100: =G99/F99-1 -> 0.3250839 | H100: =H99/G99-1 -> 0.3617816 | I100: =I99/H99-1 -> 0.28035173 | J100: =J99/I99-1 -> 0.25640349 | ... P100: =P99/O99-1 -> 0.14990875
A102: Private cloud (by size of enterprises) (€ m)
A103: Microenterprises (0-9 employees) | B103: 0.001098365 | C103: 0.001551204 | D103: 0.0021988158 | E103: 0.003161823 | F103: 0.0044280627 | G103: 0.0062691897 | H103: 0.0084496822 | I103: 0.010733319 | J103: 0.013520071 | K103: 0.017322685 | L103: 0.020947362 | M103: 0.024179561 | N103: 0.028526859 | O103: 0.033885115 | P103: 0.03947404 | R103: =(J103/D103)^(1/6)-1 -> 0.35352107 | S103: =(P103/J103)^(1/6)-1 -> 0.19551612
A104: Growth rate (%) | C104: =C103/B103-1 -> 0.41228463 | D104: =D103/C103-1 -> 0.41748974 | E104: =E103/D103-1 -> 0.43796629 | F104: =F103/E103-1 -> 0.40047774 | G104: =G103/F103-1 -> 0.41578613 | H104: =H103/G103-1 -> 0.34781089 | I104: =I103/H103-1 -> 0.27026309 | J104: =J103/I103-1 -> 0.25963557 | ... P104: =P103/O103-1 -> 0.16493748
A105: SME (10-249 employees) | B105: 3.4617641 | C105: 4.4525354 | D105: 5.7076639 | E105: 7.3239914 | F105: 9.3320842 | G105: 11.9934 | H105: 15.947957 | I105: 20.083178 | J105: 24.614987 | K105: 28.446579 | L105: 32.771288 | M105: 36.127496 | N105: 40.798532 | O105: 46.482533 | P105: 52.035062 | R105: =(J105/D105)^(1/6)-1 -> 0.27582234 | S105: =(P105/J105)^(1/6)-1 -> 0.13287696
A106: Growth rate (%) | C106: =C105/B105-1 -> 0.28620418 | D106: =D105/C105-1 -> 0.28189074 | E106: =E105/D105-1 -> 0.28318548 | F106: =F105/E105-1 -> 0.27418011 | G106: =G105/F105-1 -> 0.28517914 | H106: =H105/G105-1 -> 0.32972777 | I106: =I105/H105-1 -> 0.2592947 | J106: =J105/I105-1 -> 0.225652 | ... P106: =P105/O105-1 -> 0.1194541
A107: Large enterprises (250+ employees) | B107: 12.712218 | C107: 16.312945 | D107: 20.883365 | E107: 26.542987 | F107: 33.369099 | G107: 42.863017 | H107: 56.614023 | I107: 70.203015 | J107: 85.82816 | K107: 98.528319 | L107: 112.70197 | M107: 123.36075 | N107: 138.31805 | O107: 156.46357 | P107: 173.90119 | R107: =(J107/D107)^(1/6)-1 -> 0.26562454 | S107: =(P107/J107)^(1/6)-1 -> 0.12489536
A108: Growth rate (%) | C108: =C107/B107-1 -> 0.28324933 | D108: =D107/C107-1 -> 0.28017139 | E108: =E107/D107-1 -> 0.27101102 | F108: =F107/E107-1 -> 0.25717196 | G108: =G107/F107-1 -> 0.28451225 | H108: =H107/G107-1 -> 0.32081283 | I108: =I107/H107-1 -> 0.24002874 | J108: =J107/I107-1 -> 0.22257085 | ... P108: =P107/O107-1 -> 0.1114484
A109: Public administration | B109: 2.1007353 | C109: 2.7835149 | D109: 3.6769211 | E109: 4.826297 | F109: 6.2600603 | G109: 8.3008937 | H109: 11.026133 | I109: 13.870148 | J109: 17.109648 | K109: 20.475465 | L109: 23.947696 | M109: 26.794348 | N109: 30.701401 | O109: 35.480469 | P109: 40.27757 | R109: =(J109/D109)^(1/6)-1 -> 0.29209008 | S109: =(P109/J109)^(1/6)-1 -> 0.15337455
A110: Growth rate (%) | C110: =C109/B109-1 -> 0.32501934 | D110: =D109/C109-1 -> 0.32096332 | E110: =E109/D109-1 -> 0.31259193 | F110: =F109/E109-1 -> 0.29707315 | G110: =G109/F109-1 -> 0.32600858 | H110: =H109/G109-1 -> 0.32830679 | I110: =I109/H109-1 -> 0.257934 | J110: =J109/I109-1 -> 0.23355911 | ... P110: =P109/O109-1 -> 0.13520399
A111: Total | B111: =B109+B107+B105+B103 -> 18.275815 | C111: =C109+C107+C105+C103 -> 23.550546 | D111: =D109+D107+D105+D103 -> 30.270149 | E111: =E109+E107+E105+E103 -> 38.696438 | F111: =F109+F107+F105+F103 -> 48.965672 | G111: =G109+G107+G105+G103 -> 63.16358 | H111: =H109+H107+H105+H103 -> 83.596563 | I111: =I109+I107+I105+I103 -> 104.16707 | ... P111: =P109+P107+P105+P103 -> 266.25329 | R111: =(J111/D111)^(1/6)-1 -> 0.27092593 | S111: =(P111/J111)^(1/6)-1 -> 0.13047205
A112: Growth rate (%) | C112: =C111/B111-1 -> 0.28861809 | D112: =D111/C111-1 -> 0.28532683 | E112: =E111/D111-1 -> 0.27836957 | F112: =F111/E111-1 -> 0.26537932 | G112: =G111/F111-1 -> 0.28995635 | H112: =H111/G111-1 -> 0.32349311 | I112: =I111/H111-1 -> 0.24606887 | J112: =J111/I111-1 -> 0.22463183 | ... P112: =P111/O111-1 -> 0.11655112
A114: Private cloud spending per capita (by size of enterprises) (€ )
...

Sheet Hungary
A1: Year | B1: 2016 | C1: 2017 | D1: 2018 | E1: 2019 | F1: 2020 | G1: 2021 | H1: 2022 | I1: 2023 | J1: 2024 | K1: 2025e | L1: 2026f | M1: 2027f | N1: 2028f | O1: 2029f | P1: 2030f | R1: CAGR 2019-2024 | S1: CAGR 2025-2030
A2: Total IT market size (€ m) | B2: =B4+B6+B8 -> 2841.1602 | C2: =C4+C6+C8 -> 2880.9095 | D2: =D4+D6+D8 -> 2980.0745 | E2: =E4+E6+E8 -> 3161.2676 | F2: =F4+F6+F8 -> 3231.4135 | G2: =G4+G6+G8 -> 3534.726 | H2: =H4+H6+H8 -> 3788.987 | I2: =I4+I6+I8 -> 4091.6888 | ... P2: =P4+P6+P8 -> 5868.5537 | R2: =(J2/D2)^(1/6)-1 -> 0.06727163 | S2: =(P2/J2)^(1/6)-1 -> 0.0490005
A3: Growth rate (%) | C3: =C2/B2-1 -> 0.013990509 | D3: =D2/C2-1 -> 0.03442143 | E3: =E2/D2-1 -> 0.060801536 | F3: =F2/E2-1 -> 0.022189149 | G3: =G2/F2-1 -> 0.093863726 | H3: =H2/G2-1 -> 0.071932312 | I3: =I2/H2-1 -> 0.079889911 | J3: =J2/I2-1 -> 0.07640156 | ... P3: =P2/O2-1 -> 0.047258577
A4: Software | B4: 588.95646 | C4: 618.37799 | D4: 652.9643 | E4: 693.37724 | F4: 720.76081 | G4: 763.96636 | H4: 811.89817 | I4: 889.8116 | J4: 964.54726 | K4: 1023.7636 | L4: 1083.1756 | M4: 1139.3837 | N4: 1199.5731 | O4: 1262.0846 | P4: 1329.7312 | R4: =(J4/D4)^(1/6)-1 -> 0.067183278 | S4: =(P4/J4)^(1/6)-1 -> 0.054969877
A5: Growth rate (%) | C5: =C4/B4-1 -> 0.049955343 | D5: =D4/C4-1 -> 0.05593071 | E5: =E4/D4-1 -> 0.061891494 | F5: =F4/E4-1 -> 0.039493029 | G5: =G4/F4-1 -> 0.05994437 | H5: =H4/G4-1 -> 0.062740734 | I5: =I4/H4-1 -> 0.095964531 | J5: =J4/I4-1 -> 0.083990428 | ... P5: =P4/O4-1 -> 0.053599145
A6: Hardware | B6: 1368.1529 | C6: 1340.4638 | D6: 1360.8356 | E6: 1446.9223 | F6: 1484.4377 | G6: 1708.662 | H6: 1846.5736 | I6: 1975.7972 | J6: 2126.0431 | K6: 2207.5707 | L6: 2297.1398 | M6: 2383.4956 | N6: 2465.3923 | O6: 2543.7633 | P6: 2628.5457 | R6: =(J6/D6)^(1/6)-1 -> 0.077195178 | S6: =(P6/J6)^(1/6)-1 -> 0.035994008
A7: Growth rate (%) | C7: =C6/B6-1 -> -0.02023832 | D7: =D6/C6-1 -> 0.01519758 | E7: =E6/D6-1 -> 0.063260187 | F7: =F6/E6-1 -> 0.025927745 | G7: =G6/F6-1 -> 0.15104999 | H7: =H6/G6-1 -> 0.080713176 | I7: =I6/H6-1 -> 0.069980224 | J7: =J6/I6-1 -> 0.076043166 | ... P7: =P6/O6-1 -> 0.033329511
A8: Services | B8: 884.05084 | C8: 922.06772 | D8: 966.27462 | E8: 1020.9681 | F8: 1026.2149 | G8: 1062.0976 | H8: 1130.5152 | I8: 1226.08 | J8: 1313.7099 | K8: 1408.6078 | L8: 1500.5954 | M8: 1593.4065 | N8: 1692.6574 | O8: 1797.8816 | P8: 1910.2769 | R8: =(J8/D8)^(1/6)-1 -> 0.052526765 | S8: =(P8/J8)^(1/6)-1 -> 0.064386789
A9: Growth rate (%) | C9: =C8/B8-1 -> 0.043003039 | D9: =D8/C8-1 -> 0.047943224 | E9: =E8/D8-1 -> 0.056602395 | F9: =F8/E8-1 -> 0.0051390833 | G9: =G8/F8-1 -> 0.034966016 | H9: =H8/G8-1 -> 0.064417492 | I9: =I8/H8-1 -> 0.084532051 | J9: =J8/I8-1 -> 0.07147158 | ... P9: =P8/O8-1 -> 0.062515373
A11: Smartphones market size (€ m) | B11: 705.71633 | C11: 643.03269 | D11: 621.63182 | E11: 667.24369 | F11: 606.70365 | G11: 737.95701 | H11: 813.014 | I11: 831.78264 | J11: 865.83319 | K11: 880.30647 | L11: 906.34501 | M11: 931.68328 | N11: 951.78991 | O11: 973.87707 | P11: 998.67813 | R11: =(J11/D11)^(1/6)-1 -> 0.056777356 | S11: =(P11/J11)^(1/6)-1 -> 0.024075286
A12: Growth rate (%) | C12: =C11/B11-1 -> -0.08882272 | D12: =D11/C11-1 -> -0.033281157 | E12: =E11/D11-1 -> 0.073374421 | F12: =F11/E11-1 -> -0.090731536 | G12: =G11/F11-1 -> 0.21633852 | H12: =H11/G11-1 -> 0.10170915 | I12: =I11/H11-1 -> 0.023085261 | J12: =J11/I11-1 -> 0.040936833 | ... P12: =P11/O11-1 -> 0.025466311
A14: Cybersecurity market size (€ m) | B14: 87.707093 | C14: 99.180546 | D14: 110.23411 | E14: 122.97689 | F14: 118.59022 | G14: 125.40649 | H14: 138.8916 | I14: 159.51689 | J14: 173.85971 | K14: 186.08691 | L14: 198.52375 | M14: 207.56227 | N14: 215.96692 | O14: 225.38981 | P14: 234.54884 | R14: =(J14/D14)^(1/6)-1 -> 0.078898253 | S14: =(P14/J14)^(1/6)-1 -> 0.051168624
A15: Growth rate (%) | C15: =C14/B14-1 -> 0.13081556 | D15: =D14/C14-1 -> 0.11144897 | E15: =E14/D14-1 -> 0.11559739 | F15: =F14/E14-1 -> -0.035670654 | G15: =G14/F14-1 -> 0.057477467 | H15: =H14/G14-1 -> 0.1075312 | I15: =I14/H14-1 -> 0.14849917 | J15: =J14/I14-1 -> 0.089914148 | ... P15: =P14/O14-1 -> 0.040636414
A17: Enterprises (by size) (number of enterprises in thousands)
A18: Microenterprises (0-9 employees) | B18: 518.649 | C18: 536.779 | D18: 566.058 | E18: 613.012 | F18: 636.383 | G18: 713.437 | H18: 733.768 | I18: 669.734 | J18: 666.11226 | K18: 668.94351 | L18: 680.40081 | M18: 698.73006 | N18: 710.40499 | O18: 721.71134 | P18: 732.0275 | R18: =(J18/D18)^(1/6)-1 -> 0.027498229 | S18: =(P18/J18)^(1/6)-1 -> 0.01585096
A19: Growth rate (%) | C19: =C18/B18-1 -> 0.034956204 | D19: =D18/C18-1 -> 0.054545726 | E19: =E18/D18-1 -> 0.082949097 | F19: =F18/E18-1 -> 0.038124865 | G19: =G18/F18-1 -> 0.12108117 | H19: =H18/G18-1 -> 0.02849726 | I19: =I18/H18-1 -> -0.087267365 | J19: =J18/I18-1 -> -0.0054077347 | ... P19: =P18/O18-1 -> 0.01429402
A20: SME (10-249 employees) | B20: 31.643 | C20: 32.291 | D20: 32.548 | E20: 33.118 | F20: 31.484 | G20: 33.264833 | H20: 34.144139 | I20: 34.314162 | J20: 34.362028 | K20: 34.481439 | L20: 34.743112 | M20: 35.039786 | N20: 35.188784 | O20: 35.333501 | P20: 35.465611 | R20: =(J20/D20)^(1/6)-1 -> 0.009080346 | S20: =(P20/J20)^(1/6)-1 -> 0.0052824712
A21: Growth rate (%) | C21: =C20/B20-1 -> 0.020478463 | D21: =D20/C20-1 -> 0.007958874 | E21: =E20/D20-1 -> 0.017512597 | F21: =F20/E20-1 -> -0.049338728 | G21: =G20/F20-1 -> 0.056563122 | H21: =H20/G20-1 -> 0.026433487 | I21: =I20/H20-1 -> 0.0049795705 | J21: =J20/I20-1 -> 0.0013949438 | ... P21: =P20/O20-1 -> 0.0037389464
A22: Large enterprises (250+ employees) | B22: 0.881 | C22: 0.935 | D22: 0.941 | E22: 0.961 | F22: 0.929 | G22: 0.97893333 | H22: 0.99667619 | I22: 1.014419 | J22: 1.0166538 | K22: 1.027354 | L22: 1.0399955 | M22: 1.0552248 | N22: 1.0661808 | O22: 1.0764362 | P22: 1.0861191 | R22: =(J22/D22)^(1/6)-1 -> 0.012971547 | S22: =(P22/J22)^(1/6)-1 -> 0.01107659
A23: Growth rate (%) | C23: =C22/B22-1 -> 0.061293984 | D23: =D22/C22-1 -> 0.0064171123 | E23: =E22/D22-1 -> 0.021253985 | F23: =F22/E22-1 -> -0.033298647 | G23: =G22/F22-1 -> 0.053749551 | H23: =H22/G22-1 -> 0.018124684 | I23: =I22/H22-1 -> 0.017802028 | J23: =J22/I22-1 -> 0.0022030218 | ... P23: =P22/O22-1 -> 0.0089952425
A24: Number of all enterprises | B24: =B18+B20+B22 -> 551.173 | C24: =C18+C20+C22 -> 570.005 | D24: =D18+D20+D22 -> 599.547 | E24: =E18+E20+E22 -> 647.091 | F24: =F18+F20+F22 -> 668.796 | G24: =G18+G20+G22 -> 747.68077 | H24: =H18+H20+H22 -> 768.90882 | I24: =I18+I20+I22 -> 705.06258 | ... P24: =P18+P20+P22 -> 768.57923 | R24: =(J24/D24)^(1/6)-1 -> 0.02651777 | S24: =(P24/J24)^(1/6)-1 -> 0.015339066
A25: Growth rate (%) | C25: =C24/B24-1 -> 0.034167131 | D25: =D24/C24-1 -> 0.051827616 | E25: =E24/D24-1 -> 0.079299871 | F25: =F24/E24-1 -> 0.033542423 | G25: =G24/F24-1 -> 0.11795042 | H25: =H24/G24-1 -> 0.028391861 | I25: =I24/H24-1 -> -0.083034858 | J25: =J24/I24-1 -> -0.0050657102 | ... P25: =P24/O24-1 -> 0.01379456
A27: Percentage of enterprises using cloud computing
A28: Percent of microenterprises using cloud computing | B28: 0.056892482 | C28: 0.069435497 | D28: 0.0844961 | E28: 0.10246367 | F28: 0.12373554 | G28: 0.14869193 | H28: 0.17766128 | I28: 0.21087659 | J28: 0.2484258 | K28: 0.29020228 | L28: 0.33586461 | M28: 0.3848165 | N28: 0.43621688 | O28: 0.48902522 | P28: 0.54207967
A29: Percent of SME using cloud computing | B29: 0.11923441 | C29: 0.14461265 | D29: 0.17432338 | E29: 0.20864926 | F29: 0.24770647 | G29: 0.2913828 | H29: 0.33928702 | I29: 0.39072432 | J29: 0.444711 | K29: 0.50003511 | L29: 0.55535836 | M29: 0.60934254 | N29: 0.66077593 | O29: 0.70867519 | P29: 0.75234586
A30: Percent of large enterprises using cloud computing | B30: 0.29506649 | C30: 0.37085728 | D30: 0.45358925 | E30: 0.53896657 | F30: 0.62211732 | G30: 0.69865618 | H30: 0.76553503 | I30: 0.82136614 | J30: 0.86622584 | K30: 0.90117551 | L30: 0.9277558 | M30: 0.94760261 | N30: 0.96221917 | O30: 0.97287507 | P30: 0.98058616
A31: Percent of all enterprises using cloud computing | B31: 0.06085225 | C31: 0.074188745 | D31: 0.08995191 | E31: 0.10854648 | F31: 0.13026383 | G31: 0.15576041 | H31: 0.18560044 | I31: 0.22050781 | J31: 0.25893605 | K31: 0.30136418 | L31: 0.34737207 | M31: 0.39633109 | N31: 0.44755106 | O31: 0.49994938 | P31: 0.55240195
A33: Number of enterprises using cloud computing (thousands)
A34: Number of microenterprises using cloud computing | B34: =B28*B18 -> 29.507229 | C34: =C28*C18 -> 37.271517 | D34: =D28*D18 -> 47.829693 | E34: =E28*E18 -> 62.811458 | F34: =F28*F18 -> 78.743193 | G34: =G28*G18 -> 106.08232 | H34: =H28*H18 -> 130.36216 | I34: =I28*I18 -> 141.23122 | ... P34: =P28*P18 -> 396.81722 | R34: =(J34/D34)^(1/6)-1 -> 0.22981868 | S34: =(P34/J34)^(1/6)-1 -> 0.15693173
A35: Growth rate (%) | C35: =C34/B34-1 -> 0.26313172 | D35: =D34/C34-1 -> 0.28327734 | E35: =E34/D34-1 -> 0.31323146 | F35: =F34/E34-1 -> 0.25364377 | G35: =G34/F34-1 -> 0.34719358 | H35: =H34/G34-1 -> 0.2288773 | I35: =I34/H34-1 -> 0.083375878 | J35: =J34/I34-1 -> 0.17169184 | ... P35: =P34/O34-1 -> 0.12433498
A36: Number of SME using cloud computing | B36: =B29*B20 -> 3.7729345 | C36: =C29*C20 -> 4.6696871 | D36: =D29*D20 -> 5.6738774 | E36: =E29*E20 -> 6.9100463 | F36: =F29*F20 -> 7.7987906 | G36: =G29*G20 -> 9.6928003 | H36: =H29*H20 -> 11.584663 | I36: =I29*I20 -> 13.407378 | ... P36: =P29*P20 -> 26.682406 | R36: =(J36/D36)^(1/6)-1 -> 0.17954031 | S36: =(P36/J36)^(1/6)-1 -> 0.09734887
A37: Growth rate (%) | C37: =C36/B36-1 -> 0.23768041 | D37: =D36/C36-1 -> 0.21504445 | E37: =E36/D36-1 -> 0.21787022 | F37: =F36/E36-1 -> 0.12861627 | G37: =G36/F36-1 -> 0.24285941 | H37: =H36/G36-1 -> 0.19518229 | I37: =I36/H36-1 -> 0.15733858 | J37: =J36/I36-1 -> 0.13975844 | ... P37: =P36/O36-1 -> 0.065592325
A38: Number of large enterprises using cloud computing | B38: =B30*B22 -> 0.25995358 | C38: =C30*C22 -> 0.34675155 | D38: =D30*D22 -> 0.42682749 | E38: =E30*E22 -> 0.51794688 | F38: =F30*F22 -> 0.57794699 | G38: =G30*G22 -> 0.68393782 | H38: =H30*H22 -> 0.76299054 | I38: =I30*I22 -> 0.83320945 | ... P38: =P30*P22 -> 1.0650333 | R38: =(J38/D38)^(1/6)-1 -> 0.12830188 | S38: =(P38/J38)^(1/6)-1 -> 0.032190424
A39: Growth rate (%) | C39: =C38/B38-1 -> 0.33389799 | D39: =D38/C38-1 -> 0.23093172 | E39: =E38/D38-1 -> 0.21348061 | F39: =F38/E38-1 -> 0.11584222 | G39: =G38/F38-1 -> 0.18339195 | H39: =H38/G38-1 -> 0.11558466 | I39: =I38/H38-1 -> 0.092031174 | J39: =J38/I38-1 -> 0.056939305 | ... P39: =P38/O38-1 -> 0.016992627
A40: Number of all enterprises using cloud computing | B40: =B38+B36+B34 -> 33.540117 | C40: =C38+C36+C34 -> 42.287956 | D40: =D38+D36+D34 -> 53.930398 | E40: =E38+E36+E34 -> 70.239451 | F40: =F38+F36+F34 -> 87.11993 | G40: =G38+G36+G34 -> 116.45906 | H40: =H38+H36+H34 -> 142.70981 | I40: =I38+I36+I34 -> 155.47181 | ... P40: =P38+P36+P34 -> 424.56466 | R40: =(J40/D40)^(1/6)-1 -> 0.22432531 | S40: =(P40/J40)^(1/6)-1 -> 0.15200636
A41: Growth rate (%) | C41: =C40/B40-1 -> 0.26081717 | D41: =D40/C40-1 -> 0.27531344 | E41: =E40/D40-1 -> 0.30240928 | F41: =F40/E40-1 -> 0.24032761 | G41: =G40/F40-1 -> 0.33676716 | H41: =H40/G40-1 -> 0.22540755 | I41: =I40/H40-1 -> 0.089426175 | J41: =J40/I40-1 -> 0.16832303 | ... P41: =P40/O40-1 -> 0.12015758
A43: Total cloud computing market size (€ m) | B43: =B55+B111 -> 52.239215 | C43: =C55+C111 -> 66.480665 | D43: =D55+D111 -> 84.622791 | E43: =E55+E111 -> 107.54221 | F43: =F55+F111 -> 134.57261 | G43: =G55+G111 -> 173.57689 | H43: =H55+H111 -> 228.61606 | I43: =I55+I111 -> 284.22129 | ... P43: =P55+P111 -> 840.38772 | R43: =(J43/D43)^(1/6)-1 -> 0.26544051 | S43: =(P43/J43)^(1/6)-1 -> 0.15857368
A44: Growth rate (%) | C44: =C43/B43-1 -> 0.27261991 | D44: =D43/C43-1 -> 0.27289327 | E44: =E43/D43-1 -> 0.27084211 | F44: =F43/E43-1 -> 0.25134696 | G44: =G43/F43-1 -> 0.28983814 | H44: =H43/G43-1 -> 0.31708815 | I44: =I43/H43-1 -> 0.24322538 | J44: =J43/I43-1 -> 0.22259083 | ... P44: =P43/O43-1 -> 0.13548335
A46: Public cloud (by size of enterprises) (€ m)
A47: Microenterprises (0-9 employees) | B47: 4.0127774 | C47: 5.2119002 | D47: 6.7953141 | E47: 8.9383458 | F47: 11.503204 | G47: 14.917975 | H47: 20.061554 | I47: 25.47155 | J47: 31.269206 | K47: 37.944519 | L47: 45.455996 | M47: 54.641161 | N47: 64.629186 | O47: 75.980966 | P47: 88.299815 | R47: =(J47/D47)^(1/6)-1 -> 0.28968769 | S47: =(P47/J47)^(1/6)-1 -> 0.18888676
A48: Growth rate (%) | C48: =C47/B47-1 -> 0.29882613 | D48: =D47/C47-1 -> 0.30380742 | E48: =E47/D47-1 -> 0.31536904 | F48: =F47/E47-1 -> 0.28694997 | G48: =G47/F47-1 -> 0.29685389 | H48: =H47/G47-1 -> 0.34479075 | I48: =I47/H47-1 -> 0.26966979 | J48: =J47/I47-1 -> 0.22761303 | ... P48: =P47/O47-1 -> 0.16213072
A49: SME (10-249 employees) | B49: 27.924001 | C49: 34.487764 | D49: 42.661007 | E49: 52.667327 | F49: 64.061977 | G49: 79.826324 | H49: 101.93774 | I49: 124.13711 | J49: 148.37254 | K49: 167.24963 | L49: 190.27278 | M49: 217.06247 | N49: 243.46996 | O49: 271.20994 | P49: 298.35484 | R49: =(J49/D49)^(1/6)-1 -> 0.23089329 | S49: =(P49/J49)^(1/6)-1 -> 0.1234746
A50: Growth rate (%) | C50: =C49/B49-1 -> 0.23505811 | D50: =D49/C49-1 -> 0.23698965 | E50: =E49/D49-1 -> 0.23455424 | F50: =F49/E49-1 -> 0.21635141 | G50: =G49/F49-1 -> 0.24607963 | H50: =H49/G49-1 -> 0.27699409 | I50: =I49/H49-1 -> 0.21777376 | J50: =J49/I49-1 -> 0.19523114 | ... P50: =P49/O49-1 -> 0.10008814
A51: Large enterprises (250+ employees) | B51: 4.9118266 | C51: 6.8705706 | D51: 9.5171321 | E51: 13.058034 | F51: 17.527662 | G51: 24.704154 | H51: 34.904091 | I51: 44.929134 | J51: 57.588752 | K51: 72.339965 | L51: 89.447051 | M51: 110.74262 | N51: 134.65221 | O51: 162.4545 | P51: 193.44267 | R51: =(J51/D51)^(1/6)-1 -> 0.34991139 | S51: =(P51/J51)^(1/6)-1 -> 0.22377742
A52: Growth rate (%) | C52: =C51/B51-1 -> 0.39878117 | D52: =D51/C51-1 -> 0.38520259 | E52: =E51/D51-1 -> 0.3720556 | F52: =F51/E51-1 -> 0.34228943 | G52: =G51/F51-1 -> 0.40943809 | H52: =H51/G51-1 -> 0.41288348 | I52: =I51/H51-1 -> 0.28721685 | J52: =J51/I51-1 -> 0.28176856 | ... P52: =P51/O51-1 -> 0.19074991
A53: Public administration | B53: 2.0469064 | C53: 2.704085 | D53: 3.5817173 | E53: 4.7429792 | F53: 6.1554703 | G53: 8.2870001 | H53: 11.192843 | I53: 14.297882 | J53: 17.956777 | K53: 21.907575 | L53: 26.525382 | M53: 32.210104 | N53: 38.467609 | O53: 45.642839 | P53: 53.511756 | R53: =(J53/D53)^(1/6)-1 -> 0.30824629 | S53: =(P53/J53)^(1/6)-1 -> 0.19960096
A54: Growth rate (%) | C54: =C53/B53-1 -> 0.32105944 | D54: =D53/C53-1 -> 0.32455792 | E54: =E53/D53-1 -> 0.32421932 | F54: =F53/E53-1 -> 0.29780672 | G54: =G53/F53-1 -> 0.3462822 | H54: =H53/G53-1 -> 0.35065073 | I54: =I53/H53-1 -> 0.27741291 | J54: =J53/I53-1 -> 0.25590468 | ... P54: =P53/O53-1 -> 0.17240201
A55: Total | B55: =B53+B51+B49+B47 -> 38.895511 | C55: =C53+C51+C49+C47 -> 49.27432 | D55: =D53+D51+D49+D47 -> 62.55517 | E55: =E53+E51+E49+E47 -> 79.406686 | F55: =F53+F51+F49+F47 -> 99.248313 | G55: =G53+G51+G49+G47 -> 127.73545 | H55: =H53+H51+H49+H47 -> 168.09623 | I55: =I53+I51+I49+I47 -> 208.83568 | ... P55: =P53+P51+P49+P47 -> 633.60908 | R55: =(J55/D55)^(1/6)-1 -> 0.26405499 | S55: =(P55/J55)^(1/6)-1 -> 0.16366257
A56: Growth rate (%) | C56: =C55/B55-1 -> 0.2668382 | D56: =D55/C55-1 -> 0.26952885 | E56: =E55/D55-1 -> 0.26938646 | F56: =F55/E55-1 -> 0.2498735 | G56: =G55/F55-1 -> 0.28702896 | H56: =H55/G55-1 -> 0.31597163 | I56: =I55/H55-1 -> 0.24235786 | J56: =J55/I55-1 -> 0.22195249 | ... P56: =P55/O55-1 -> 0.14104539
A58: Public cloud spending per capita (by size of enterprises) (€ )
A59: Microenterprises (0-9 employees) | B59: =(B47*1000000)/(B34*1000) -> 135.99303 | C59: =(C47*1000000)/(C34*1000) -> 139.83601 | D59: =(D47*1000000)/(D34*1000) -> 142.07313 | E59: =(E47*1000000)/(E34*1000) -> 142.30439 | F59: =(F47*1000000)/(F34*1000) -> 146.08506 | G59: =(G47*1000000)/(G34*1000) -> 140.6264 | H59: =(H47*1000000)/(H34*1000) -> 153.89093 | I59: =(I47*1000000)/(I34*1000) -> 180.35353 | ... P59: =(P47*1000000)/(P34*1000) -> 222.52012 | R59: =(J59/D59)^(1/6)-1 -> 0.048681161 | S59: =(P59/J59)^(1/6)-1 -> 0.027620493
A60: Growth rate (%) | C60: =C59/B59-1 -> 0.028258657 | D60: =D59/C59-1 -> 0.01599816 | E60: =E59/D59-1 -> 0.0016277306 | F60: =F59/E59-1 -> 0.026567513 | G60: =G59/F59-1 -> -0.037366338 | H60: =H59/G59-1 -> 0.094324669 | I60: =I59/H59-1 -> 0.17195686 | J60: =J59/I59-1 -> 0.047726871 | ... P60: =P59/O59-1 -> 0.033616087
A61: SME (10-249 employees) | B61: =(B49*1000000)/(B36*1000) -> 7401.136 | C61: =(C49*1000000)/(C36*1000) -> 7385.455 | D61: =(D49*1000000)/(D36*1000) -> 7518.8454 | E61: =(E49*1000000)/(E36*1000) -> 7621.8486 | F61: =(F49*1000000)/(F36*1000) -> 8214.3476 | G61: =(G49*1000000)/(G36*1000) -> 8235.6307 | H61: =(H49*1000000)/(H36*1000) -> 8799.3705 | I61: =(I49*1000000)/(I36*1000) -> 9258.8657 | ... P61: =(P49*1000000)/(P36*1000) -> 11181.707 | R61: =(J61/D61)^(1/6)-1 -> 0.04353644 | S61: =(P61/J61)^(1/6)-1 -> 0.023808046
A62: Growth rate (%) | C62: =C61/B61-1 -> -0.0021187245 | D62: =D61/C61-1 -> 0.018061226 | E62: =E61/D61-1 -> 0.013699342 | F62: =F61/E61-1 -> 0.077736911 | G62: =G61/F61-1 -> 0.0025909767 | H62: =H61/G61-1 -> 0.068451314 | I62: =I61/H61-1 -> 0.0522191 | J62: =J61/I61-1 -> 0.048670575 | ... P62: =P61/O61-1 -> 0.032372437
A63: Large enterprises (250+ employees) | B63: =(B51*1000000)/(B38*1000) -> 18895.015 | C63: =(C51*1000000)/(C38*1000) -> 19814.102 | D63: =(D51*1000000)/(D38*1000) -> 22297.374 | E63: =(E51*1000000)/(E38*1000) -> 25211.146 | F63: =(F51*1000000)/(F38*1000) -> 30327.455 | G63: =(G51*1000000)/(G38*1000) -> 36120.468 | H63: =(H51*1000000)/(H38*1000) -> 45746.427 | I63: =(I51*1000000)/(I38*1000) -> 53922.977 | ... P63: =(P51*1000000)/(P38*1000) -> 181630.63 | R63: =(J63/D63)^(1/6)-1 -> 0.19640977 | S63: =(P63/J63)^(1/6)-1 -> 0.18561207
A64: Growth rate (%) | C64: =C63/B63-1 -> 0.048641786 | D64: =D63/C63-1 -> 0.12532853 | E64: =E63/D63-1 -> 0.13067781 | F64: =F63/E63-1 -> 0.20293838 | G64: =G63/F63-1 -> 0.19101545 | H64: =H63/G63-1 -> 0.26649598 | I64: =I63/H63-1 -> 0.17873636 | J64: =J63/I63-1 -> 0.21271728 | ... P64: =P63/O63-1 -> 0.17085402
A65: Total | B65: =(B55*1000000)/(B40*1000) -> 1159.6713 | C65: =(C55*1000000)/(C40*1000) -> 1165.2093 | D65: =(D55*1000000)/(D40*1000) -> 1159.9241 | E65: =(E55*1000000)/(E40*1000) -> 1130.5141 | F65: =(F55*1000000)/(F40*1000) -> 1139.2148 | G65: =(G55*1000000)/(G40*1000) -> 1096.8271 | H65: =(H55*1000000)/(H40*1000) -> 1177.8884 | I65: =(I55*1000000)/(I40*1000) -> 1343.2382 | ... P65: =(P55*1000000)/(P40*1000) -> 1492.3736 | R65: =(J65/D65)^(1/6)-1 -> 0.032450267 | S65: =(P65/J65)^(1/6)-1 -> 0.010118178
A66: Growth rate (%) | C66: =C65/B65-1 -> 0.0047754959 | D66: =D65/C65-1 -> -0.0045358191 | E66: =E65/D65-1 -> -0.025355178 | F66: =F65/E65-1 -> 0.0076962626 | G66: =G65/F65-1 -> -0.037207824 | H66: =H65/G65-1 -> 0.073905273 | I66: =I65/H65-1 -> 0.1403782 | J66: =J65/I65-1 -> 0.045902941 | ... P66: =P65/O65-1 -> 0.018647204
A68: Public cloud (by model) (€ m)
A69: SaaS | B69: 25.400863 | C69: 32.013107 | D69: 40.024871 | E69: 50.504782 | F69: 62.973946 | G69: 80.05508 | H69: 103.81678 | I69: 128.27986 | J69: 155.31548 | K69: 180.97264 | L69: 211.11642 | M69: 247.25036 | N69: 285.20156 | O69: 327.2453 | P69: 371.31576 | R69: =(J69/D69)^(1/6)-1 -> 0.25356676 | S69: =(P69/J69)^(1/6)-1 -> 0.1563468
